Workbook

Sheet Code Dumps to help
B2: Starting party | C2: public enum PartyLayoutType implements ChanceHaver { Basic(RarityUtils.IGNORED_RARITY, new HeroCol[]{HeroCol.orange, HeroCol.yellow, HeroCol.grey, HeroCol.red, HeroCol.blue}), Greens(1.0F, new HeroCol[]{HeroCol.green, HeroCol.green, HeroCol.grey, HeroCol.orange, HeroCol.yellow}), Force(1.0F, new HeroCol[]{HeroCol.yellow, HeroCol.yellow, HeroCol.orange, HeroCol.grey, HeroCol.grey}), Magical(0.8F, new HeroCol[]{HeroCol.red, HeroCol.red, HeroCol.blue, HeroCol.green, HeroCol.orange}), Flex(0.7F, new HeroCol[]{HeroCol.green, HeroCol.yellow, null, HeroCol.blue, HeroCol.red}), Mountain(0.3F, new HeroCol[]{HeroCol.blue, HeroCol.blue, HeroCol.grey, HeroCol.grey, HeroCol.green}), Defensive(0.2F, new HeroCol[]{HeroCol.red, HeroCol.red, HeroCol.grey, HeroCol.grey, HeroCol.yellow}), RNG(0.2F, new HeroCol[]{null, null, null, null, null}), Strays(0.1F, new HeroCol[]{HeroCol.grey, HeroCol.orange, HeroCol.orange, null, null}), Cisab(0.1F, new HeroCol[]{HeroCol.blue, HeroCol.red, HeroCol.grey, HeroCol.yellow, HeroCol.orange}), Rush(0.05F, new HeroCol[]{HeroCol.blue, HeroCol.blue, HeroCol.orange, HeroCol.grey, HeroCol.yellow}), Surrounded(GAR(), new HeroCol[]{null, null, HeroCol.red, null, null}), DMLS(GAR(), new HeroCol[]{HeroCol.red, HeroCol.red, HeroCol.grey, HeroCol.red, HeroCol.red}), Sunset(GAR(), new HeroCol[]{HeroCol.blue, HeroCol.orange, HeroCol.yellow, null, HeroCol.green}), CornCob(GAR(), new HeroCol[]{HeroCol.yellow, HeroCol.yellow, HeroCol.yellow, HeroCol.yellow, HeroCol.yellow}), Beach(GAR(), new HeroCol[]{HeroCol.blue, HeroCol.blue, HeroCol.yellow, HeroCol.yellow, HeroCol.yellow}), Sword(GAR(), new HeroCol[]{HeroCol.orange, HeroCol.orange, HeroCol.grey, HeroCol.grey, HeroCol.grey}), LampPost(GAR(), new HeroCol[]{null, HeroCol.yellow, HeroCol.grey, HeroCol.grey, HeroCol.grey});
B3: Zones and enemies | C3: public enum Zone { Forest(0, new String[]{"archer", "goblin", "boar", "rat", "wolf", "grandma", "thorn", "seed", "bee", "log", "chest"}), Dungeon(1, new String[]{"shade", "snake", "goblin", "quartz", "ogre", "slate", "slimer", "cyclops", "warchief", "dragon egg", "chest", "Illusion", "sudul", "bandit", "barrel", "militia", "fountain", "blind"}), Catacombs(2, new String[]{"shade", "zombie", "z0mbie", "bones", "wizz", "fanatic", "sniper", "imp", "grave", "quartz", "ghost", "slimer", "spiker", "sudul", "chest", "Illusion", "banshee", "militia", "Carrier", "fountain"}), Lair(3, new String[]{"chomp", "basilisk", "sniper", "demon", "ghost", "alpha", "blind", "ogre", "spiker", "slate", "troll", "caw", "snake", "cyclops", "warchief", "caw egg", "hydra", "gnoll", "dragon egg", "bandit", "thorn", "Carrier", "log", "chest"}), Pit(4, new String[]{"chomp", "demon", "sniper", "zombie", "z0mbie", "wizz", "basilisk", "spiker", "troll", "caw", "hydra", "fanatic", "dragon egg", "wisp", "banshee", "barrel", "shade"}), Nightmare(5, new String[]{"deathsigil", "decaysigil", "painsigil", "z0mbie", "x2.basilisk", "x2.basalt", "x2.lich", "x2.goblin", "x2.inevitable", "x3.hexia", "x3.alpha", "x3.warchief", "x3.log", "x3.shade", "x4.dragon egg", "x4.sniper", "x4.snake", "x5.wolf", "x5.the hand", "x6.sudul", "x6.dragon", "x7.bones", "x8.illusion", "x8.troll king", "x9.thorn", "x9.slate"}), Snow(-1, new String[]{"archer", "goblin", "boar", "rat", "wolf", "grandma", "thorn", "seed", "bee", "log"}), Ice(-1, new String[]{"archer", "goblin", "boar", "rat", "wolf", "grandma", "thorn", "seed", "bee", "log"}), All(-1, MonsterTypeLib.stringArray(MonsterTypeLib.getAllValidMonsters()));
B4: Items part 1 | C4: private static List<ItBill> makeOneToFive() { return Arrays.asList((new ItBill(1, "Arrow")).trigger(new AffectSides(new TypeCondition(EffType.Damage), new AffectSideEffect[]{new ReplaceWith(new EntSide[]{ESB.headshot.val(2)})})), (new ItBill(1, "Memory")).trigger(new AffectSides(SpecificSidesType.Left, new AffectSideEffect[]{new ReturnToInnate()})), (new ItBill(1, "Balisong")).trigger(new AffectSides(SpecificSidesType.Left, new AffectSideEffect[]{new ReplaceWith(new EntSide[]{ESB.dmgCantrip.val(1)})})), (new ItBill(1, "Corset")).trigger(new AffectSides(SpecificSidesType.LeftTwo, new AffectSideEffect[]{new AffectByIndex(new AffectSideEffect[]{new ReplaceWithBlank(ChoosableType.Item), new FlatBonus(1)})})), (new ItBill(1, "Tankard")).trigger(SpecificSidesType.Middle, new AddKeyword(new Keyword[]{Keyword.acidic})), (new ItBill(1, "Doll")).trigger(new AffectSides(SpecificSidesType.Left, new AffectSideEffect[]{new CopyBaseFromHeroAbove(true)})).trigger(new AffectSides(SpecificSidesType.RightFive, new AffectSideEffect[]{new FlatBonus(-1)})), (new ItBill(1, "Wand of Wand")).trigger(new AffectSides(SpecificSidesType.Middle, new AffectSideEffect[]{new ReplaceWith(new EntSide[]{ESB.wandOfWand.val(1)})})), (new ItBill(1, "Sorcery Notes")).trigger(new AffectSides(SpecificSidesType.LeftTwo, new AffectSideEffect[]{new ReplaceWith(new EntSide[]{ESB.manaCantrip.val(1), ESB.blankItem})})), (new ItBill(1, "Quiver")).trigger(new AffectSides(SpecificSidesType.RightFive, new AffectSideEffect[]{new ReplaceWith(new EntSide[]{ESB.arrow.val(1)})})), (new ItBill(1, "Revive Potion")).trigger(new AffectSides(SpecificSidesType.Right, new AffectSideEffect[]{new ReplaceWith(new EntSide[]{ESB.potionRevive.val(5)})})), (new ItBill(1, "Courage Potion")).trigger(new AffectSides(SpecificSidesType.Left, new AffectSideEffect[]{new AddKeyword(new Keyword[]{Keyword.potion}), new FlatBonus(3)})), (new ItBill(1, "Pendulum")).trigger(new AffectSides(new AffectSideEffect[]{new SwapSides(SpecificSidesType.Left, SpecificSidesType.Middle)})), (new ItBill(1, "Tattered Robes")).trigger(new AffectSides(SpecificSidesType.RightThree, new AffectSideEffect[]{new ReplaceWith(new EntSide[]{ESB.mana.val(1), ESB.mana.val(1), ESB.mana.val(1)})})).trigger(new TriggerPersonalToGlobal(new GlobalMaxMana(1))), (new ItBill(1, "Leather Vest")).trigger(new MaxHP(1)), (new ItBill(1, "Healing Wand")).trigger(new AffectSides(SpecificSidesType.RightMost, new AffectSideEffect[]{new ReplaceWith(new EntSide[]{ESB.wandHeal.val(4)})})), (new ItBill(1, "Castor Root")).trigger(new AffectSides(new TypeCondition(EffType.Blank), new AffectSideEffect[]{new ReplaceWith(new EntSide[]{ESB.heal.val(1)})})), (new ItBill(1, "Seedling")).trigger(new AffectSides(SpecificSidesType.Left, new AffectSideEffect[]{new ReplaceWith(new EntSide[]{ESB.damageGrowth.val(2)})})), (new ItBill(1, "Reagents")).trigger(new AffectSides(SpecificSidesType.RightTwo, new AffectSideEffect[]{new ReplaceWith(new EntSide[]{ESB.blankItem, ESB.healRegen.val(1)})})), (new ItBill(1, "Rusty Plate")).trigger(new AffectSides(SpecificSidesType.Middle, new AffectSideEffect[]{new ReplaceWith(new EntSide[]{ESB.blankItem})})).trigger(new MaxHP(3)), (new ItBill(1, "Anchor")).trigger(new StartOfCombat((new EffBill()).shield(2).self().bEff())), (new ItBill(1, "Big Shield")).trigger(new AffectSides(SpecificSidesType.Left, new AffectSideEffect[]{new ReplaceWith(new EntSide[]{ESB.shield.val(4)})})), (new ItBill(1, "Cloak")).trigger(new AffectSides(SpecificSidesType.Middle, new AffectSideEffect[]{new ReplaceWith(new EntSide[]{ESB.dodge})})), (new ItBill(1, "Scar")).trigger(new EmptyPips(5)), (new ItBill(1, "Ballet Shoes")).trigger(new AffectSides(new AffectSideEffect[]{new SwapSides(SpecificSidesType.Left, SpecificSidesType.RightMost)})), (new ItBill(1, "Titanbane Potion")).trigger(new AffectSides(SpecificSidesType.Middle, new AffectSideEffect[]{new AddKeyword(new Keyword[]{Keyword.dispel, Keyword.potion})})), (new ItBill(1, "Change of Heart")).trigger(new AffectSides(new TypeCondition(EffType.Heal), new AffectSideEffect[]{new ChangeType(ESB.shield, "basic shield")})), (new ItBill(1, "Emerald Shard")).trigger(new CopyAlliedItems(2)), (new ItBill(1, "Barkskin")).trigger(new ShieldImmunity()).trigger(new MaxHP(2)), (new ItBill(1, "Knife Bag")).trigger(new AffectSides(new TypeCondition(EffType.Blank), new AffectSideEffect[]{new ReplaceWith(new EntSide[]{ESB.dmgCantrip.val(1).withKeyword(Keyword.pain)})})), (new ItBill(1, "Big Heart")).trigger(new AffectSides(SpecificSidesType.Middle, new AffectSideEffect[]{new ReplaceWith(new EntSide[]{ESB.heal.val(7)})})), (new ItBill(1, "Compass")).trigger(new AffectSides(new AffectSideEffect[]{new Rotate()})), (new ItBill(1, "Bone Charm")).trigger(new AvoidDeathPenalty()), (new ItBill(1, "Infused Herbs")).trigger(new AffectSides(SpecificSidesType.Bot, new AffectSideEffect[]{new ReplaceWith(new EntSide[]{ESB.infusedHerbs.val(2)})})), new ItBill(1, (new SpellBill()).title("Poultice").cost(1).eff((new EffBill()).heal(2).keywords(new Keyword[]{Keyword.singleCast}))), (new ItBill(1, "Cheating Sleeves")).trigger(new AffectSides(SpecificSidesType.Wings, new AffectSideEffect[]{new AddKeyword(new Keyword[]{Keyword.quin})})), (new ItBill(1, "Copper Ring")).trigger(new EmptyPips(1)).trigger(new TriggerPersonalToGlobal(new GlobalMaxMana(1))), (new ItBill(1, "Wolf Ears")).trigger(new MaxHpSet(6)), (new ItBill(1, "Basilisk Scale")).trigger(new StartPetrified(1)).trigger(new AffectSides(SpecificSidesType.Top, new AffectSideEffect[]{new FlatBonus(3)})), (new ItBill(1, "Glass Helm")).trigger(new MaxHP(3)).trigger(new Permadeath()), (new ItBill(1, "Iron Heart")).trigger(new AffectSides(new AffectSideEffect[]{new AddKeyword(new Keyword[]{Keyword.exert}), new FlatBonus(1)})), (new ItBill(1, "Bowl")).trigger(new AffectSides(SpecificSidesType.Column, new AffectSideEffect[]{new ReturnToInnate()})), (new ItBill(1, "Coin")).trigger(new AffectSides(SpecificSidesType.Left, new AffectSideEffect[]{new FlatBonus(4)})).trigger(new TriggerPersonalToGlobal(new GlobalBonusRerolls(-1))), (new ItBill(1, "Trowel")).trigger(new AffectSides(SpecificSidesType.Left, new AffectSideEffect[]{new ReplaceWith(new EntSide[]{ESB.resurrect.val(1)})})), (new ItBill(1, "Doom Blade")).trigger(new AffectSides(new TypeCondition(EffType.Blank), new AffectSideEffect[]{new ReplaceWith(new EntSide[]{ESB.dmgDeath.val(3)})})), (new ItBill(1, "Tincture")).trigger(new AffectSides(SpecificSidesType.RightMost, new AffectSideEffect[]{new AddKeyword(new Keyword[]{Keyword.cleanse})})), (new ItBill(1, "Whey")).trigger(new AffectSides(SpecificSidesType.Left, new AffectSideEffect[]{new AddKeyword(new Keyword[]{Keyword.vitality})})), (new ItBill(1, "Necromancer Tome")).trigger(new TriggerPersonalToGlobal(new GlobalAllowDeadHeroSpells())).trigger(new AffectSides(SpecificSidesType.Left, new AffectSideEffect[]{new ReplaceWith(new EntSide[]{ESB.manaPain.val(3)})})), (new ItBill(1, "Clumsy Shoes")).trigger(new AffectSides(new TargetedCondition(), new AffectSideEffect[]{new AddKeyword(new Keyword[]{Keyword.heavy, Keyword.eliminate}), new FlatBonus(1)})), new ItBill(2, (new SpellBill()).cost(2).title("Wings").eff((new EffBill()).heal(3).targetType(TargetingType.TopAndBot))), (new ItBill(2, "Needle")).trigger(new AffectSides(new TargetedCondition(), new AffectSideEffect[]{new AddKeyword(new Keyword[]{Keyword.picky}), new FlatBonus(2)})), (new ItBill(2, "Ice Cube")).trigger(new AffectSides(SpecificSidesType.Left, new AffectSideEffect[]{new AddKeyword(new Keyword[]{Keyword.stasis})})), (new ItBill(2, "Worn Arms")).trigger(new AffectSides(SpecificSidesType.Wings, new AffectSideEffect[]{new ReplaceWith(new EntSide[]{ESB.dmg.val(2), ESB.shield.val(2)})})), (new ItBill(2, "Foil")).trigger(new AffectSides(SpecificSidesType.Right, new AffectSideEffect[]{new ReplaceWith(new EntSide[]{ESB.dmg.val(0).withKeyword(Keyword.skill)})})), (new ItBill(2, "Kilt")).trigger(new CopySide(SpecificSidesType.Right, SpecificSidesType.RightMost)), (new ItBill(2, "Static Tome")).trigger(new AffectSides(SpecificSidesType.Wings, new AffectSideEffect[]{new ReplaceWith(new EntSide[]{ESB.manaPair.val(1)})})), (new ItBill(2, "Polearm")).trigger(new AffectSides(new TypeCondition(EffType.Damage), new AffectSideEffect[]{new ChangeToMyPosition(SpecificSidesType.Top)})), (new ItBill(2, "Flickering Blade")).trigger(new AffectSides(SpecificSidesType.RightMost, new AffectSideEffect[]{new ReplaceWith(new EntSide[]{ESB.dmgCopycat.val(1)})})), (new ItBill(2, "Origami")).trigger(new AffectSides(new AffectSideEffect[]{new Flip()})), (new ItBill(2, "Statuette")).trigger(new AffectSides(SpecificSidesType.Row, new AffectSideEffect[]{new ReplaceWith(new EntSide[]{ESB.blankItem})})).trigger(new MaxHP(6)), (new ItBill(2, "Spinach")).trigger(new StartOfCombat((new EffBill()).heal(3).self().bEff())), (new ItBill(2, "Buckler")).trigger(new AffectSides(SpecificSidesType.Middle, new AffectSideEffect[]{new ReplaceWith(new EntSide[]{ESB.shield.val(3).withKeyword(Keyword.bloodlust)})})), (new ItBill(2, "Sapphire")).trigger(new AffectSides(SpecificSidesType.Middle, new AffectSideEffect[]{new ReplaceWith(new EntSide[]{ESB.mana.val(2)})})), (new ItBill(2, "Ace of Spades")).trigger(new AffectSides(SpecificSidesType.All, new AffectSideEffect[]{new AffectByIndex(new AffectSideEffect[]{new FlatBonus(2), new FlatBonus(-2), new FlatBonus(-2), new FlatBonus(-2), new FlatBonus(-2), new FlatBonus(-2)})})), (new ItBill(2, "Garnet")).trigger(new IncomingEffBonus(1, new EffType[]{EffType.Heal})), (new ItBill(2, "Powdered Mana")).trigger(new AffectSides(new TypeCondition(EffType.Blank), new AffectSideEffect[]{new ReplaceWith(new EntSide[]{ESB.mana.val(1)})})), (new ItBill(2, "Burning Blade")).trigger(new AffectSides(SpecificSidesType.Left, new AffectSideEffect[]{new ReplaceWith(new EntSide[]{ESB.dmg.val(4)})})).trigger(new MaxHP(-2)), (new ItBill(2, "Citrine Ring")).trigger(new AffectSides(SpecificSidesType.RightMost, new AffectSideEffect[]{new FlatBonus(1)})), (new ItBill(2, "Big Hammer")).trigger(new AffectSides(SpecificSidesType.LeftTwo, new AffectSideEffect[]{new ReplaceWith(new EntSide[]{ESB.dmgHeavy.val(5), ESB.blankItem})})), (new ItBill(2, "Autumn Leaf")).trigger(new AffectSides(SpecificSidesType.RightMost, new AffectSideEffect[]{new AddKeyword(new Keyword[]{Keyword.growth})})), (new ItBill(2, "Blessed Water")).trigger(new AffectSides(SpecificSidesType.Middle, new AffectSideEffect[]{new ReplaceWith(new EntSide[]{ESB.healVitality.val(3)})})), (new ItBill(2, "Blessed Ring")).trigger(new AffectSides(SpecificSidesType.RightMost, new AffectSideEffect[]{new ReplaceWith(new EntSide[]{ESB.shieldRescue.val(1)})})), (new ItBill(2, "Twin Daggers")).trigger(new AffectSides(SpecificSidesType.Wings, new AffectSideEffect[]{new ReplaceWith(new EntSide[]{ESB.dmgCantrip.val(1)})})), (new ItBill(2, "Rain of Arrows")).trigger(new AffectSides(SpecificSidesType.Top, new AffectSideEffect[]{new ReplaceWith(new EntSide[]{ESB.arrowDuplicate.val(1)})})), (new ItBill(2, "Liqueur")).trigger(new AffectSides(new AffectSideEffect[]{new SwapSides(SpecificSidesType.Top, SpecificSidesType.RightMost)})).trigger(new TriggerPersonalToGlobal(new GlobalMaxMana(2))), (new ItBill(2, "Peaked Cap")).trigger(new CopySide(SpecificSidesType.Middle, SpecificSidesType.Left)), (new ItBill(2, "Sapphire Skull")).trigger(new OnDeathEffect((new EffBill()).mana(2).bEff(), new ManaGainEvent(2, "Sapphire Skull"))), (new ItBill(2, "First aid Kit")).trigger(new EquipRestrictCol(HeroCol.orange)).trigger(new AffectSides(SpecificSidesType.Bot, new AffectSideEffect[]{new ReplaceWith(new EntSide[]{ESB.healCleanse.val(2)})})), (new ItBill(2, "Friendship Bracelet")).trigger(new EmptyPips(2)).trigger(new TriggerPersonalToGlobal(new GlobalFleeAt(5), "friendship")), (new ItBill(2, "Clumsy Hammer")).trigger(new AffectSides(SpecificSidesType.Top, new AffectSideEffect[]{new ReplaceWith(new EntSide[]{ESB.dmgHeavy.val(4).withKeyword(Keyword.eliminate)})})), (new ItBill(2, "Tower Shield")).trigger(new AffectSides(SpecificSidesType.Middle, new AffectSideEffect[]{new ReplaceWith(new EntSide[]{ESB.shield.val(7).withKeyword(Keyword.heavy)})})), (new ItBill(2, "Square Wheel")).trigger(new AffectSides(SpecificSidesType.RightThree, new AffectSideEffect[]{new ReplaceWith(new EntSide[]{ESB.rerollCantrip.val(1), ESB.blankItem, ESB.blankItem})})), (new ItBill(2, "Silver Imp")).confirmed().trigger(new AffectSides(SpecificSidesType.Wings, new AffectSideEffect[]{new ReplaceWith(new EntSide[]{ESB.rerollCantrip.val(1).withKeyword(Keyword.pain)})})), (new ItBill(2, "Fletching")).trigger(new AffectSides(SpecificSidesType.Left, new AffectSideEffect[]{new AddKeyword(new Keyword[]{Keyword.ranged})})), (new ItBill(2, "Wandify")).trigger(new AffectSides(SpecificSidesType.RightTwo, new AffectSideEffect[]{new AddKeyword(new Keyword[]{Keyword.singleUse}), new FlatBonus(1)})), (new ItBill(2, "Leather Gloves")).trigger(new CopySide(SpecificSidesType.RightMost, SpecificSidesType.Wings)), new ItBill(2, (new SpellBill()).cost(1).title("remedy").eff((new EffBill()).heal(1).visual(VisualEffectType.HealBasic).keywords(new Keyword[]{Keyword.cleanse, Keyword.singleCast}))), (new ItBill(2, "Golden Thread")).trigger(new EquipRestrictCol(HeroCol.yellow)).trigger(new AffectSides(new NotCondition(new TypeCondition(EffType.Damage)), new AffectSideEffect[]{new FlatBonus(1)})), (new ItBill(2, "Clef")).trigger(new AffectSides(SpecificSidesType.Left, new AffectSideEffect[]{new AddKeyword(new Keyword[]{Keyword.treble})})), (new ItBill(2, "Rejuvenation Wand")).trigger(new AffectSides(SpecificSidesType.Wings, new AffectSideEffect[]{new ReplaceWith(new EntSide[]{ESB.wandHeal.val(10)})})), (new ItBill(2, "Quicksilver")).trigger(new KeepShields()), (new ItBill(2, "Pillow")).confirmed().trigger(new AffectSides(SpecificSidesType.Left, new AffectSideEffect[]{new AddKeyword(new Keyword[]{Keyword.patient})})), (new ItBill(2, "Faint Halo")).confirmed().trigger(new OnRescue((new EffBill()).self().buff(new Buff(new MaxHP(1))).bEff())), (new ItBill(2, "Terrarium")).trigger(new AffectSides(SpecificSidesType.RightTwo, new AffectSideEffect[]{new ReplaceWith(new EntSide[]{ESB.shieldGrowth.val(2), ESB.manaGrowth.val(1)})})), new ItBill(3, (new SpellBill()).title("Flare").cost(4).eff((new EffBill()).damage(5).visual(VisualEffectType.Flame))), (new ItBill(3, "Shortsword")).trigger(new AffectSides(SpecificSidesType.RightTwo, new AffectSideEffect[]{new ReplaceWith(new EntSide[]{ESB.dmg.val(2)})})), (new ItBill(3, "Longbow")).trigger(new AffectSides(SpecificSidesType.Wings, new AffectSideEffect[]{new ReplaceWith(new EntSide[]{ESB.arrow.val(2)})})), (new ItBill(3, "Incense")).trigger(new AffectSides(SpecificSidesType.Top, new AffectSideEffect[]{new AddKeyword(new Keyword[]{Keyword.rite})})), (new ItBill(3, "Juice")).trigger(new AffectSides(SpecificSidesType.Left, new AffectSideEffect[]{new AddKeyword(new Keyword[]{Keyword.selfCleanse})})), (new ItBill(3, "Golden Cup")).trigger(new EmptyPips(100)).trigger(new TriggerPersonalToGlobal(new GlobalMaxMana(100))), (new ItBill(3, "Wristblade")).trigger(new AffectSides(new TypeCondition(EffType.Blank), new AffectSideEffect[]{new ReplaceWith(new EntSide[]{ESB.dmgDouble.val(1)})})), (new ItBill(3, "Ash")).trigger(new AffectSides(SpecificSidesType.MiddleTwo, new AffectSideEffect[]{new AddKeyword(new Keyword[]{Keyword.enduring})})), (new ItBill(3, "Pure Heart Pendant")).trigger(new AffectSides(SpecificSidesType.Middle, new AffectSideEffect[]{new ReplaceWith(new EntSide[]{ESB.healCleanse.val(3)})})), new ItBill(3, (new SpellBill()).cost(3).title("sprout").eff((new EffBill()).heal(3).keywords(new Keyword[]{Keyword.channel}).visual(VisualEffectType.HealBasic))), (new ItBill(3, "Scalpel")).trigger(new EquipRestrictCol(HeroCol.red)).trigger(new AffectSides(new TypeCondition(EffType.Damage), new AffectSideEffect[]{new FlatBonus(1)})), (new ItBill(3, "Lead Boots")).trigger(new AffectSides(new AffectSideEffect[]{new AddKeyword(new Keyword[]{Keyword.sticky}), new FlatBonus(1)})), (new ItBill(3, "Abacus")).trigger(new AffectSides(new AffectSideEffect[]{new Shift()})).trigger(new MaxHP(1)), (new ItBill(3, "Lightning Rod")).trigger(new AffectSides(SpecificSidesType.Left, new AffectSideEffect[]{new ReplaceWith(new EntSide[]{ESB.dmgRangedRampage.val(0)})})), (new ItBill(3, "Iron Pendant")).trigger(new IncomingEffBonus(1, new EffType[]{EffType.Shield})), (new ItBill(3, "Droopy Hat")).trigger(new MaxHP(2)).trigger(new TriggerPersonalToGlobal(new GlobalMaxMana(2))), (new ItBill(3, "Enchanted Shield")).trigger(new StartOfTurnSelf(new Eff[]{(new EffBill()).shield(1).self().bEff()})), (new ItBill(3, "Whetstone")).trigger(new AffectSides(new TypeCondition(EffType.Damage, true), new AffectSideEffect[]{new FlatBonus(1)})), (new ItBill(3, "Pocket Phylactery")).trigger(new AffectSides(SpecificSidesType.LeftTwo, new AffectSideEffect[]{new AddKeyword(new Keyword[]{Keyword.pain})})).trigger(new MaxHP(6)), (new ItBill(3, "Ladder")).trigger(new AffectSides(SpecificSidesType.Middle, new AffectSideEffect[]{new CopyBaseFromHeroAbove(true)})), (new ItBill(3, "Magnet")).trigger(new AffectSides(SpecificSidesType.RightTwo, new AffectSideEffect[]{new AddKeyword(new Keyword[]{Keyword.wham})})), (new ItBill(3, "Blood Chalice")).trigger(new OnOverheal((new EffBill()).shield(1).self())), (new ItBill(3, "Smelly Manure")).trigger(new AffectSides(new SpecificSidesCondition(SpecificSidesType.All), new AffectSideEffect[]{new AffectByIndex(new AffectSideEffect[]{new AddKeyword(new Keyword[]{Keyword.decay}), new AddKeyword(new Keyword[]{Keyword.decay}), new AddKeyword(new Keyword[]{Keyword.growth}), new AddKeyword(new Keyword[]{Keyword.growth}), new AddKeyword(new Keyword[]{Keyword.decay}), new AddKeyword(new Keyword[]{Keyword.decay})})})), (new ItBill(3, "Lich Finger")).trigger(new AffectSides(SpecificSidesType.Left, new AffectSideEffect[]{new AddKeyword(new Keyword[]{Keyword.manaGain, Keyword.death})})), (new ItBill(3, "Unholy Strength")).trigger(new ShieldImmunity()).trigger(new HealImmunity()).trigger(new AffectSides(SpecificSidesType.Row, new AffectSideEffect[]{new FlatBonus(1)})), (new ItBill(3, "Three of a Kind")).trigger(new AffectSides(SpecificSidesType.RightMost, new AffectSideEffect[]{new AddKeyword(new Keyword[]{Keyword.trio})})), (new ItBill(3, "Clover")).trigger(new AffectSides(SpecificSidesType.LeftTwo, new AffectSideEffect[]{new FlatBonus(new int[]{1, -2})})), (new ItBill(3, "Diving Suit")).trigger(new AffectSides(SpecificSidesType.RightTwo, new AffectSideEffect[]{new CopyBaseFromHeroAbove(false)})), (new ItBill(3, "Poem")).trigger(new AffectSides(new TypeCondition(EffType.Damage), new AffectSideEffect[]{new AddKeyword(new Keyword[]{Keyword.alliteration})})), (new ItBill(3, "Syringe")).trigger(new PersonalConditionLink(new SnapshotCondition(SnapshotConditionType.OrFewerHeroes, 2), new AffectSides(new AffectSideEffect[]{new AddKeyword(new Keyword[]{Keyword.cantrip})}))), (new ItBill(3, "Aegis")).trigger(new AffectSides(SpecificSidesType.Middle, new AffectSideEffect[]{new ReplaceWith(new EntSide[]{ESB.shieldDuplicate.val(1).withKeyword(Keyword.steel)})})), (new ItBill(3, "Duvet")).trigger(new AffectSides(SpecificSidesType.RightThree, new AffectSideEffect[]{new AddKeyword(new Keyword[]{Keyword.patient})})), (new ItBill(3, "Siphon")).trigger(new AffectSides(new TypeCondition(EffType.Mana), new AffectSideEffect[]{new AddKeyword(new Keyword[]{Keyword.pain}), new FlatBonus(1)})), (new ItBill(3, "Ritual Dagger")).trigger(new AffectSides(SpecificSidesType.RightMost, new AffectSideEffect[]{new ReplaceWith(new EntSide[]{ESB.resurrect.val(4).withKeyword(Keyword.death)})})), (new ItBill(3, "Harpoon")).trigger(new AffectSides(SpecificSidesType.RightMost, new AffectSideEffect[]{new ReplaceWith(new EntSide[]{ESB.dmgVuln.val(1)})})), (new ItBill(3, "Wild Seeds")).trigger(new AffectSides(SpecificSidesType.LeftTwo, new AffectSideEffect[]{new AddKeyword(new Keyword[]{Keyword.undergrowth})})), (new ItBill(3, "Mana Bomb")).trigger(new AffectSides(SpecificSidesType.RightMost, new AffectSideEffect[]{new ReplaceWith(new EntSide[]{ESB.manaBomb.val(0)})})), (new ItBill(3, "Viscera")).trigger(new AffectSides(SpecificSidesType.Middle, new AffectSideEffect[]{new ReplaceWith(new EntSide[]{ESB.dmgFleshPain.val(0)})})), new ItBill(3, (new SpellBill()).cost(3).title("heat").eff((new EffBill()).keywords(new Keyword[0]).group().heal(3).keywords(new Keyword[]{Keyword.cleanse}).restrict(StateConditionType.HasShields))), (new ItBill(4, "Relic")).trigger(new AddKeyword(new Keyword[]{Keyword.swapTerminal})), (new ItBill(4, "Corruption")).trigger(new AffectSides(new TypeCondition(EffType.Heal), new AffectSideEffect[]{new AddKeyword(new Keyword[]{Keyword.evil}), new FlatBonus(1)})), (new ItBill(4, "Pulley")).trigger(new AffectSides(new AffectSideEffect[]{new Shift(false)})).trigger(new ItemSlots(2)), new ItBill(4, (new SpellBill()).cost(4).title("Mark").eff((new EffBill()).damage(2).keywords(new Keyword[]{Keyword.vulnerable}).visual(VisualEffectType.Slice))), (new ItBill(4, "Chakram")).trigger(new AffectSides(new TypeCondition(EffType.Shield), new AffectSideEffect[]{new ChangeType(ESB.arrow, "ranged damage")})), (new ItBill(4, "Cracked Plate")).trigger(new MaxHP(-4)).trigger(new StartOfTurnSelf(new Eff[]{(new EffBill()).shield(4).self().bEff()})), (new ItBill(4, "Splitting Arrows")).trigger(new AffectSides(SpecificSidesType.RightTwo, new AffectSideEffect[]{new ReplaceWith(new EntSide[]{ESB.arrowCleave.val(1)})})), (new ItBill(4, "Hissing Ring")).trigger(new AffectSides(SpecificSidesType.Middle, new AffectSideEffect[]{new ReplaceWith(new EntSide[]{ESB.dmgPoison.val(2)})})), (new ItBill(4, "Magic Staff")).trigger(new AffectSides(new TypeCondition(EffType.Mana), new AffectSideEffect[]{new SetValue(2)})), (new ItBill(4, "Obol")).trigger(new AffectSides(SpecificSidesType.RightTwo, new AffectSideEffect[]{new AddKeyword(new Keyword[]{Keyword.deathwish})})), (new ItBill(4, "Demon Eye")).trigger(new AffectSides(SpecificSidesType.Left, new AffectSideEffect[]{new AddKeyword(new Keyword[]{Keyword.pain}), new FlatBonus(2)})), (new ItBill(4, "Idol of Aiiu")).trigger(new HpBonusLetter(1, HpBonusLetter.VOWELS)), (new ItBill(4, "Glass Blade")).trigger(new AffectSides(SpecificSidesType.Left, new AffectSideEffect[]{new ReplaceWith(new EntSide[]{ESB.dmg.val(5)})})).trigger(new LostOnDeath("Glass Blade")), new ItBill(4, (new SpellBill()).cost(2).title("hack").eff((new EffBill()).replaceBlanksWith(ESB.dmg.val(4)))), (new ItBill(4, "Antivenom")).trigger(new DamageImmunity(true, false)), (new ItBill(4, "Chainmail")).trigger(new MaxHP(3)), new ItBill(4, (new SpellBill()).cost(3).title("hex").eff((new EffBill()).kill().value(6).keywords(new Keyword[]{Keyword.ranged, Keyword.singleCast}).restrict(new ConditionalRequirement[]{TargetingRestriction.ExactlyValue}).visual(VisualEffectType.Cross).value(6))), new ItBill(4, (new SpellBill()).cost(4).title("invest").eff((new EffBill()).mana(6).keywords(new Keyword[]{Keyword.future, Keyword.cooldown}))), (new ItBill(4, "Life Bolt")).trigger(new AfterUseAbility((Integer)null, (new EffBill()).heal(1).self().bEff())), (new ItBill(4, "Soup")).trigger(new AffectSides(new TypeCondition(EffType.Shield), new AffectSideEffect[]{new ChangeType(ESB.healShield, "heal and shield")})), (new ItBill(4, "Tiara")).trigger(new AffectSides(new TypeCondition(EffType.Mana), new AffectSideEffect[]{new AddKeyword(new Keyword[]{Keyword.selfHeal})})), (new ItBill(4, "Charged Skull")).trigger(new OnDeathEffect((new EffBill()).mana(4).bEff(), new ManaGainEvent(4, "Charged Skull"))), (new ItBill(4, "Apple")).trigger(new AffectSides(SpecificSidesType.LeftTwo, new AffectSideEffect[]{new AddKeyword(new Keyword[]{Keyword.ego})})), (new ItBill(4, "Mana Jelly")).trigger(new AffectSides(new TypeCondition(EffType.Mana), new AffectSideEffect[]{new AddKeyword(new Keyword[]{Keyword.singleUse, Keyword.cantrip})})), (new ItBill(4, "Jester Cap")).trigger(new AffectSides(SpecificSidesType.All, new AffectSideEffect[]{new ReplaceWithEnt(HeroTypeUtils.byName("jester"))})), (new ItBill(4, "Natural")).trigger(new EquipRestrictCol(HeroCol.blue)).trigger(new AffectSides(SpecificSidesType.RightTwo, new AffectSideEffect[]{new ReplaceWith(new EntSide[]{ESB.mana.val(2)})})), (new ItBill(4, "Updog")).trigger(new AffectSides(SpecificSidesType.Top, new AffectSideEffect[]{new AddKeyword(new Keyword[]{Keyword.overdog})})), (new ItBill(4, "Flawed Diamond")).trigger(new AffectSides(SpecificSidesType.LeftTwo, new AffectSideEffect[]{new AddKeyword(new Keyword[]{Keyword.pristine})})).trigger(new EmptyPips(4)), (new ItBill(4, "Duelling Pistol")).trigger(new AffectSides(SpecificSidesType.Left, new AffectSideEffect[]{new AddKeyword(new Keyword[]{Keyword.duel})})), (new ItBill(4, "Ink Bottle")).trigger(new AffectSides(new TypeCondition(EffType.Blank), new AffectSideEffect[]{new ReplaceWith(new EntSide[]{ESB.shieldCantrip.val(1)})})), (new ItBill(4, "Eyepatch")).trigger(new AffectSides(SpecificSidesType.Left, new AffectSideEffect[]{new RemoveAllKeywords()})), (new ItBill(4, "PowerStone")).trigger(new EquipRestrictCol(HeroCol.grey)).trigger(new AffectSides(SpecificSidesType.Middle, new AffectSideEffect[]{new ReplaceWith(new EntSide[]{ESB.mana.val(0).withKeyword(Keyword.steel)})})), (new ItBill(4, "Red flag")).trigger(new MaxHP(3)).trigger(new AffectSides(SpecificSidesType.Middle, new AffectSideEffect[]{new ReplaceWith(new EntSide[]{ESB.redFlag})})), (new ItBill(4, "Inner Strength")).trigger(new AffectSides(new AffectSideEffect[]{new RemoveKeywordColour(new Color[]{Colours.red, Colours.purple})})), (new ItBill(4, "Alembic")).trigger(new AffectSides(SpecificSidesType.Middle, new AffectSideEffect[]{new ReplaceWith(new EntSide[]{ESB.giveManaGainPain})})), (new ItBill(4, "Bonesaw")).trigger(new EquipRestrictCol(HeroCol.red)).trigger(new AffectSides(SpecificSidesType.Wings, new AffectSideEffect[]{new ReplaceWith(new EntSide[]{ESB.dmgCruel.val(3)})})), (new ItBill(4, "Full Moon")).trigger(new PersonalTurnRequirement(new TurnRequirementEveryN(2), new AffectSides(SpecificSidesType.All, new AffectSideEffect[]{new ReplaceWithEnt(MonsterTypeLib.byName("wolf"))}))), (new ItBill(4, "Shuriken")).trigger(new AffectSides(SpecificSidesType.RightTwo, new AffectSideEffect[]{new AddKeyword(new Keyword[]{Keyword.ranged, Keyword.chain})})), (new ItBill(4, "Troll Nose")).trigger(new StartRegenned(1)), (new ItBill(4, "Dragonhide Gloves")).trigger(new CopySide(SpecificSidesType.Middle, SpecificSidesType.Wings)), (new ItBill(4, "Glowing Egg")).trigger(new AffectSides(SpecificSidesType.Left, new AffectSideEffect[]{new AddKeyword(new Keyword[]{Keyword.growth})})), (new ItBill(4, "Eggshell")).trigger(new AffectSides(new AffectSideEffect[]{new AddKeyword(new Keyword[]{Keyword.zeroed})})), (new ItBill(4, "Whiskers")).trigger(new AffectSides(SpecificSidesType.RightThree, new AffectSideEffect[]{new ReplaceWith(new EntSide[]{ESB.arrowCopycat.val(1), ESB.dmgCopycat.val(1), ESB.shieldCopycat.val(1)})})), (new ItBill(4, "Faerie Pact")).trigger(new AffectSides(SpecificSidesType.RightMost, new AffectSideEffect[]{new ReplaceWith(new EntSide[]{ESB.mana.val(4)})})).trigger(new MaxHP(-4)), (new ItBill(4, "Fangs")).trigger(new AffectSides(SpecificSidesType.Left, new AffectSideEffect[]{new AddKeyword(new Keyword[]{Keyword.selfHeal})})), (new ItBill(4, "Cart")).trigger(new TriggerPersonalToGlobal(new GlobalHeroes(new ItemSlots(1)))).trigger(new ItemSlots(-2)), new ItBill(4, (new SpellBill()).title("beam").cost(5).eff((new EffBill()).damage(7).keywords(new Keyword[]{Keyword.singleCast, Keyword.ranged}).visual(VisualEffectType.Beam))), (new ItBill(4, "Dynamo")).trigger(new AffectSides(SpecificSidesType.RightTwo, new AffectSideEffect[]{new AddKeyword(new Keyword[]{Keyword.singleUse, Keyword.era})})), (new ItBill(5, "Cracked Wheel")).trigger(new AffectSides(new AffectSideEffect[]{new AddKeyword(new Keyword[]{Keyword.sticky})})).trigger(new TriggerPersonalToGlobal(new GlobalBonusRerolls(1))), (new ItBill(5, "Cocoon")).trigger(new AffectSides(new AffectSideEffect[]{new AddKeyword(new Keyword[]{Keyword.era}), new FlatBonus(-1)})), (new ItBill(5, "Shimmering Halo")).confirmed().trigger(new OnRescue((new EffBill()).self().buff(new Buff(new MaxHP(2))).bEff())), (new ItBill(5, "Wand Grips")).trigger(new AffectSides(SpecificSidesType.Left, new AffectSideEffect[]{new AddKeyword(new Keyword[]{Keyword.singleUse}), new FlatBonus(2)})), (new ItBill(5, "Lens")).trigger(new AffectSides(new TypeCondition(EffType.Heal), new AffectSideEffect[]{new AddKeyword(new Keyword[]{Keyword.focus})})), (new ItBill(5, "Poodle")).trigger(new AffectSides(SpecificSidesType.Column, new AffectSideEffect[]{new AddKeyword(new Keyword[]{Keyword.dog})})), (new ItBill(5, "Decree")).trigger(new AffectSides(new AffectSideEffect[]{new AddKeyword(new Keyword[]{Keyword.dogma})})), (new ItBill(5, "Erythrocyte")).trigger(new AffectSides(SpecificSidesType.Middle, new AffectSideEffect[]{new ReplaceWith(new EntSide[]{ESB.shieldFlesh.val(0)})})), (new ItBill(5, "Mini Crossbow")).trigger(new AffectSides(SpecificSidesType.Top, new AffectSideEffect[]{new ReplaceWith(new EntSide[]{ESB.rangedEngage.val(2)})})), (new ItBill(5, "Crystallise")).trigger(new AffectSides(new AffectSideEffect[]{new AddKeyword(new Keyword[]{Keyword.stasis})})), (new ItBill(5, "Longsword")).trigger(new AffectSides(SpecificSidesType.Row, new AffectSideEffect[]{new ReplaceWith(new EntSide[]{ESB.dmg.val(3)})})), (new ItBill(5, "Demon Horn")).trigger(new AffectSides(SpecificSidesType.RightMost, new AffectSideEffect[]{new ReplaceWith(new EntSide[]{ESB.demonHorn.val(2)})})), (new ItBill(5, "Pauldron")).trigger(new AffectSides(SpecificSidesType.Wings, new AffectSideEffect[]{new FlatBonus(new int[]{2, -2})})), (new ItBill(5, "Sack of Mana")).trigger(new AffectSides(SpecificSidesType.Column, new AffectSideEffect[]{new ReplaceWith(new EntSide[]{ESB.blankItem, ESB.mana.val(4), ESB.blankItem})})), (new ItBill(5, "Enchanted Harp")).trigger(new AffectSides(SpecificSidesType.Middle, new AffectSideEffect[]{new ReplaceWith(new EntSide[]{ESB.shieldAll.val(2)})})), (new ItBill(5, "Ambrosia")).trigger(new AffectSides(SpecificSidesType.Left, new AffectSideEffect[]{new AddKeyword(new Keyword[]{Keyword.rescue})})), (new ItBill(5, "Fearless")).trigger(new MaxHP(1)).trigger(new AffectSides(SpecificSidesType.RightMost, new AffectSideEffect[]{new ReplaceWith(new EntSide[]{ESB.stun})})), (new ItBill(5, "Ordinary Triangle")).trigger(new AffectSides(new ExactlyCondition(3), new AffectSideEffect[]{new FlatBonus(1)})), (new ItBill(5, "Monocle")).trigger(new AffectSides(SpecificSidesType.Middle, new AffectSideEffect[]{new AddKeyword(new Keyword[]{Keyword.engage})})), (new ItBill(5, "Doomblade")).trigger(new AffectSides(new TypeCondition(EffType.Damage), new AffectSideEffect[]{new AddKeyword(new Keyword[]{Keyword.guilt}), new FlatBonus(1)})), (new ItBill(5, "Simplicity")).trigger(new AffectSides(new TypeCondition(Arrays.asList(EffType.Heal, EffType.Mana, EffType.Damage, EffType.Shield), true), new AffectSideEffect[]{new FlatBonus(1)})), (new ItBill(5, "Glyph of Purity")).trigger(new AffectSides(SpecificSidesType.Wings, new AffectSideEffect[]{new AddKeyword(new Keyword[]{Keyword.cleanse})})), (new ItBill(5, "Door")).trigger(new PersonalConditionLink(new SnapshotCondition(SnapshotConditionType.OrMoreMonsters, 4), new AffectSides(new TypeCondition(EffType.Shield), new AffectSideEffect[]{new FlatBonus(2)}))), (new ItBill(5, "Ruby")).trigger(new IncomingEffBonus(2, new EffType[]{EffType.Heal})).trigger(new EmptyPips(2)), (new ItBill(5, "Whiskey")).trigger(new MaxHP(3)).trigger(new EmptyPips(6)), (new ItBill(5, "Polished Emerald")).trigger(new CopyAlliedItems(2, 4)), (new ItBill(5, "Treasure Chest")).trigger(new AffectSides(SpecificSidesType.Left, new AffectSideEffect[]{new AddKeyword(new Keyword[]{Keyword.hoard, Keyword.singleUse})})), (new ItBill(5, "Sling")).trigger(new AffectSides(SpecificSidesType.Bot, new AffectSideEffect[]{new AddKeyword(new Keyword[]{Keyword.underdog})})), (new ItBill(5, "Shining Bow")).trigger(new AffectSides(new TypeCondition(EffType.Damage), new AffectSideEffect[]{new AddKeyword(new Keyword[]{Keyword.ranged})})), (new ItBill(5, "Sponge")).trigger(new OtherDeathEffect("Sponge", false, (new EffBill()).self().buff(new Buff(1, new AffectSides(new AffectSideEffect[]{new FlatBonus(1)}))))), (new ItBill(5, "Sceptre")).trigger(new AffectSides(SpecificSidesType.Left, new AffectSideEffect[]{new ReplaceWith(new EntSide[]{ESB.scepter.val(1)})})), (new ItBill(7, "Wine")).trigger(new StartPoisoned(1)).trigger(new TriggerPersonalToGlobal(new GlobalMonsters(new StartPoisoned(1))))); } }
B5: Items part 2 | C5: private static List<ItBill> makeSixToNine() { return Arrays.asList((new ItBill(5, "Gizmo")).trigger(SpecificSidesType.RightTwo, new AddKeyword(new Keyword[]{Keyword.shifter})), (new ItBill(5, "Nunchaku")).trigger(new AffectSides(SpecificSidesType.Wings, new AffectSideEffect[]{new AddKeyword(new Keyword[]{Keyword.chain})})), (new ItBill(5, "Early Grave")).trigger(new AffectSides(new OrMoreCondition(3), new AffectSideEffect[]{new AddKeyword(new Keyword[]{Keyword.pain, Keyword.cantrip})})), (new ItBill(5, "Bandana")).trigger(new AffectSides(new HasValue(false), new AffectSideEffect[]{new AddKeyword(new Keyword[]{Keyword.cantrip})})), (new ItBill(6, "Blindfold")).trigger(new AffectSides(new AffectSideEffect[]{new RemoveAllKeywords()})), (new ItBill(6, "Determination")).trigger(new PersonalTurnRequirement(new TurnRequirementFirst(), new Undying())), (new ItBill(6, "Leaden Handle")).trigger(new AffectSides(new TargetedCondition(), new AffectSideEffect[]{new AddKeyword(new Keyword[]{Keyword.heavy}), new FlatBonus(1)})), (new ItBill(6, "Urn")).trigger(new AffectSides(new AffectSideEffect[]{new AddKeyword(new Keyword[]{Keyword.enduring})})), (new ItBill(6, "Braids")).trigger(new CopySide(SpecificSidesType.Left, SpecificSidesType.Middle)), (new ItBill(6, "Kite Shield")).trigger(new AffectSides(new TypeCondition(EffType.Shield), new AffectSideEffect[]{new SetValue(3)})), (new ItBill(6, "Idol of Chrzktx")).trigger(new HpBonusLetter(1, HpBonusLetter.CONSONANTS)), (new ItBill(6, "Wedding Rings")).trigger(new AffectSides(new TypeCondition(EffType.Heal), new AffectSideEffect[]{new AddKeyword(new Keyword[]{Keyword.pair})})), (new ItBill(6, "Jewel Loupe")).trigger(new AffectSides(new ExactlyCondition(1), new AffectSideEffect[]{new AddKeyword(new Keyword[]{Keyword.manaGain})})), (new ItBill(6, "Honeycomb")).trigger(new AffectSides(SpecificSidesType.RightThree, new AffectSideEffect[]{new AddKeyword(new Keyword[]{Keyword.sixth})})), (new ItBill(6, "Lich Eye")).trigger(new AffectSides(new AffectSideEffect[]{new AddKeyword(new Keyword[]{Keyword.manaGain, Keyword.death}), new FlatBonus(2)})), (new ItBill(6, "Eucalyptus")).trigger(new AffectSides(SpecificSidesType.Right, new AffectSideEffect[]{new ReplaceWith(new EntSide[]{ESB.healCleanse.val(1).withKeyword(Keyword.quadUse)})})), (new ItBill(6, "Tie")).trigger(new AffectSides(SpecificSidesType.Middle, new AffectSideEffect[]{new AddKeyword(new Keyword[]{Keyword.pristine})})), (new ItBill(6, "Karma")).trigger(new AffectSides(new TypeCondition(EffType.Heal, false, false), new AffectSideEffect[]{new AddKeyword(new Keyword[]{Keyword.selfHeal})})).trigger(new AffectSides(new TypeCondition(EffType.Shield, false, false), new AffectSideEffect[]{new AddKeyword(new Keyword[]{Keyword.selfShield})})).trigger(new AffectSides(new TypeCondition(EffType.Damage, false, false), new AffectSideEffect[]{new AddKeyword(new Keyword[]{Keyword.pain})})), (new ItBill(6, "Candle")).trigger(new AffectSides(new AffectSideEffect[]{new AddKeyword(new Keyword[]{Keyword.vigil})})), (new ItBill(6, "Silver Pendant")).trigger(new IncomingEffBonus(2, new EffType[]{EffType.Shield})), (new ItBill(6, "Ghost Shield")).trigger(new StartOfTurnSelf(new Eff[]{(new EffBill()).shield(2).self().bEff()})), (new ItBill(6, "Wrench")).trigger(new AffectSides(SpecificSidesType.Middle, new AffectSideEffect[]{new FlatBonus(1)})), (new ItBill(6, "Blood Amulet")).trigger(new AffectSides(SpecificSidesType.LeftTwo, new AffectSideEffect[]{new AddKeyword(new Keyword[]{Keyword.selfHeal})})), (new ItBill(6, "Catnip")).trigger(new AffectSides(SpecificSidesType.RightMost, new AffectSideEffect[]{new AddKeyword(new Keyword[]{Keyword.cantrip})})), (new ItBill(6, "Tooth Necklace")).trigger(new AffectSides(SpecificSidesType.LeftTwo, new AffectSideEffect[]{new AddKeyword(new Keyword[]{Keyword.cruel})})), (new ItBill(6, "Crescent Shield")).trigger(new AffectSides(SpecificSidesType.Left, new AffectSideEffect[]{new ReplaceWith(new EntSide[]{ESB.shieldCrescent.val(1)})})), (new ItBill(6, "Ocular Amulet")).trigger(new AffectSides(SpecificSidesType.Left, new AffectSideEffect[]{new FlatBonus(1)})), (new ItBill(6, "InfiniHeal")).trigger(new AffectSides(SpecificSidesType.RightTwo, new AffectSideEffect[]{new ChangeType(ESB.healAll, "heal all")})), (new ItBill(6, "Water")).trigger(new AffectSides(SpecificSidesType.Row, new AffectSideEffect[]{new FlatBonus(new int[]{1, -1, 1, -1})})), (new ItBill(6, "Blinding Bolt")).trigger(new AfterUseAbility((Integer)null, (new EffBill()).shield(2).self().bEff())), (new ItBill(6, "Sparks")).trigger(new AffectSides(new ExactlyCondition(1), new AffectSideEffect[]{new AddKeyword(new Keyword[]{Keyword.cantrip})})), (new ItBill(6, "Scales")).trigger(new AffectSides(SpecificSidesType.RightMost, new AffectSideEffect[]{new SetToHighest()})), (new ItBill(6, "Jump")).trigger(new AffectSides(SpecificSidesType.Wings, new AffectSideEffect[]{new AddAllKeywordsFromOtherSides(SpecificSidesType.Left)})).trigger(new AffectSides(SpecificSidesType.Left, new AffectSideEffect[]{new ReplaceWithBlank(ChoosableType.Item)})), new ItBill(6, (new SpellBill()).title("Luck").cost(3).eff((new EffBill()).keywords(new Keyword[]{Keyword.future, Keyword.cooldown}).reroll(8))), (new ItBill(6, "Demonic Deal")).trigger(new AffectSides(new AffectSideEffect[]{new AddKeyword(new Keyword[]{Keyword.pain}), new FlatBonus(2)})), (new ItBill(6, "Twisted Flax")).trigger(new AffectSides(SpecificSidesType.Column, new AffectSideEffect[]{new FlatBonus(new int[]{1, -1, 1})})), (new ItBill(6, "Wand of Stun")).trigger(new AffectSides(SpecificSidesType.Middle, new AffectSideEffect[]{new ReplaceWith(new EntSide[]{ESB.wandStun})})), (new ItBill(6, "Hourglass")).trigger(new PersonalTurnRequirement(new TurnRequirementFirst(), new AffectSides(new AffectSideEffect[]{new FlatBonus(true, new int[]{1})}))), (new ItBill(6, "Cauldron")).trigger(new AffectSides(SpecificSidesType.Middle, new AffectSideEffect[]{new AddKeyword(new Keyword[]{Keyword.rite}), new FlatBonus(1)})), (new ItBill(6, "Conduit")).trigger(new AffectSides(SpecificSidesType.Middle, new AffectSideEffect[]{new ReplaceWith(new EntSide[]{ESB.manaDuplicate.val(2)})})), (new ItBill(6, "Enhance Wand")).trigger(new AffectSides(SpecificSidesType.Top, new AffectSideEffect[]{new ReplaceWith(new EntSide[]{ESB.wandFightBonus.val(1)})})), (new ItBill(7, "Ornate Hilt")).trigger(new AffectSides(new TypeCondition(EffType.Damage), new AffectSideEffect[]{new AddKeyword(new Keyword[]{Keyword.selfShield})})), (new ItBill(7, "Duck")).trigger(new AffectSides(SpecificSidesType.RightTwo, new AffectSideEffect[]{new AddKeyword(new Keyword[]{Keyword.echo})})), (new ItBill(7, "Troll Blood")).trigger(new StartRegenned(2)), (new ItBill(7, "Iron Helm")).trigger(new MaxHP(6)), (new ItBill(7, "Wooden Bracelet")).trigger(new AffectSides(new NoKeywordsCondition(), new AffectSideEffect[]{new FlatBonus(1)})), (new ItBill(7, "Two Reeds")).trigger(new AffectSides(new EvennessCondition(true), new AffectSideEffect[]{new FlatBonus(1)})), (new ItBill(7, "Twisted Bar")).trigger(new AffectSides(new AffectSideEffect[]{new SetValue(2)})), (new ItBill(7, "Thimble")).trigger(new OnMyTurn(new DamageImmunity(true, true, false), "thimble")), (new ItBill(7, "Pair of Kings")).trigger(new AffectSides(SpecificSidesType.Wings, new AffectSideEffect[]{new AddKeyword(new Keyword[]{Keyword.pair})})), (new ItBill(7, "Ichor Chalice")).trigger(new OnOverheal((new EffBill()).damage(1).targetType(TargetingType.Top))), (new ItBill(7, "Second Chance")).trigger(new AffectSides(SpecificSidesType.RightMost, new AffectSideEffect[]{new ReplaceWith(new EntSide[]{ESB.recharge})})), (new ItBill(7, "Sharp Wit")).trigger(new AffectSides(new TypeCondition(EffType.Mana), new AffectSideEffect[]{new ChangeType(ESB.dmg, "basic damage", 3), new RemoveKeyword(new Keyword[]{Keyword.manaGain})})), (new ItBill(7, "Ogre Blood")).trigger(new AffectSides(SpecificSidesType.Middle, new AffectSideEffect[]{new AddKeyword(new Keyword[]{Keyword.bloodlust})})), (new ItBill(7, "Dragon Pipe")).trigger(new AffectSides(new TypeCondition(EffType.Heal), new AffectSideEffect[]{new FlatBonus(1)})), (new ItBill(7, "Metal Studs")).trigger(new AffectSides(new TypeCondition(EffType.Shield), new AffectSideEffect[]{new FlatBonus(1)})), (new ItBill(7, "Demon Claw")).trigger(new AffectSides(SpecificSidesType.Left, new AffectSideEffect[]{new AddKeyword(new Keyword[]{Keyword.rampage}), new FlatBonus(-1)})), (new ItBill(7, "Pocket Mirror")).trigger(new CopySide(SpecificSidesType.Left, SpecificSidesType.RightMost)), (new ItBill(7, "Boots of Speed")).trigger(new TriggerPersonalToGlobal(new GlobalBonusRerolls(1))).trigger(new AffectSides(SpecificSidesType.Left, new AffectSideEffect[]{new ReplaceWith(new EntSide[]{ESB.dodge})})), (new ItBill(7, "Mushroom")).trigger(new AffectSides(new AffectSideEffect[]{new AddKeyword(new Keyword[]{Keyword.decay}), new FlatBonus(1)})), (new ItBill(7, "Flute")).trigger(new AffectSides(SpecificSidesType.RightMost, new AffectSideEffect[]{new ReplaceWith(new EntSide[]{ESB.flute.val(1)})})), (new ItBill(7, "Wandcraft")).trigger(new AffectSides(new AffectSideEffect[]{new ChangeType(ESB.wandMana, "single-use mana")})), (new ItBill(7, "Charge Link")).trigger(new AffectSides(SpecificSidesType.Wings, new AffectSideEffect[]{new AddKeyword(new Keyword[]{Keyword.charged, Keyword.singleUse})})), (new ItBill(7, "Broadsword")).trigger(new AffectSides(SpecificSidesType.Column, new AffectSideEffect[]{new ReplaceWith(new EntSide[]{ESB.dmg.val(4)})})), (new ItBill(7, "Anvil")).trigger(new AffectSides(SpecificSidesType.Middle, new AffectSideEffect[]{new AddKeyword(new Keyword[]{Keyword.steel})})), (new ItBill(7, "Botany")).trigger(new AffectSides(new TypeCondition(EffType.Heal), new AffectSideEffect[]{new AddKeyword(new Keyword[]{Keyword.groupGrowth})})), new ItBill(7, (new SpellBill()).cost(2).title("charge").eff((new EffBill()).shield(2).keywords(new Keyword[]{Keyword.boost, Keyword.singleCast}).friendly())), (new ItBill(7, "Glass Heart")).trigger(new Permadeath()).trigger(new AffectSides(new AffectSideEffect[]{new FlatBonus(1)})), (new ItBill(7, "Burning Halo")).confirmed().trigger(new OnRescue((new EffBill()).group().damage(1).bEff())), (new ItBill(7, "Tentacle")).trigger(new AffectSides(SpecificSidesType.RightTwo, new AffectSideEffect[]{new AddKeyword(new Keyword[]{Keyword.repel})})), (new ItBill(8, "Holy Book")).trigger(new AffectSides(SpecificSidesType.Row, new AffectSideEffect[]{new AddKeyword(new Keyword[]{Keyword.cleanse, Keyword.selfCleanse})})), new ItBill(8, (new SpellBill()).title("Spark").cost(4).eff((new EffBill()).friendly().specialAddKeyword(new Keyword[]{Keyword.manaGain}))), (new ItBill(8, "Poison Dip")).trigger(new AffectSides(SpecificSidesType.Wings, new AffectSideEffect[]{new AddKeyword(new Keyword[]{Keyword.poison})})), (new ItBill(8, "Sickle")).trigger(new AffectSides(new HighestCondition(false), new AffectSideEffect[]{new FlatBonus(1)})), (new ItBill(8, "Tourmaline Paraiba")).trigger(new AffectSides(new TypeCondition(EffType.Mana), new AffectSideEffect[]{new AddKeyword(new Keyword[]{Keyword.era})})), (new ItBill(8, "Tusk")).trigger(new AffectSides(new TypeCondition(EffType.Heal), new AffectSideEffect[]{new FlatBonus(1)})).trigger(new AffectSides(new TypeCondition(EffType.Shield), new AffectSideEffect[]{new FlatBonus(1)})), (new ItBill(8, "Bullseye")).trigger(new AffectSides(SpecificSidesType.Column, new AffectSideEffect[]{new AddKeyword(new Keyword[]{Keyword.engage})})), (new ItBill(8, "Katar")).trigger(new AffectSides(new TypeCondition(EffType.Damage), new AffectSideEffect[]{new AddKeyword(new Keyword[]{Keyword.trio})})), (new ItBill(8, "Prism")).trigger(new AffectSides(SpecificSidesType.Middle, new AffectSideEffect[]{new AddKeyword(new Keyword[]{Keyword.rainbow})})), (new ItBill(8, "Mirror Mask")).trigger(new AffectSides(new AffectSideEffect[]{new CopyBaseFromHeroAbove(true)})), (new ItBill(8, "Scorpion Tail")).trigger(new AffectSides(SpecificSidesType.Wings, new AffectSideEffect[]{new AddKeyword(new Keyword[]{Keyword.weaken, Keyword.pain})})), (new ItBill(8, "Greatsword")).trigger(new AffectSides(SpecificSidesType.Middle, new AffectSideEffect[]{new ReplaceWith(new EntSide[]{ESB.dmgInspire.val(5)})})), (new ItBill(8, "Deadly Bolt")).trigger(new AfterUseAbility((Integer)null, (new EffBill()).damage(1).targetType(TargetingType.Top).bEff())), (new ItBill(8, "Sapphire Ring")).trigger(new AffectSides(new TypeCondition(EffType.Mana), new AffectSideEffect[]{new FlatBonus(1)})), (new ItBill(8, "Faerie Dust")).trigger(new AffectSides(new TypeCondition(EffType.Blank), new AffectSideEffect[]{new ReplaceWith(new EntSide[]{ESB.mana.val(3)})})), (new ItBill(8, "Singularity")).trigger(new AffectSides(SpecificSidesType.RightTwo, new AffectSideEffect[]{new FlatBonus(2)})), (new ItBill(8, "Serration")).trigger(new AffectSides(SpecificSidesType.Wings, new AffectSideEffect[]{new AddKeyword(new Keyword[]{Keyword.vulnerable})})), (new ItBill(8, "Iron Crown")).trigger(new EquipRestrictCol(HeroCol.grey)).trigger(new AffectSides(SpecificSidesType.Left, new AffectSideEffect[]{new FlatBonus(4)})), (new ItBill(8, "Standard")).trigger(new EquipRestrictCol(HeroCol.yellow)).trigger(new AffectSides(new AffectSideEffect[]{new FlatBonus(1)})), (new ItBill(8, "Olympian Trident")).trigger(new AffectSides(SpecificSidesType.Middle, new AffectSideEffect[]{new AddKeyword(new Keyword[]{Keyword.cleave})})), (new ItBill(8, "Sushi")).trigger(new AffectSides(SpecificSidesType.Left, new AffectSideEffect[]{new ReplaceWith(new EntSide[]{ESB.rerollCantrip.val(2)})})), (new ItBill(8, "Brimstone")).trigger(new AffectSides(SpecificSidesType.RightMost, new AffectSideEffect[]{new MultiplyEffect(3)})), (new ItBill(8, "Ironblood Pendant")).trigger(new IncomingEffBonus(3, new EffType[]{EffType.Heal, EffType.Shield})), (new ItBill(8, "Gauntlet")).trigger(new AffectSides(new TypeCondition(EffType.Damage), new AffectSideEffect[]{new FlatBonus(1)})), (new ItBill(8, "Lion")).trigger(new AffectSides(SpecificSidesType.LeftTwo, new AffectSideEffect[]{new AddKeyword(new Keyword[]{Keyword.fierce})})), (new ItBill(8, "Wax Seal")).trigger(new AffectSides(new AffectSideEffect[]{new BonusForIdentical()})), (new ItBill(9, "Boarhide Bracers")).trigger(new AffectSides(SpecificSidesType.Wings, new AffectSideEffect[]{new FlatBonus(2)})), (new ItBill(9, "Timestone")).trigger(new AffectSides(SpecificSidesType.RightTwo, new AffectSideEffect[]{new AddKeyword(new Keyword[]{Keyword.cantrip})})), (new ItBill(9, "Triple Shuriken")).trigger(new AffectSides(new AffectSideEffect[]{new AddKeyword(new Keyword[]{Keyword.ranged, Keyword.chain})})), (new ItBill(9, "Collar")).trigger(new AffectSides(SpecificSidesType.Wings, new AffectSideEffect[]{new AddKeyword(new Keyword[]{Keyword.copycat})})), (new ItBill(9, "Silk Cape")).trigger(new CopySide(SpecificSidesType.Left, SpecificSidesType.Row)), (new ItBill(9, "Emerald Mirror")).trigger(new CopyAlliedItems(6, 8)), (new ItBill(9, "Horned Viper")).trigger(new AffectSides(SpecificSidesType.LeftTwo, new AffectSideEffect[]{new AddKeyword(new Keyword[]{Keyword.poison})})), (new ItBill(9, "Angel Feather")).trigger(new AffectSides(SpecificSidesType.Wings, new AffectSideEffect[]{new AddKeyword(new Keyword[]{Keyword.rescue})})), (new ItBill(9, "Dumbbell")).trigger(new AffectSides(new OrMoreCondition(4), new AffectSideEffect[]{new FlatBonus(4)})), (new ItBill(9, "Chaos Wand")).trigger(new AffectSides(SpecificSidesType.Middle, new AffectSideEffect[]{new ReplaceWith(new EntSide[]{ESB.wandChaos.val(1)})})), (new ItBill(9, "Charged Hammer")).trigger(new AffectSides(SpecificSidesType.Left, new AffectSideEffect[]{new ReplaceWith(new EntSide[]{ESB.chargedHammer.val(10)})})), (new ItBill(9, "Eye of Horus")).trigger(new AffectSides(new AffectSideEffect[]{new FlatBonus(1)})), (new ItBill(9, "Helm of Power")).trigger(new AffectSides(SpecificSidesType.Left, new AffectSideEffect[]{new MultiplyEffect(2)})), (new ItBill(9, "Second Heart")).trigger(new BonusHpPerBase(1, 1)), (new ItBill(9, "Overflowing Chalice")).trigger(SpecificSidesType.RightThree, new AddKeyword(new Keyword[]{Keyword.fizz})), new ItBill(10, (new SpellBill()).title("Abyss").cost(5).eff((new EffBill()).kill().restrict(StateConditionType.HalfOrLessHP).visual(VisualEffectType.Singularity))), (new ItBill(9, "Spike Stone")).trigger(new AffectSides(SpecificSidesType.Column, new AffectSideEffect[]{new AddKeyword(new Keyword[]{Keyword.fumble}), new FlatBonus(3)}))); } }
B6: Items part 3 | C6: message.txt 17 KB private static List<ItBill> makeTenFifteen() { return Arrays.asList((new ItBill(10, "Puzzle Box")).trigger(new AffectSides(SpecificSidesType.LeftTwo, new AffectSideEffect[]{new AddKeyword(new Keyword[]{Keyword.enduring})})).trigger(new AffectSides(new AffectSideEffect[]{new SwapSides(SpecificSidesType.Left, SpecificSidesType.Middle)})), (new ItBill(10, "Antlers")).trigger(new AffectSides(new TypeCondition(EffType.Heal), new AffectSideEffect[]{new FlatBonus(1)})).trigger(new AffectSides(new TypeCondition(EffType.Shield), new AffectSideEffect[]{new FlatBonus(1)})).trigger(new AffectSides(new TypeCondition(EffType.Damage), new AffectSideEffect[]{new FlatBonus(1)})).trigger(new AffectSides(new TypeCondition(EffType.Mana), new AffectSideEffect[]{new FlatBonus(1)})), (new ItBill(10, "Egg Basket")).trigger(new AffectSides(SpecificSidesType.All, new AffectSideEffect[]{new AffectByIndex(new AffectSideEffect[]{new FlatBonus(6), new ReplaceWith(new EntSide[]{ESB.blankItem}), new ReplaceWith(new EntSide[]{ESB.blankItem}), new ReplaceWith(new EntSide[]{ESB.blankItem}), new ReplaceWith(new EntSide[]{ESB.blankItem}), new ReplaceWith(new EntSide[]{ESB.blankItem})})})), (new ItBill(10, "Stream")).trigger(new AffectSides(SpecificSidesType.Right, new AffectSideEffect[]{new AddAllKeywordsFromOtherSides()})), (new ItBill(10, "Mithril Shields")).trigger(new AffectSides(new TypeCondition(EffType.Shield, false), new AffectSideEffect[]{new AddKeyword(new Keyword[]{Keyword.cantrip})})), (new ItBill(10, "Heart of Light")).trigger(new AffectSides(new TypeCondition(EffType.Blank), new AffectSideEffect[]{new ReplaceWith(new EntSide[]{ESB.healCleanse.val(10).withKeyword(Keyword.quadUse)})})), (new ItBill(10, "Shiny Gauntlets")).trigger(new AffectSides(SpecificSidesType.Wings, new AffectSideEffect[]{new AddKeyword(new Keyword[]{Keyword.pristine})})), (new ItBill(11, "Telescope")).trigger(new AffectSides(SpecificSidesType.LeftTwo, new AffectSideEffect[]{new AddKeyword(new Keyword[]{Keyword.spy})})), (new ItBill(11, "Mana Potion")).trigger(new AffectSides(SpecificSidesType.Top, new AffectSideEffect[]{new ReplaceWith(new EntSide[]{ESB.manaPotion.val(20)})})), (new ItBill(11, "Stilts")).trigger(new AffectSides(SpecificSidesType.Column, new AffectSideEffect[]{new AddKeyword(new Keyword[]{Keyword.tall})})), (new ItBill(11, "Full Plate")).trigger(new MaxHP(14)), (new ItBill(11, "Diamond Skull")).trigger(new MaxHP(2)).trigger(new OnDeathEffect((new EffBill()).friendly().group().buff(new AffectSides(new AffectSideEffect[]{new FlatBonus(1)})))), (new ItBill(11, "Poseidon Charm")).trigger(new AffectSides(SpecificSidesType.Wings, new AffectSideEffect[]{new AddKeyword(new Keyword[]{Keyword.cleave})})), (new ItBill(11, "Bismuth")).trigger(new AffectSides(new TypeCondition(EffType.Blank), new AffectSideEffect[]{new ReplaceWith(new EntSide[]{ESB.giveCopycat})})), (new ItBill(11, "Economancy")).trigger(new AffectSides(SpecificSidesType.Column, new AffectSideEffect[]{new AddKeyword(new Keyword[]{Keyword.squared})})), (new ItBill(12, "Shining Emerald")).trigger(new CopyAlliedItems(13, 20)), (new ItBill(12, "Broomstick")).trigger(new AffectSides(SpecificSidesType.Wings, new AffectSideEffect[]{new AddKeyword(new Keyword[]{Keyword.manaGain})})), (new ItBill(12, "Locket")).trigger(new AffectSides(new AffectSideEffect[]{new AddKeyword(new Keyword[]{Keyword.resilient})})), (new ItBill(12, "Ruby Shards")).trigger(new AffectSides(new TypeCondition(Arrays.asList(EffType.Heal, EffType.Shield), false), new AffectSideEffect[]{new AddKeyword(Arrays.asList(Keyword.cleave))})), (new ItBill(12, "Coffee")).trigger(new AffectSides(new HighestCondition(), new AffectSideEffect[]{new AddKeyword(new Keyword[]{Keyword.cantrip})})), (new ItBill(12, "Conjuring Rings")).trigger(new AffectSides(SpecificSidesType.Top, new AffectSideEffect[]{new AddKeyword(new Keyword[]{Keyword.duplicate})})), (new ItBill(13, "Bronze Bell")).trigger(new AffectSides(SpecificSidesType.Wings, new AffectSideEffect[]{new AddKeyword(new Keyword[]{Keyword.resonate})})), (new ItBill(13, "Titanbane Amulet")).trigger(new AffectSides(new AffectSideEffect[]{new AddKeyword(new Keyword[]{Keyword.dispel})})), (new ItBill(13, "Demon Heart")).trigger(new AffectSides(SpecificSidesType.Column, new AffectSideEffect[]{new AddKeyword(new Keyword[]{Keyword.inflictInflictDeath})})), (new ItBill(13, "Illegal")).trigger(new AffectSides(SpecificSidesType.LeftTwo, new AffectSideEffect[]{new AffectByIndex(new AffectSideEffect[]{new ReplaceWith(new EntSide[]{ESB.rerollCantrip.val(2)}), new ReplaceWith(new EntSide[]{ESB.recharge})})})), (new ItBill(14, "Ethereal Cloak")).trigger(new AffectSides(new AffectSideEffect[]{new ReplaceWith(new EntSide[]{ESB.dodge})})).trigger(new GhostHP(PipLoc.all())), (new ItBill(14, "Huge Sword")).trigger(new AffectSides(new TypeCondition(EffType.Damage), new AffectSideEffect[]{new AddKeyword(new Keyword[]{Keyword.cleave})})), (new ItBill(14, "Fertiliser")).trigger(new AffectSides(new AffectSideEffect[]{new AddKeyword(new Keyword[]{Keyword.growth})})), (new ItBill(14, "Whirlwind")).trigger(new AffectSides(SpecificSidesType.Column, new AffectSideEffect[]{new AddKeyword(new Keyword[]{Keyword.cantrip})})), (new ItBill(14, "Golden D6")).trigger(new AffectSides(SpecificSidesType.All, new AffectSideEffect[]{new AffectByIndex(new AffectSideEffect[]{new SetValue(6), new SetValue(5), new SetValue(4), new SetValue(3), new SetValue(1), new SetValue(2)})})), (new ItBill(14, "Third Heart")).trigger(new BonusHpPerBase(2, 1)), (new ItBill(15, "Archmage Orb")).trigger(new AffectSides(SpecificSidesType.Middle, new AffectSideEffect[]{new AddKeyword(new Keyword[]{Keyword.charged})})), new ItBill(15, (new SpellBill()).cost(13).title("infinity").eff((new EffBill()).kill().visual(VisualEffectType.Singularity))), (new ItBill(15, "Banned")).trigger(new AffectSides(SpecificSidesType.LeftTwo, new AffectSideEffect[]{new AffectByIndex(new AffectSideEffect[]{new AddKeyword(new Keyword[]{Keyword.cleave}), new AddKeyword(new Keyword[]{Keyword.growth})})})), (new ItBill(15, "Diamond Ring")).trigger(new AffectSides(new TypeCondition(EffType.Damage, false), new AffectSideEffect[]{new ChangeType(ESB.healShieldMana, "heal, shield, managain")})), (new ItBill(15, "Dolphin")).trigger(new AffectSides(new AffectSideEffect[]{new AddKeyword(new Keyword[]{Keyword.echo})})), (new ItBill(15, "Titan Blade")).trigger(new AffectSides(SpecificSidesType.Left, new AffectSideEffect[]{new ReplaceWith(new EntSide[]{ESB.dmgDeath.val(100)})})), (new ItBill(15, "Emerald Satchel")).trigger(new CopyInvItems())); } private static List<ItBill> makeSixteenPlus() { return Arrays.asList((new ItBill(16, "Pentagram")).trigger(new PersonalTurnRequirement(new TurnRequirementFirstN(5), new Undying())), (new ItBill(16, "Farewell")).trigger(new OnDeathEffect((new EffBill()).kill().targetType(TargetingType.Top))), (new ItBill(16, "Blue Skink")).trigger(new AffectSides(new AffectSideEffect[]{new ChangeToAboveType(false)})), (new ItBill(16, "Chocolate Bar")).trigger(new AffectSides(new TypeCondition(Arrays.asList(EffType.Damage, EffType.Shield), false), new AffectSideEffect[]{new AddKeyword(new Keyword[]{Keyword.doubleUse})})), (new ItBill(16, "Whirlpool")).trigger(new AffectSides(new AffectSideEffect[]{new AddAllKeywordsFromOtherSides()})), (new ItBill(17, "Taboo")).trigger(new AffectSides(new TypeCondition(EffType.Heal), new AffectSideEffect[]{new AddKeyword(new Keyword[]{Keyword.hyperUse})})), (new ItBill(17, "Obsidian Edge")).trigger(new AffectSides(new TypeCondition(EffType.Damage), new AffectSideEffect[]{new MultiplyEffect(3)})), (new ItBill(17, "Face of Horus")).trigger(new AffectSides(new AffectSideEffect[]{new FlatBonus(2)})), (new ItBill(18, "Bag of Holding")).trigger(new AllItemsTier(7, 7))); } }
B7: Items part 4 | C7: private static List<ItBill> makeZeroes() { return Arrays.asList((new ItBill(0, "Monster Grin")).trigger(new AffectSides(SpecificSidesType.Wings, new AffectSideEffect[]{new AddKeyword(new Keyword[]{Keyword.possessed})})), (new ItBill(0, "Old Root")).trigger(new AffectSides(new TypeCondition(EffType.Heal, true), new AffectSideEffect[]{new FlatBonus(2)})), (new ItBill(0, "Stake")).trigger(new AffectSides(new TypeCondition(EffType.Damage), new AffectSideEffect[]{new AddKeyword(new Keyword[]{Keyword.terminal})})), new ItBill(0, new Tactic("Oof", new TacticCost(TacticCostType.blank, 5), (new EffBill()).damage(5).visual(VisualEffectType.Sword).bEff())), (new ItBill(0, "Knot")).trigger(new AffectSides(new TypeCondition(EffType.Blank), new AffectSideEffect[]{new AddKeyword(new Keyword[]{Keyword.permissive})})), (new ItBill(0, "Cholesterol")).trigger(new EmptyPips(5)).trigger(new HealImmunity()), (new ItBill(0, "Twiddle")).trigger(new AffectSides(new AffectSideEffect[]{new SwapSides(SpecificSidesType.Top, SpecificSidesType.Bot)})), (new ItBill(0, "Cyanide Pill")).trigger(new AffectSides(SpecificSidesType.RightTwo, new AffectSideEffect[]{new AddKeyword(new Keyword[]{Keyword.cantrip, Keyword.death})})), new ItBill(0, "Void"), (new ItBill(0, "Yearn")).trigger(new AffectSides(new TypeCondition(EffType.Blank), new AffectSideEffect[]{new ReplaceWith(new EntSide[]{ESB.healShieldMana.val(0)})})), (new ItBill(0, "Splinter")).trigger(new MaxHP(-1)), (new ItBill(0, "Scissors")).trigger(new AffectSides(SpecificSidesType.RightMost, new AffectSideEffect[]{new AddKeyword(new Keyword[]{Keyword.deathwish, Keyword.pain})})), new ItBill(0, (new SpellBill()).title("Betray").cost(2).eff((new EffBill()).kill().friendly())), new ItBill(0, (new SpellBill()).title("Waste").cost(1).eff((new EffBill()).replaceBlanksWith(ESB.dmgDeath.val(1)))), new ItBill(0, (new SpellBill()).title("Aid").cost(1).eff((new EffBill()).heal(2).enemy().group())), new ItBill(0, (new SpellBill()).title("Mana").cost(1).eff((new EffBill()).mana(1).keywords(new Keyword[]{Keyword.singleCast}))), new ItBill(0, (new SpellBill()).title("Hinder").cost(1).eff((new EffBill()).friendly().damage(1).keywords(new Keyword[]{Keyword.weaken}))), (new ItBill(0, "Spanner")).trigger(new AffectSides(SpecificSidesType.RightMost, new AffectSideEffect[]{new ReturnToInnate()})), (new ItBill(0, "Peanut Shell")).trigger(new ForceEquip()).trigger(new EmptyPips(1)), (new ItBill(0, "Extra Pocket")).trigger(new ItemSlots(1)), new ItBill(0, new Tactic("Burstic", new TacticCost(new TacticCostType[]{TacticCostType.basicMana, TacticCostType.basicMana}), SpellLib.BURST.getBaseEffect())), (new ItBill(0, "Brick")).trigger(new AffectSides(new TypeCondition(EffType.Shield, true), new AffectSideEffect[]{new AddKeyword(new Keyword[]{Keyword.petrify})})), (new ItBill(0, "Cracked Emerald")).trigger(new CopyAlliedItems(12)), (new ItBill(0, "Fly")).trigger(new AffectSides(SpecificSidesType.Left, new AffectSideEffect[]{new AddKeyword(new Keyword[]{Keyword.growth, Keyword.decay})})), (new ItBill(0, "Snake Oil")).trigger(new AffectSides(new TypeCondition(EffType.Heal, true), new AffectSideEffect[]{new AddKeyword(new Keyword[]{Keyword.engage})})), (new ItBill(0, "Rusty Longsword")).trigger(new AffectSides(SpecificSidesType.Row, new AffectSideEffect[]{new ReplaceWith(new EntSide[]{ESB.dmg.val(1)})})), (new ItBill(0, "Bond Certificate")).trigger(new PersonalTurnRequirement(new TurnRequirementN(15), new AffectSides(new AffectSideEffect[]{new FlatBonus(true, new int[]{15})}))), (new ItBill(0, "Bent Spoon")).trigger(new AffectSides(SpecificSidesType.LeftTwo, new AffectSideEffect[]{new FlatBonus(0)})), (new ItBill(0, "Bent Fork")).trigger(new AffectSides(SpecificSidesType.RightTwo, new AffectSideEffect[]{new MultiplyEffect(1)})), (new ItBill(0, "Bent Spork")).trigger(new AffectSides(SpecificSidesType.Column, new AffectSideEffect[]{new MultiplyEffect(-1)})), (new ItBill(0, "Toy Sword")).trigger(new AffectSides(SpecificSidesType.RightMost, new AffectSideEffect[]{new ReplaceWith(new EntSide[]{ESB.dmg.val(0)})})), (new ItBill(0, "Fidget Spinner")).trigger(new AffectSides(SpecificSidesType.Middle, new AffectSideEffect[]{new ReplaceWith(new EntSide[]{ESB.recharge.withKeyword(Keyword.duplicate)})})), (new ItBill(0, "Wooden Armour")).trigger(new MaxHP(2)).trigger(new AffectSides(new AffectSideEffect[]{new FlatBonus(-1)})), (new ItBill(0, "Burred Shield")).trigger(new AffectSides(SpecificSidesType.Left, new AffectSideEffect[]{new ReplaceWith(new EntSide[]{ESB.shieldPain.val(5)})})), (new ItBill(0, "Hidden Strength")).trigger(new AffectSides(SpecificSidesType.Bot, new AffectSideEffect[]{new ReplaceWith(new EntSide[]{ESB.dmgAll.val(10).withKeyword(Keyword.manacost)})})), (new ItBill(0, "Rorrim Tekcop")).trigger(new CopySide(SpecificSidesType.RightMost, SpecificSidesType.Left)), (new ItBill(0, "Trick Deck")).trigger(new AffectSides(SpecificSidesType.Left, new AffectSideEffect[]{new AddKeyword(new Keyword[]{Keyword.sept})})), (new ItBill(0, "Dull Wit")).trigger(new AffectSides(new TypeCondition(EffType.Mana), new AffectSideEffect[]{new ChangeType(ESB.dmg, "basic damage"), new RemoveKeyword(new Keyword[]{Keyword.manaGain})})), (new ItBill(0, "Dead Branch")).trigger(new AffectSides(SpecificSidesType.Bot, new AffectSideEffect[]{new ReplaceWith(new EntSide[]{ESB.stick.val(1)})})), (new ItBill(0, "Two of Clubs")).trigger(new AffectSides(SpecificSidesType.All, new AffectSideEffect[]{new AffectByIndex(new AffectSideEffect[]{new FlatBonus(-1), new FlatBonus(-1), new FlatBonus(-1), new FlatBonus(-1), new FlatBonus(-1), new FlatBonus(1)})})), (new ItBill(0, "Flea")).trigger(new AffectSides(new ExactlyCondition(0), new AffectSideEffect[]{new AddKeyword(new Keyword[]{Keyword.pain}), new FlatBonus(1)})), (new ItBill(0, "Cracked Phylactery")).trigger(new AffectSides(SpecificSidesType.LeftTwo, new AffectSideEffect[]{new AddKeyword(new Keyword[]{Keyword.selfHeal})})).trigger(new MaxHP(-6)), (new ItBill(0, "Paper")).trigger(new AffectSides(SpecificSidesType.Left, new AffectSideEffect[]{new AddKeyword(new Keyword[]{Keyword.nothing})})), (new ItBill(0, "Sprinkles")).trigger(new EquipRestrictCol(HeroCol.violet)).trigger(new AffectSides(SpecificSidesType.Left, new AffectSideEffect[]{new FlatBonus(1)})), (new ItBill(0, "Big Fish")).trigger(new AffectSides(new TypeCondition(EffType.Damage), new AffectSideEffect[]{new AddKeyword(new Keyword[]{Keyword.vitality})})), (new ItBill(0, "Card")).trigger(new AffectSides(SpecificSidesType.RightTwo, new AffectSideEffect[]{new AddKeyword(new Keyword[]{Keyword.inflictInflictNothing})})), (new ItBill(0, "Grass")).trigger(new AffectSides(new TypeCondition(EffType.Blank), new AffectSideEffect[]{new ReplaceWith(new EntSide[]{ESB.blankPetrified})})), (new ItBill(0, "False Idol")).trigger(new HpBonusLetter(1, new char[]{'z'})), (new ItBill(0, "Stoneskin")).trigger(new MaxHP(2)).trigger(new AffectSides(new AffectSideEffect[]{new ReplaceWithBlank(ChoosableType.Item)})), new ItBill(0, (new SpellBill()).title("Niche").cost(2).eff((new EffBill()).kill().restrict(new ConditionalRequirement[]{TargetingRestriction.ExactlyValue}).value(41).visual(VisualEffectType.Singularity))), new ItBill(0, (new SpellBill()).title("Invoke").cost(1).eff((new EffBill()).summon("demon", 1))), (new ItBill(0, "Orbit")).trigger(PersonalPerN.basicMultiple(4, new AffectSides(new AffectSideEffect[]{new Shift()}))), (new ItBill(0, "Refactor")).trigger(new AffectSides(new TypeCondition(EffType.Recharge, false), new AffectSideEffect[]{new ReplaceWith(new EntSide[]{ESB.giveDoubleUse})})), (new ItBill(0, "Chalk")).trigger(new AffectSides(new TextureCondition(ESB.blankCurse, "[purple]curse blank[cu]"), new AffectSideEffect[]{new ReplaceWith(new EntSide[]{ESB.manaDeath.val(3)})})), (new ItBill(0, "Camomile")).trigger(new AffectSides(new AffectSideEffect[]{new RemoveKeyword(new Keyword[]{Keyword.cantrip})})), (new ItBill(0, "Overprepared")).trigger(new PersonalTurnRequirement(new TurnRequirementN(0), new AffectSides(new AffectSideEffect[]{new FlatBonus(true, new int[]{1})}))), (new ItBill(0, "Pin")).trigger(new AffectSides(new TypeCondition(EffType.Blank), new AffectSideEffect[]{new ReplaceWith(new EntSide[]{ESB.dmgSelfCantrip.val(1)})})), (new ItBill(0, "Atlas Stone")).trigger(new AffectSides(SpecificSidesType.Wings, new AffectSideEffect[]{new FlatBonus(1)})).trigger(new ItemSlots(-2)), (new ItBill(0, "Huge Scabbard")).trigger(new AffectSides(new ExactlyCondition(10), new AffectSideEffect[]{new FlatBonus(1)})), (new ItBill(0, "Banana Peel")).trigger(new AffectSides(SpecificSidesType.RightTwo, new AffectSideEffect[]{new ReplaceWith(new EntSide[]{ESB.giveCantripJoke})})), (new ItBill(0, "Cigarette end")).trigger(new AffectSides(new HasKeyword(new Keyword[]{Keyword.singleUse}), new AffectSideEffect[]{new AddKeyword(new Keyword[]{Keyword.doubleUse})})), (new ItBill(0, "Lawnmower")).trigger(new AffectSides(new AffectSideEffect[]{new RemoveKeywordColour(new Color[]{Colours.green})})), (new ItBill(0, "Scoundrel Stash")).trigger(new EquipRestrictNamed("Scoundrel")).trigger(new AffectSides(SpecificSidesType.LeftTwo, new AffectSideEffect[]{new FlatBonus(1)})), new ItBill(0, (new SpellBill()).cost(2).title("Tsrub").eff((new EffBill()).or((new EffBill()).damage(2).friendly().visual(VisualEffectType.Flame), (new EffBill()).shield(2).enemy()))), (new ItBill(0, "Shroud")).trigger(new AffectSides(SpecificSidesType.Middle, new AffectSideEffect[]{new AddKeyword(new Keyword[]{Keyword.reborn})})), (new ItBill(0, "Dusty Emerald")).trigger(new CopyAlliedItems(0)), (new ItBill(0, "Sleeper Agent")).trigger(new AffectSides(SpecificSidesType.RightMost, new AffectSideEffect[]{new ReplaceWith(new EntSide[]{ESB.backstab.val(5)})})), (new ItBill(0, "Tin Foil Hat")).trigger(new AffectSides(new AffectSideEffect[]{new BecomeIdentical()})), (new ItBill(0, "Potion Shard")).trigger(new AffectSides(SpecificSidesType.Bot, new AffectSideEffect[]{new ReplaceWith(new EntSide[]{ESB.dmgPainDiscard.val(3)})})), (new ItBill(0, "Idol of Pythagoras")).trigger(new HpBonusLetter(1, HpBonusLetter.NUMBERS)), (new ItBill(0, "Stale Bread")).trigger(new AffectSides(SpecificSidesType.LeftTwo, new AffectSideEffect[]{new ReplaceWith(new EntSide[]{ESB.rerollCantrip.val(0), ESB.blank})})), (new ItBill(0, "Taxes")).trigger(new AffectSides(new AffectSideEffect[]{new AddKeyword(new Keyword[]{Keyword.mandatory})})), new ItBill(0, (new SpellBill()).cost(4).title("bank").eff((new EffBill()).mana(3).keywords(new Keyword[]{Keyword.future, Keyword.singleCast}))), (new ItBill(0, "Can")).trigger(new AffectSides(SpecificSidesType.RightTwo, new AffectSideEffect[]{new AddKeyword(new Keyword[]{Keyword.century})}))); } }
B8: Items part 5 | C8: private static List<ItBill> makeNegatives() { return Arrays.asList((new ItBill(-1, "Tracked")).trigger(new ForceEquip()).trigger(new OnDeathEffect((new EffBill()).summon("wolf", 1))), (new ItBill(-1, "Broken Heart")).trigger(new ForceEquip()).trigger(new HealImmunity()), (new ItBill(-1, "Weariness")).trigger(new ForceEquip()).trigger(new AffectSides(SpecificSidesType.LeftTwo, new AffectSideEffect[]{new AddKeyword(new Keyword[]{Keyword.exert})})), (new ItBill(-1, "Coiled Snake")).trigger(new ForceEquip()).trigger(new StartPoisoned(1)), (new ItBill(-1, "Brittle")).trigger(new ForceEquip()).trigger(new Permadeath()), (new ItBill(-1, "Martyr")).trigger(new ForceEquip()).trigger(new AffectSides(SpecificSidesType.LeftTwo, new AffectSideEffect[]{new AddKeyword(new Keyword[]{Keyword.death}), new FlatBonus(2)})), (new ItBill(-1, "Affliction")).trigger(new ForceEquip()).trigger(new AffectSides(SpecificSidesType.LeftTwo, new AffectSideEffect[]{new AddKeyword(new Keyword[]{Keyword.pain})})), (new ItBill(-1, "Lead Weight")).trigger(new ForceEquip()).trigger(new AffectSides(SpecificSidesType.Wings, new AffectSideEffect[]{new ReplaceWith(new EntSide[]{ESB.blankItem})})), (new ItBill(-1, "Handcuffs")).trigger(new ForceEquip()).trigger(new ItemSlots(-1)), (new ItBill(-1, "Mould")).trigger(new ForceEquip()).trigger(new AffectSides(new AffectSideEffect[]{new AddKeyword(new Keyword[]{Keyword.decay})})), (new ItBill(-1, "D4")).trigger(new ForceEquip()).trigger(new AffectSides(SpecificSidesType.Right, new AffectSideEffect[]{new ReplaceWith(new EntSide[]{ESB.dmgSelfCantrip.val(1)})})), (new ItBill(-1, "Cursed Bolt")).trigger(new ForceEquip()).trigger(new AfterUseAbility((Integer)null, (new EffBill()).damage(1).self().bEff())), (new ItBill(-1, "Barrel Hoops")).trigger(new ForceEquip()).trigger(new DamageAdjacentsOnDeath(5)), (new ItBill(-2, "Slimed")).trigger(new ForceEquip()).trigger(new AffectSides(new AffectSideEffect[]{new AddKeyword(new Keyword[]{Keyword.sticky})})), (new ItBill(-2, "Soul Link")).trigger(new ForceEquip()).trigger(new OtherDeathEffect("Soul Link", true, (new EffBill()).self().kill())), (new ItBill(-2, "Wretched Crown")).trigger(new ForceEquip()).trigger(new OnDeathEffect((new EffBill()).friendly().group().kill())), (new ItBill(-2, "Broken Spirit")).trigger(new ForceEquip()).trigger(new HealImmunity()).trigger(new ShieldImmunity()), (new ItBill(-2, "Exhaustion")).trigger(new ForceEquip()).trigger(new AffectSides(new AffectSideEffect[]{new AddKeyword(new Keyword[]{Keyword.exert})})), (new ItBill(-2, "Compulsion")).trigger(new ForceEquip()).trigger(new AffectSides(new AffectSideEffect[]{new AddKeyword(new Keyword[]{Keyword.mandatory, Keyword.pain})})), (new ItBill(-2, "Conscience")).trigger(new ForceEquip()).trigger(new OtherDeathEffect("Conscience", false, (new EffBill()).self().damage(1).bEff())), (new ItBill(-2, "Parasite")).trigger(new ForceEquip()).trigger(new SetStartingHp(1)), (new ItBill(-2, "Pharaoh Curse")).trigger(new ForceEquip()).trigger(new AffectSides(new AffectSideEffect[]{new FlatBonus(-1)})), (new ItBill(-4, "Backstab")).trigger(new ForceEquip()).trigger(new AffectSides(SpecificSidesType.MiddleFour, new AffectSideEffect[]{new ReplaceWith(new EntSide[]{ESB.backstab.val(4)})})), (new ItBill(Math.round(ModTierUtils.blanked(0.8F)), "Amnesia")).trigger(new ForceEquip()).trigger(new AffectSides(new AffectSideEffect[]{new ReplaceWithBlank(ChoosableType.Item)})), (new ItBill(Math.round(ModTierUtils.deadHero(0.85F)), "Dead Crow")).trigger(new ForceEquip()).trigger(new StartOfCombat((new EffBill()).self().kill().bEff())), (new ItBill(-4, "Empathy")).trigger(new ForceEquip()).trigger(new OtherDeathEffect("Conscience", false, (new EffBill()).self().kill().bEff()))); } }
B10: Blue Heroes | C10: HeroCol col = HeroCol.blue; int lv = 1; bills.add(((HTBill)((HTBill)((HTBill)(new HTBill(col, lv)).name("Mage")).hp(4)).sides(new EntSide[]{ESB.mana.val(2), ESB.mana.val(2), ESB.mana.val(1), ESB.mana.val(1), ESB.blank, ESB.blank})).spell((new SpellBill()).title("Poke").cost(1).eff((new EffBill()).damage(1).keywords(new Keyword[]{Keyword.cooldown}).visual(VisualEffectType.Slice)))); bills.add(((HTBill)((HTBill)((HTBill)(new HTBill(col, lv)).name("Prodigy")).hp(4)).sides(ESB.wandMana.val(3), ESB.wandMana.val(3))).spell((new SpellBill()).title("Scorch").cost(2).eff((new EffBill()).damage(1).keywords(new Keyword[]{Keyword.cleave, Keyword.singleCast}).visual(VisualEffectType.Flame)))); bills.add(((HTBill)((HTBill)((HTBill)(new HTBill(col, lv)).name("Meddler")).hp(6)).sides(new EntSide[]{ESB.mana.val(3), ESB.manaCantrip.val(1), ESB.manaPain.val(2), ESB.manaPain.val(2), ESB.manaCantripBoned.val(1), ESB.manaCantripBoned.val(1)})).spell((new SpellBill()).title("Slay").cost(3).eff((new EffBill()).kill().restrict(new ConditionalRequirement[]{TargetingRestriction.ExactlyValue}).value(3).visual(VisualEffectType.Ellipse)))); bills.add(((HTBill)((HTBill)((HTBill)(new HTBill(col, lv)).name("Student")).hp(5)).sides(ESB.recharge, ESB.shieldMana.val(1), ESB.shieldMana.val(1))).spell((new SpellBill()).title("Slice").cost(3).eff((new EffBill()).damage(1).group().visual(VisualEffectType.Slice)))); bills.add(((HTBill)((HTBill)((HTBill)(new HTBill(col, lv)).name("Initiate")).hp(4)).sides(new EntSide[]{ESB.manaCantrip.val(1), ESB.manaGrowth.val(1), ESB.wandMana.val(1), ESB.wandMana.val(1), ESB.wandMana.val(1), ESB.blank})).spell((new SpellBill()).title("gather").cost(2).eff((new EffBill()).replaceBlanksWith(ESB.mana.val(2))))); bills.add(((HTBill)((HTBill)((HTBill)(new HTBill(col, lv)).name("Cultist")).hp(5)).sides(new EntSide[]{ESB.manaPain.val(4), ESB.manaPain.val(3), ESB.wandSelfHeal.val(1), ESB.wandSelfHeal.val(1), ESB.manaPain.val(2), ESB.manaPain.val(1)})).spell((new SpellBill()).title("cut").cost(1).eff((new EffBill()).damage(3).friendly().keywords(new Keyword[]{Keyword.cooldown}).visual(VisualEffectType.Slice).bonusUntargeted(new EffBill[]{(new EffBill()).damage(2).targetType(TargetingType.Top).visual(VisualEffectType.Slice)})))); lv = 2; bills.add(((HTBill)((HTBill)((HTBill)(new HTBill(col, lv)).name("Caldera")).hp(6)).sides(new EntSide[]{ESB.wandFire.val(3), ESB.mana.val(2), ESB.dmgMana.val(1), ESB.dmgMana.val(1), ESB.mana.val(2), ESB.blank})).spell((new SpellBill()).title("scald").cost(3).eff((new EffBill()).damage(2).group().restrict(StateConditionType.Damaged).visual(VisualEffectType.Flame)))); bills.add(((HTBill)((HTBill)((HTBill)(new HTBill(col, lv)).name("Evoker")).hp(8)).sides(ESB.mana.val(3), ESB.mana.val(2), ESB.mana.val(1))).spell((new SpellBill()).title("drop").cost(3).eff((new EffBill()).damage(4).targetType(TargetingType.Top).visual(VisualEffectType.Anvil)))); bills.add(((HTBill)((HTBill)((HTBill)(new HTBill(col, lv)).name("Glacia")).hp(9)).sides(new EntSide[]{ESB.wandWeaken.val(1), ESB.mana.val(2), ESB.shieldMana.val(1), ESB.shieldMana.val(1), ESB.mana.val(1), ESB.mana.val(1)})).spell((new SpellBill()).title("chill").cost(2).eff((new EffBill()).damage(2).keywords(new Keyword[]{Keyword.weaken, Keyword.singleCast}).visual(VisualEffectType.Frost)))); bills.add(((HTBill)((HTBill)((HTBill)(new HTBill(col, lv)).name("Jester")).hp(6)).sides(new EntSide[]{ESB.mana.val(3), ESB.rerollCantrip.val(1), ESB.wandMana.val(1), ESB.wandMana.val(1), ESB.dodge, ESB.blank})).spell((new SpellBill()).title("flick").cost(1).eff((new EffBill()).keywords(new Keyword[]{Keyword.engage, Keyword.cooldown}).damage(1).visual(VisualEffectType.Slice)))); bills.add(((HTBill)((HTBill)((HTBill)(new HTBill(col, lv)).name("Sparky")).hp(7)).sides(new EntSide[]{ESB.dmgMana.val(2), ESB.mana.val(1), ESB.wandCharged.val(0), ESB.wandCharged.val(0), ESB.mana.val(1), ESB.blank})).spell((new SpellBill()).title("zap").cost(1).eff((new EffBill()).keywords(new Keyword[]{Keyword.cooldown}).kill().restrict(new ConditionalRequirement[]{TargetingRestriction.ExactlyValue}).value(2).visual(VisualEffectType.LightningBig)))); bills.add(((HTBill)((HTBill)((HTBill)(new HTBill(col, lv)).name("Myco")).hp(8)).sides(new EntSide[]{ESB.manaDecay.val(3), ESB.manaDecay.val(2), ESB.shieldGrowth.val(1), ESB.damageGrowth.val(1), ESB.manaDecay.val(1), ESB.resurrect.val(1)})).spell((new SpellBill()).title("Spore").cost(1).eff((new EffBill()).keywords(new Keyword[]{Keyword.cooldown}).friendly().buff(new Buff(1, new AffectSides(new AffectSideEffect[]{new AddKeyword(new Keyword[]{Keyword.decay}), new FlatBonus(1)})))))); bills.add(((HTBill)((HTBill)((HTBill)(new HTBill(col, lv)).name("Seer")).hp(7)).sides(new EntSide[]{ESB.manaGrowth.val(1), ESB.wandPoison.val(1), ESB.wandMana.val(3), ESB.wandMana.val(3), ESB.blank, ESB.blank})).spell((new SpellBill()).title("Foretell").cost(3).eff((new EffBill()).mana(4).keywords(new Keyword[]{Keyword.future})))); bills.add(((HTBill)((HTBill)((HTBill)(new HTBill(col, lv)).name("Fiend")).hp(6)).sides(new EntSide[]{ESB.manaCantrip.val(1), ESB.manaPain.val(3), ESB.wandSelfHeal.val(2), ESB.wandSelfHeal.val(2), ESB.manaPain.val(2), ESB.blank})).spell((new SpellBill()).title("Burn").cost(1).eff((new EffBill()).damage(1).targetType(TargetingType.ALL).keywords(new Keyword[]{Keyword.cooldown}).visual(VisualEffectType.Flame)))); lv = 3; bills.add(((HTBill)((HTBill)((HTBill)(new HTBill(col, lv)).name("Artificer")).hp(8)).sides(new EntSide[]{ESB.wandSelfHeal.val(3), ESB.wandCharged.val(2), ESB.wandMana.val(4), ESB.wandMana.val(4), ESB.wandPoison.val(2), ESB.wandHeal.val(10)})).spell((new SpellBill()).title("blades").cost(4).eff((new EffBill()).damage(2).visual(VisualEffectType.MultiBlade).group()))); bills.add(((HTBill)((HTBill)((HTBill)(new HTBill(col, lv)).name("Weaver")).hp(10)).sides(new EntSide[]{ESB.manaDouble.val(0), ESB.mana.val(3), ESB.wandMana.val(3), ESB.wandMana.val(3), ESB.dodge, ESB.blank})).spell((new SpellBill()).title("crush").cost(3).eff((new EffBill()).damage(3).targetType(TargetingType.TopAndBot).visual(VisualEffectType.Crush)))); bills.add(((HTBill)((HTBill)((HTBill)(new HTBill(col, lv)).name("Sorcerer")).hp(7)).sides(new EntSide[]{ESB.manaCantrip.val(1), ESB.rerollCantrip.val(1), ESB.manaCantrip.val(1), ESB.manaCantrip.val(1), ESB.blank, ESB.blank})).spell((new SpellBill()).title("miasma").cost(3).eff((new EffBill()).damage(1).keywords(new Keyword[]{Keyword.poison, Keyword.cleave}).visual(VisualEffectType.PerlinPoison)))); bills.add(((HTBill)((HTBill)((HTBill)(new HTBill(col, lv)).name("Chronos")).hp(7)).sides(new EntSide[]{ESB.recharge, ESB.rerollCantrip.val(1), ESB.manaGrowth.val(2), ESB.manaGrowth.val(2), ESB.dodge, ESB.blank})).spell((new SpellBill()).title("tick").cost(4).eff((new EffBill()).damage(1).visual(VisualEffectType.Freeze).keywords(new Keyword[]{Keyword.weaken, Keyword.cleave})))); bills.add(((HTBill)((HTBill)((HTBill)(new HTBill(col, lv)).name("Warlock")).hp(8)).sides(new EntSide[]{ESB.manaLust.val(2), ESB.wandSelfHeal.val(3), ESB.manaPain.val(4), ESB.manaPain.val(4), ESB.blank, ESB.blank})).spell((new SpellBill()).title("blaze").cost(6).eff((new EffBill()).damage(13).visual(VisualEffectType.Flame)))); bills.add(((HTBill)((HTBill)((HTBill)(new HTBill(col, lv)).name("Ace")).hp(8)).sides(new EntSide[]{ESB.manaTriple.val(3), ESB.manaPair.val(2), ESB.blank, ESB.blank, ESB.mana.val(1), ESB.blank})).spell((new SpellBill()).title("Draw").cost(1).eff((new EffBill()).justTarget().friendly().value(1).keywords(new Keyword[]{Keyword.boost, Keyword.deplete})))); bills.add(((HTBill)((HTBill)((HTBill)(new HTBill(col, lv)).name("Ghast")).hp(8)).sides(new EntSide[]{ESB.manaDeath.val(5), ESB.mana.val(2), ESB.wandWeaken.val(2), ESB.wandWeaken.val(2), ESB.mana.val(1), ESB.blank})).spell((new SpellBill()).title("Harvest").cost(1).eff((new EffBill()).keywords(new Keyword[]{Keyword.cooldown}).kill().restrict(new ConditionalRequirement[]{TargetingRestriction.ExactlyValue}).visual(VisualEffectType.Singularity).value(1).bonusUntargeted(new EffBill[]{(new EffBill()).mana(3)})))); bills.add(((HTBill)((HTBill)((HTBill)(new HTBill(col, lv)).name("Wizard")).hp(9)).sides(new EntSide[]{ESB.wandFightBonus.val(1), ESB.manaCantrip.val(1), ESB.shieldMana.val(1), ESB.shieldMana.val(1), ESB.dmgMana.val(1), ESB.dmgMana.val(1)})).spell((new SpellBill()).cost(4).title("Inspire").eff((new EffBill()).recharge().keywords(new Keyword[]{Keyword.cooldown})))); List<HeroType> result = new ArrayList();
B11: Green Heroes | C11: public class HeroTypeBlobGreen { static final int TWIN_HP = 4; public static List<HeroType> makeDesigned() { HeroCol c = HeroCol.green; List<HTBill> htb = new ArrayList(Arrays.asList((HTBill)((HTBill)((HTBill)((HTBill)(new HTBill(c, 1)).name("Tinder")).hp(5)).sides(ESB.dmgPain.val(2), ESB.dmgPain.val(2), ESB.dmgSelfMandatory.val(3), ESB.dmgSelfMandatory.val(3), ESB.stick.val(1))).trait(new OnDeathEffect((new EffBill()).group().damage(1)), new CalcStats(1.05F, 1.0F)), ((HTBill)((HTBill)((HTBill)(new HTBill(c, 1)).name("Reflection")).hp(2)).sides(ESB.wandInflictPain.val(1), ESB.wandEcho.val(0), ESB.wandEcho.val(0))).tactic(new Tactic("Thrike", new TacticCost(new TacticCostType[]{TacticCostType.pips3}), (new EffBill()).damage(3).visual(VisualEffectType.Sword).bEff())), (HTBill)((HTBill)((HTBill)((HTBill)((HTBill)(new HTBill(c, 1)).name("Housecat")).hp(3)).sides(ESB.bite.val(3), ESB.slash.val(1), ESB.slash.val(1))).trait(new ForeverYoung(), new CalcStats(0.0F, 0.0F))).trait(new ReplaceChat(new String[]{"Meow", "Meow", "Meow", "Mew", "Mauu", "Miaaaauu", "Mew mew mew", "purr purr", "prrr", "Yowwwwl", "chirp", "hiss!", "Oh Long Johnson"})), ((HTBill)((HTBill)((HTBill)(new HTBill(c, 1)).name("Primrose")).hp(5)).sides(new EntSide[]{ESB.damageGrowth.val(2), ESB.healGroooooowth.val(1), ESB.shieldGrowth.val(1), ESB.shieldGrowth.val(1), ESB.healGroooooowth.val(1), ESB.giveGrowth})).tactic(new Tactic("Leaf", new TacticCost(new TacticCostType[]{TacticCostType.keyword, TacticCostType.blank}), (new EffBill()).friendly().justTarget().value(1).keywords(new Keyword[]{Keyword.boost}))), ((HTBill)((HTBill)((HTBill)(new HTBill(c, 1)).name("Spade")).hp(7)).sides(new EntSide[]{ESB.resurrect.val(1), ESB.resurrect.val(1), ESB.resurrect.val(1), ESB.resurrect.val(1), ESB.resurrect.val(1), ESB.resurrect.val(1)})).tactic(new Tactic("Mulch", new TacticCost(new TacticCostType[]{TacticCostType.wild}), (new EffBill()).heal(2).bEff())), (HTBill)((HTBill)((HTBill)((HTBill)(new HTBill(c, 1)).name("Pockets")).hp(4)).sides(ESB.wandFierce.val(2), ESB.wandInfExer.val(1), ESB.stick.val(1), ESB.wandHeal.val(1), ESB.wandSelfHeal.val(1))).trait(new AddChoosableOnPick(new Choosable[]{new AndChoosable(new Choosable[]{new RandomTieredChoosable(1, 1, ChoosableType.Item), new RandomTieredChoosable(0, 2, ChoosableType.Item)})})), (HTBill)((HTBill)((HTBill)((HTBill)(new HTBill(c, 2)).name("Presence")).hp(8)).sides(ESB.giveCruelDeathwish, ESB.giveSelfShieldSelfHeal, ESB.giveEngage, ESB.giveGrowth, ESB.giveCleanseSelfCleanse)).trait(new GhostHP(PipLoc.all()), new CalcStats(0.0F, 3.0F)), (HTBill)((HTBill)((HTBill)((HTBill)(new HTBill(c, 2)).name("Spine")).hp(8)).sides(ESB.heal.val(4), ESB.heal.val(4), ESB.dmgCantrip.val(1), ESB.dmgCantrip.val(1))).trait(new Spiky(1), new CalcStats(0.5F, 0.7F)), (HTBill)((HTBill)((HTBill)((HTBill)(new HTBill(c, 2)).name("Granite")).hp(5)).sides(ESB.undying, ESB.dmgHeavy.val(3), ESB.dmgHeavy.val(2), ESB.dmgHeavy.val(2))).trait(new StoneSpecialHp(new PipLoc(PipLocType.LeftmostN, 2)), new CalcStats(0.0F, 7.0F)), (HTBill)((HTBill)((HTBill)(new HTBill(c, 2)).name("Statue")).hp(20)).sides(new EntSide[]{ESB.blank, ESB.blank, ESB.blank, ESB.blank, ESB.blank, ESB.blank}), (HTBill)((HTBill)((HTBill)((HTBill)(new HTBill(c, 2)).name("Mimic")).hp(10)).sides(new EntSide[]{ESB.blankUnset, ESB.blankUnset, ESB.blankUnset, ESB.blankUnset, ESB.blankUnset, ESB.blankUnset})).trait(new Trait((new AffectSides(new AffectSideEffect[]{new ReplaceWithOtherHeroSideInOrder(4)})).mimicPriority(), new CalcStats(HeroTypeUtils.getEffectTierFor(2) * 0.85F, 0.0F))), ((HTBill)((HTBill)((HTBill)(new HTBill(c, 2)).name("Sphere")).hp(10)).sides(ESB.stun, ESB.rerollCantrip.val(1), ESB.blank, ESB.blank, ESB.rerollCantrip.val(1))).tactic(new Tactic("Slam", new TacticCost(new TacticCostType[]{TacticCostType.keyword, TacticCostType.keyword}), (new EffBill()).damage(4).keywords(new Keyword[]{Keyword.heavy}).visual(VisualEffectType.Anvil))), (HTBill)((HTBill)((HTBill)((HTBill)(new HTBill(c, 2)).name("Coffin")).hp(7)).sides(ESB.shield.val(2), ESB.stick.val(1), ESB.stick.val(1))).trait(new AddChoosableOnPick(new Choosable[]{new RandomTieredChoosable(0, 1, ChoosableType.Hero)})), (HTBill)((HTBill)((HTBill)(new HTBill(c, 2)).name("Alien")).hp(8)).tactic(new Tactic("Devoid", new TacticCost(new TacticCostType[]{TacticCostType.blank, TacticCostType.basicSword, TacticCostType.basicSword}), (new EffBill()).group().kill().restrict(new ConditionalRequirement[]{new ParamCondition(ParamConType.OrLessHp, 2, false)}).visual(VisualEffectType.Singularity).bEff())).sides(ESB.justTargetEnemyPips.val(3).withKeyword(Keyword.damage), ESB.justTargetAllyPips.val(5).withKeyword(Keyword.shield), ESB.justTargetAllyPips.val(2).withKeyword(Keyword.cleanse), ESB.justTargetAllyPips.val(2).withKeyword(Keyword.cleanse)), (HTBill)((HTBill)((HTBill)((HTBill)(new HTBill(c, 3)).name("Tainted")).hp(13)).sides(new EntSide[]{ESB.blankStasis, ESB.blankStasis, ESB.dmgCleave.val(3), ESB.dmgCleave.val(3), ESB.dmgPoison.val(4), ESB.shieldCleave.val(3)})).trait(new AddChoosableOnPick(new Choosable[]{new RandomTieredChoosable(-4, 1, ChoosableType.Modifier)})), (HTBill)((HTBill)((HTBill)((HTBill)(new HTBill(c, 3)).name("Luggage")).hp(5)).sides(ESB.shieldCleave.val(1), ESB.shieldCleave.val(1))).trait(new AddChoosableOnPick(new Choosable[]{new AndChoosable(new Choosable[]{new RandomTieredChoosable(6, 1, ChoosableType.Item), new RandomTieredChoosable(7, 1, ChoosableType.Item), new RandomTieredChoosable(8, 1, ChoosableType.Item)})})), (HTBill)((HTBill)((HTBill)((HTBill)(new HTBill(c, 3)).name("Vessel")).hp(5)).sides(ESB.dmgDeath.val(5), ESB.shield.val(5), ESB.healCleanse.val(5))).trait(new AddChoosableOnPick(new Choosable[]{new RandomTieredChoosable(3, 1, ChoosableType.Modifier)})), (HTBill)((HTBill)((HTBill)((HTBill)(new HTBill(c, 3)).name("Jumble")).hp(10)).sides(new EntSide[]{ESB.dmg.val(3), ESB.shield.val(2), ESB.shield.val(2), ESB.shield.val(2), ESB.heal.val(1), ESB.heal.val(1)})).trait(new SimpleKeywordTrait(Keyword.fluctuate)), (HTBill)((HTBill)((HTBill)((HTBill)(new HTBill(c, 3)).name("Dice")).hp(12)).sides(new EntSide[]{ESB.dmg.val(6), ESB.dmg.val(6), ESB.shieldCantrip.val(6), ESB.shieldCantrip.val(6), ESB.heal.val(6), ESB.heal.val(6)})).trait(new SimpleKeywordTrait(Keyword.lucky)), (HTBill)((HTBill)((HTBill)((HTBill)(new HTBill(c, 3)).name("Robot")).hp(14)).sides(new EntSide[]{ESB.shieldCrescent.val(1), ESB.flute.val(1), ESB.wandOfWand.val(1), ESB.demonHorn.val(1), ESB.arrowDuplicate.val(1), ESB.shieldPain.val(1)})).trait(new ItemSlots(2), new CalcStats(0.2F, 0.0F)), (HTBill)((HTBill)((HTBill)((HTBill)((HTBill)(new HTBill(c, 3)).name("Twin")).hp(4)).sides(HeroTypeUtils.makeTwinSides())).trait(new Trait(new TwinPersonal(((HTBill)((HTBill)((HTBill)((HTBill)((HTBill)(new HTBill(c, 3)).name("Tw1n")).hp(4)).sides(HeroTypeUtils.makeTwinSides())).trait(new Trait(new NoEquip(), false))).trait(new Trait(new CopyItemsFromSingleHero("Twin"), false))).bEntType())))).hiddenNoCalc(new SkipLateStart()))); List<HeroType> result = new ArrayList(); Iterator var3 = htb.iterator();
B12: Grey Heroes | C12: public class HeroTypeBlobGrey { public static List<HeroType> makeDesigned() { List<HTBill> bills = new ArrayList(); HeroCol col = HeroCol.grey; int lv = 1; bills.add((HTBill)((HTBill)((HTBill)(new HTBill(col, lv)).name("Defender")).hp(7)).sides(new EntSide[]{ESB.shield.val(3), ESB.shield.val(2), ESB.dmg.val(1), ESB.dmg.val(1), ESB.shield.val(1), ESB.blank})); bills.add((HTBill)((HTBill)((HTBill)(new HTBill(col, lv)).name("Buckle")).hp(6)).sides(new EntSide[]{ESB.shieldPristine.val(2), ESB.dmgHeavy.val(2), ESB.shield.val(2), ESB.shield.val(2), ESB.blank, ESB.blank})); bills.add((HTBill)((HTBill)((HTBill)(new HTBill(col, lv)).name("Squire")).hp(5)).sides(new EntSide[]{ESB.shieldFocus.val(2), ESB.dmgFocus.val(1), ESB.redirect.val(2), ESB.redirect.val(2), ESB.shield.val(1), ESB.shield.val(1)})); bills.add((HTBill)((HTBill)((HTBill)(new HTBill(col, lv)).name("Alloy")).hp(4)).sides(new EntSide[]{ESB.dmgSelfShield.val(1), ESB.shieldRepel.val(1), ESB.shieldCleave.val(1), ESB.healShield.val(1), ESB.shieldCleanse.val(1), ESB.shieldCantrip.val(1)})); bills.add((HTBill)((HTBill)((HTBill)(new HTBill(col, lv)).name("Wallop")).hp(5)).sides(ESB.undying, ESB.dmgSelfShield.val(2), ESB.stun, ESB.stun, ESB.dmgSelfShield.val(1))); lv = 2; bills.add(((HTBill)((HTBill)((HTBill)(new HTBill(col, lv)).name("Knight")).hp(9)).sides(new EntSide[]{ESB.shieldSteel.val(3), ESB.shieldSteel.val(3), ESB.dmgExert.val(3), ESB.dmgExert.val(3), ESB.blank, ESB.blank})).tactic(new Tactic("Parry", new TacticCost(new TacticCostType[]{TacticCostType.basicSword, TacticCostType.basicSword}), (new EffBill()).shield(3).bEff()))); bills.add((HTBill)((HTBill)((HTBill)(new HTBill(col, lv)).name("Armorer")).hp(9)).sides(new EntSide[]{ESB.dmgHeavy.val(3), ESB.shield.val(4), ESB.shieldCleave.val(1), ESB.shieldCleave.val(1), ESB.shieldSmith.val(1), ESB.shieldSmith.val(1)})); bills.add(((HTBill)((HTBill)((HTBill)(new HTBill(col, lv)).name("Bard")).hp(6)).sides(new EntSide[]{ESB.dmgCantrip.val(1), ESB.rerollCantrip.val(1), ESB.shieldAll.val(1), ESB.shieldAll.val(1), ESB.shieldCantrip.val(1), ESB.blank})).tactic(new Tactic("Else", new TacticCost(new TacticCostType[]{TacticCostType.blank}), (new EffBill()).shield(1).keywords(new Keyword[]{Keyword.cleanse}).bEff()))); bills.add(((HTBill)((HTBill)((HTBill)(new HTBill(col, lv)).name("Cleric")).hp(8)).sides(ESB.healShield.val(3), ESB.shieldCleanse.val(2), ESB.wandMana.val(2), ESB.wandMana.val(2))).spell((new SpellBill()).cost(1).title("light").eff((new EffBill()).shield(1).keywords(new Keyword[]{Keyword.cleanse, Keyword.cleave, Keyword.singleCast})))); bills.add((HTBill)((HTBill)((HTBill)(new HTBill(col, lv)).name("Guardian")).hp(8)).sides(new EntSide[]{ESB.shieldCleave.val(2), ESB.dmgCleave.val(1), ESB.shieldEngage.val(3), ESB.shieldEngage.val(3), ESB.blank, ESB.blank})); bills.add((HTBill)((HTBill)((HTBill)(new HTBill(col, lv)).name("Pilgrim")).hp(9)).sides(new EntSide[]{ESB.recharge, ESB.undying, ESB.giveSelfShield, ESB.giveSelfShield, ESB.stun, ESB.stun})); bills.add((HTBill)((HTBill)((HTBill)(new HTBill(col, lv)).name("Monk")).hp(9)).sides(new EntSide[]{ESB.shieldCleanse.val(2), ESB.shieldRepel.val(1), ESB.redirect.val(3), ESB.redirect.val(3), ESB.shieldRepel.val(1), ESB.blank})); bills.add((HTBill)((HTBill)((HTBill)(new HTBill(col, lv)).name("Warden")).hp(10)).sides(new EntSide[]{ESB.shield.val(4), ESB.shield.val(3), ESB.dmg.val(2), ESB.dmg.val(2), ESB.shield.val(2), ESB.shield.val(1)})); lv = 3; bills.add((HTBill)((HTBill)((HTBill)(new HTBill(col, lv)).name("Keeper")).hp(10)).sides(new EntSide[]{ESB.shieldRepel.val(2), ESB.shieldRepel.val(2), ESB.shieldSteel.val(5), ESB.shieldSteel.val(5), ESB.giveSelfShieldSelfHeal, ESB.blank})); bills.add((HTBill)((HTBill)((HTBill)(new HTBill(col, lv)).name("Paladin")).hp(11)).sides(new EntSide[]{ESB.shieldCleanse.val(4), ESB.dmgHeavy.val(4), ESB.healShield.val(3), ESB.healShield.val(3), ESB.dmgHeavy.val(4), ESB.dmgHeavy.val(4)})); bills.add(((HTBill)((HTBill)((HTBill)(new HTBill(col, lv)).name("Prince")).hp(11)).sides(ESB.dmgInspire.val(3), ESB.shieldDuplicate.val(3), ESB.healShield.val(3))).tactic(new Tactic("Unite", new TacticCost(new TacticCostType[]{TacticCostType.basicSword, TacticCostType.basicShield, TacticCostType.basicHeal, TacticCostType.blank}), (new EffBill()).damage(15).visual(VisualEffectType.Flame).bEff()))); bills.add((HTBill)((HTBill)((HTBill)(new HTBill(col, lv)).name("Stalwart")).hp(11)).sides(new EntSide[]{ESB.shieldCleanse.val(3), ESB.shieldCleanse.val(3), ESB.shieldCleave.val(2), ESB.shieldCleave.val(2), ESB.shieldDouble.val(2), ESB.dmgExert.val(5)})); bills.add(((HTBill)((HTBill)((HTBill)(new HTBill(col, lv)).name("Poet")).hp(9)).sides(ESB.manaCantrip.val(1), ESB.shieldAll.val(2), ESB.shieldCharged.val(2), ESB.shieldCharged.val(2), ESB.shieldCantrip.val(2))).spell((new SpellBill()).cost(4).title("clink").eff((new EffBill()).shield(1).group().keywords(new Keyword[]{Keyword.boost, Keyword.singleCast})))); bills.addAll(Arrays.asList((HTBill)((HTBill)((HTBill)(new HTBill(col, lv)).name("Valkyrie")).hp(9)).sides(new EntSide[]{ESB.dmgDeathwish.val(4), ESB.shieldRescue.val(2), ESB.undying, ESB.undying, ESB.resurrect.val(2), ESB.blank}), (HTBill)((HTBill)((HTBill)(new HTBill(col, lv)).name("Stoic")).hp(15)).sides(new EntSide[]{ESB.stun, ESB.redirect.val(3), ESB.dmgSelfShield.val(2), ESB.dmgSelfShield.val(2), ESB.redirect.val(2), ESB.redirect.val(1)}))); List<HeroType> result = new ArrayList(); Iterator var4 = bills.iterator();
B13: Orange Heroes | C13: public class HeroTypeBlobOrange { public static List<HeroType> makeDesigned() { List<HTBill> bills = new ArrayList(); HeroCol col = HeroCol.orange; int lv = 1; bills.add((HTBill)((HTBill)((HTBill)(new HTBill(col, lv)).name("Thief")).hp(4)).sides(new EntSide[]{ESB.arrow.val(2), ESB.dmg.val(2), ESB.blank, ESB.blank, ESB.dmg.val(2), ESB.blank})); bills.add((HTBill)((HTBill)((HTBill)(new HTBill(col, lv)).name("Scoundrel")).hp(6)).sides(ESB.dmgAll.val(1), ESB.dmgVuln.val(1))); bills.add((HTBill)((HTBill)((HTBill)(new HTBill(col, lv)).name("Lost")).hp(3)).sides(new EntSide[]{ESB.arrowPoison.val(1), ESB.dmgCruel.val(2), ESB.dmgCruel.val(1), ESB.dmgCruel.val(1), ESB.dodge, ESB.blank})); bills.add((HTBill)((HTBill)((HTBill)(new HTBill(col, lv)).name("Dabble")).hp(6)).sides(new EntSide[]{ESB.heal.val(5), ESB.shield.val(2), ESB.mana.val(1), ESB.mana.val(1), ESB.dmg.val(2), ESB.dmg.val(1)})); bills.add((HTBill)((HTBill)((HTBill)(new HTBill(col, lv)).name("Clumsy")).hp(5)).sides(new EntSide[]{ESB.dmgCantrip.val(1), ESB.dmgSelfCantrip.val(1), ESB.dmgCleave.val(1), ESB.dmgCleave.val(1), ESB.dmgCantrip.val(1), ESB.dmgSelfCantrip.val(1)})); lv = 2; bills.add((HTBill)((HTBill)((HTBill)(new HTBill(col, lv)).name("Dabbler")).hp(9)).sides(new EntSide[]{ESB.dmg.val(3), ESB.dmg.val(2), ESB.mana.val(2), ESB.heal.val(4), ESB.shield.val(2), ESB.shield.val(2)})); bills.add((HTBill)((HTBill)((HTBill)((HTBill)((HTBill)(new HTBill(col, lv)).name("Gambler")).hp(7)).sides(ESB.dmg.val(5), ESB.dmg.val(2), ESB.blank, ESB.blank, ESB.dmg.val(1))).trait(new Trait(new DieStopped(false, (Integer)null, EffType.Damage, true, new StateEvent[]{ChatStateEvent.GamblerCheer}), false))).trait(new Trait(new DieStopped(false, 0, EffType.Blank, (Boolean)null, new StateEvent[]{ChatStateEvent.GamblerBoo}), false))); bills.add((HTBill)((HTBill)((HTBill)(new HTBill(col, lv)).name("Ranger")).hp(7)).sides(new EntSide[]{ESB.rangedEngage.val(2), ESB.arrowCleave.val(1), ESB.arrowCleave.val(1), ESB.arrowCleave.val(1), ESB.arrow.val(2), ESB.blank})); bills.add((HTBill)((HTBill)((HTBill)(new HTBill(col, lv)).name("Rogue")).hp(7)).sides(new EntSide[]{ESB.dmgCruel.val(2), ESB.dmgCantrip.val(1), ESB.dmgPoison.val(1), ESB.dmgPoison.val(1), ESB.dmgCantrip.val(1), ESB.dodge})); bills.add((HTBill)((HTBill)((HTBill)(new HTBill(col, lv)).name("Trapper")).hp(8)).sides(ESB.headshot.val(4), ESB.dodge, ESB.dmgVuln.val(1), ESB.dmgVuln.val(1), ESB.dodge)); bills.add(((HTBill)((HTBill)((HTBill)(new HTBill(col, lv)).name("Spellblade")).hp(7)).sides(new EntSide[]{ESB.dmgCopycat.val(1), ESB.dmgPoison.val(1), ESB.dmgMana.val(1), ESB.dmgMana.val(1), ESB.mana.val(1), ESB.mana.val(1)})).spell((new SpellBill()).title("imbue").cost(1).eff((new EffBill()).visual(VisualEffectType.BoostSmith).friendly().keywords(new Keyword[]{Keyword.singleCast}).buff(new Buff(1, new AffectSides(new TypeCondition(EffType.Damage), new AffectSideEffect[]{new FlatBonus(1)})))))); bills.add((HTBill)((HTBill)((HTBill)(new HTBill(col, lv)).name("Ninja")).hp(6)).sides(new EntSide[]{ESB.dmgDouble.val(2), ESB.dmgCopycat.val(1), ESB.dmgCopycat.val(1), ESB.dmgCopycat.val(1), ESB.dodge, ESB.blank})); bills.add((HTBill)((HTBill)((HTBill)(new HTBill(col, lv)).name("Juggler")).hp(7)).sides(new EntSide[]{ESB.dmgCantrip.val(2), ESB.dmgCantrip.val(2), ESB.dmgCantrip.val(1), ESB.dmgCantrip.val(1), ESB.dmgSelfCantrip.val(1), ESB.blank})); bills.addAll(Arrays.asList()); lv = 3; bills.add((HTBill)((HTBill)((HTBill)((HTBill)((HTBill)(new HTBill(col, lv)).name("Ludus")).hp(6)).sides(new EntSide[]{ESB.dmg.val(6), ESB.dmg.val(5), ESB.dmg.val(4), ESB.dmg.val(3), ESB.dmg.val(1), ESB.dmg.val(2)})).trait(new Trait(new DieStopped(false, (Integer)null, (EffType)null, true, new StateEvent[]{ChatStateEvent.LudusCheer}), false))).trait(new Trait(new KillSpecificMonster("sudul", ChatStateEvent.Brother), false))); bills.add((HTBill)((HTBill)((HTBill)(new HTBill(col, lv)).name("Assassin")).hp(9)).sides(ESB.dmgCruel.val(4), ESB.dmgPoison.val(2), ESB.rangedEngage.val(2), ESB.rangedEngage.val(2), ESB.dodge)); bills.add((HTBill)((HTBill)((HTBill)(new HTBill(col, lv)).name("Dancer")).hp(8)).sides(new EntSide[]{ESB.dmgAllRampage.val(1), ESB.rerollCantrip.val(1), ESB.dmgCantrip.val(1), ESB.dmgCantrip.val(1), ESB.dmg.val(4), ESB.dodge})); bills.add((HTBill)((HTBill)((HTBill)(new HTBill(col, lv)).name("Fencer")).hp(9)).sides(ESB.dmgPristine.val(3), ESB.dmgAll.val(1), ESB.dmgDouble.val(2), ESB.dmgDouble.val(2), ESB.dodge)); bills.add((HTBill)((HTBill)((HTBill)(new HTBill(col, lv)).name("Sharpshot")).hp(8)).sides(new EntSide[]{ESB.headshot.val(6), ESB.arrow.val(3), ESB.arrow.val(3), ESB.arrow.val(3), ESB.arrowCopycat.val(2), ESB.blank})); bills.add((HTBill)((HTBill)((HTBill)(new HTBill(col, lv)).name("Venom")).hp(8)).sides(ESB.dosePoison.val(1), ESB.healCleanse.val(3), ESB.arrowPoison.val(2), ESB.arrowPoison.val(2))); bills.add((HTBill)((HTBill)((HTBill)(new HTBill(col, lv)).name("Roulette")).hp(8)).sides(new EntSide[]{ESB.swordRoulette.val(7), ESB.dmg.val(5), ESB.dmgCantrip.val(2), ESB.dmgCantrip.val(2), ESB.dmgCleave.val(2), ESB.dmgCleave.val(2)})); bills.add((HTBill)((HTBill)((HTBill)(new HTBill(col, lv)).name("Dabblest")).hp(9)).sides(new EntSide[]{ESB.mana.val(3), ESB.dmg.val(4), ESB.dmg.val(3), ESB.dmg.val(3), ESB.shield.val(5), ESB.heal.val(5)})); bills.add((HTBill)((HTBill)((HTBill)(new HTBill(col, lv)).name("Agent")).hp(9)).sides(new EntSide[]{ESB.wandInflictPain.val(1), ESB.dmgQuad.val(1), ESB.dmgShifter.val(3), ESB.dmgShifter.val(3), ESB.dmgQuad.val(1), ESB.blank})); List<HeroType> result = new ArrayList(); Iterator var4 = bills.iterator();
B14: Red Heroes | C14: public class HeroTypeBlobRed { public static List<HeroType> makeDesigned() { List<HTBill> bills = new ArrayList(); HeroCol col = HeroCol.red; int lv = 1; bills.add(((HTBill)((HTBill)((HTBill)(new HTBill(col, lv)).name("Healer")).hp(5)).sides(new EntSide[]{ESB.mana.val(2), ESB.mana.val(1), ESB.heal.val(4), ESB.heal.val(4), ESB.heal.val(2), ESB.heal.val(2)})).spell((new SpellBill()).cost(2).title("Mend").eff((new EffBill()).friendly().visual(VisualEffectType.HealBasic).setToHp(5)))); bills.add(((HTBill)((HTBill)((HTBill)(new HTBill(col, lv)).name("Gardener")).hp(5)).sides(ESB.mana.val(2), ESB.healGroooooowth.val(1), ESB.heal.val(2), ESB.heal.val(2), ESB.healMana.val(1))).spell((new SpellBill()).title("hemlock").cost(2).eff((new EffBill()).damage(1).keywords(new Keyword[]{Keyword.poison, Keyword.singleCast}).visual(VisualEffectType.Slice)))); bills.add(((HTBill)((HTBill)((HTBill)(new HTBill(col, lv)).name("Acolyte")).hp(5)).sides(new EntSide[]{ESB.healVitality.val(3), ESB.mana.val(1), ESB.healCleanse.val(1), ESB.healCleanse.val(1), ESB.mana.val(1), ESB.mana.val(1)})).spell((new SpellBill()).cost(2).title("restore").eff((new EffBill()).heal(1).group().visual(VisualEffectType.HealBasic)))); bills.add(((HTBill)((HTBill)((HTBill)(new HTBill(col, lv)).name("Mystic")).hp(4)).sides(ESB.healShieldMana.val(1), ESB.healMana.val(1), ESB.healMana.val(1), ESB.healMana.val(1), ESB.mana.val(1))).spell((new SpellBill()).cost(1).title("gaze").eff((new EffBill()).reroll(1).keywords(new Keyword[]{Keyword.future})))); bills.add(((HTBill)((HTBill)((HTBill)(new HTBill(col, lv)).name("Splint")).hp(4)).sides(new EntSide[]{ESB.wandMana.val(3), ESB.wandMana.val(2), ESB.wandHeal.val(5), ESB.wandHeal.val(5), ESB.wandMana.val(1), ESB.blank})).spell((new SpellBill()).cost(2).title("bandage").eff((new EffBill()).healAndShield(1).keywords(new Keyword[]{Keyword.singleCast, Keyword.cleave})))); lv = 2; bills.add(((HTBill)((HTBill)((HTBill)(new HTBill(col, lv)).name("Druid")).hp(7)).sides(new EntSide[]{ESB.damageGrowth.val(2), ESB.shieldGrowth.val(2), ESB.mana.val(2), ESB.mana.val(2), ESB.healCleanse.val(2), ESB.blank})).spell((new SpellBill()).cost(3).title("balance").eff((new EffBill()).damage(1).group().visual(VisualEffectType.Slice).bonusUntargeted(new EffBill[]{(new EffBill()).heal(1).group()})))); bills.add(((HTBill)((HTBill)((HTBill)(new HTBill(col, lv)).name("Herbalist")).hp(7)).sides(new EntSide[]{ESB.mana.val(2), ESB.mana.val(2), ESB.healRegen.val(1), ESB.healRegen.val(1), ESB.wandPoison.val(1), ESB.giveGrowth})).spell((new SpellBill()).title("vine").cost(1).eff((new EffBill()).or((new EffBill()).heal(1).visual(VisualEffectType.HealBasic), (new EffBill()).damage(1).visual(VisualEffectType.Slice))))); bills.add(((HTBill)((HTBill)((HTBill)(new HTBill(col, lv)).name("Medic")).hp(7)).sides(ESB.healRegen.val(2), ESB.mana.val(2), ESB.healCleave.val(2), ESB.healCleave.val(2))).spell((new SpellBill()).title("renew").cost(1).eff((new EffBill()).friendly().setToHp(4).visual(VisualEffectType.HealBasic)))); bills.add(((HTBill)((HTBill)((HTBill)(new HTBill(col, lv)).name("Priestess")).hp(5)).sides(new EntSide[]{ESB.healVitality.val(4), ESB.healVitality.val(4), ESB.healMana.val(1), ESB.healMana.val(1), ESB.healAll.val(1), ESB.healAll.val(1)})).spell((new SpellBill()).title("pray").cost(1).eff((new EffBill()).group().healAndShield(1).restrict(StateConditionType.Dying).keywords(new Keyword[]{Keyword.deplete}).visual(VisualEffectType.HealBasic)))); bills.add(((HTBill)((HTBill)((HTBill)(new HTBill(col, lv)).name("Vampire")).hp(7)).sides(new EntSide[]{ESB.mana.val(2), ESB.mana.val(2), ESB.dmgSelfHeal.val(2), ESB.dmgSelfHeal.val(2), ESB.heal.val(5), ESB.blank})).spell((new SpellBill()).cost(2).title("infuse").eff((new EffBill()).group().heal(1).keywords(new Keyword[]{Keyword.cruel}).visual(VisualEffectType.HealBasic)))); bills.add(((HTBill)((HTBill)((HTBill)(new HTBill(col, lv)).name("Enchanter")).hp(6)).sides(ESB.healShieldMana.val(2), ESB.giveEngage, ESB.giveSelfShieldSelfHeal, ESB.giveSelfShieldSelfHeal)).spell((new SpellBill()).title("flip").cost(2).eff((new EffBill()).friendly().group().buff(new Buff(1, new AffectSides(new AffectSideEffect[]{new Flip()})))))); bills.add(((HTBill)((HTBill)((HTBill)(new HTBill(col, lv)).name("Disciple")).hp(8)).sides(new EntSide[]{ESB.healDouble.val(2), ESB.healDouble.val(2), ESB.mana.val(2), ESB.mana.val(2), ESB.resurrect.val(1), ESB.blank})).spell((new SpellBill()).cost(1).title("Glow").eff((new EffBill()).replaceBlanksWith(ESB.healShield.val(2))))); bills.add(((HTBill)((HTBill)((HTBill)(new HTBill(col, lv)).name("Fey")).hp(5)).sides(new EntSide[]{ESB.dmgWeaken.val(1), ESB.dmgWeaken.val(1), ESB.healMana.val(1), ESB.healMana.val(1), ESB.healBoost.val(1), ESB.healBoost.val(1)})).spell((new SpellBill()).cost(2).title("circle").eff((new EffBill()).friendly().keywords(new Keyword[]{Keyword.singleCast}).group().specialAddKeyword(new Keyword[]{Keyword.selfHeal}).visual(VisualEffectType.HealBasic)))); lv = 3; bills.add(((HTBill)((HTBill)((HTBill)(new HTBill(col, lv)).name("Doctor")).hp(10)).sides(new EntSide[]{ESB.poisonAll.val(1), ESB.healMana.val(2), ESB.healRegen.val(2), ESB.healRegen.val(2), ESB.healMana.val(2), ESB.blank})).spell((new SpellBill()).cost(3).title("liquor").eff((new EffBill()).keywords(new Keyword[]{Keyword.cleanse}).heal(10).visual(VisualEffectType.HealBasic)))); bills.add(((HTBill)((HTBill)((HTBill)(new HTBill(col, lv)).name("Forsaken")).hp(9)).sides(new EntSide[]{ESB.resurrect.val(3), ESB.dmgSelfHeal.val(3), ESB.healAll.val(2), ESB.healAll.val(2), ESB.dmgSelfHeal.val(3), ESB.manaPain.val(3)})).spell((new SpellBill()).title("bind").cost(3).eff((new EffBill()).friendly().keywords(new Keyword[]{Keyword.deplete}).visual(VisualEffectType.HealBasic).buff(new Buff(1, new DamageImmunity(true, true)))))); bills.add(((HTBill)((HTBill)((HTBill)(new HTBill(col, lv)).name("Prophet")).hp(8)).sides(new EntSide[]{ESB.healRescue.val(3), ESB.healVitality.val(5), ESB.healMana.val(2), ESB.healMana.val(2), ESB.healVitality.val(5), ESB.blank})).spell((new SpellBill()).title("soothe").cost(4).eff((new EffBill()).heal(1).visual(VisualEffectType.HealBasic).group().keywords(new Keyword[]{Keyword.regen})))); bills.add(((HTBill)((HTBill)((HTBill)(new HTBill(col, lv)).name("Shaman")).hp(11)).sides(new EntSide[]{ESB.healVitality.val(5), ESB.heal.val(10), ESB.damageGrowth.val(3), ESB.shieldGrowth.val(3), ESB.healMana.val(2), ESB.blank})).spell((new SpellBill()).title("ritual").cost(3).eff((new EffBill()).visual(VisualEffectType.HealBasic).heal(2).keywords(new Keyword[]{Keyword.cleanse, Keyword.cleave})))); bills.add(((HTBill)((HTBill)((HTBill)(new HTBill(col, lv)).name("Witch")).hp(10)).sides(new EntSide[]{ESB.mana.val(3), ESB.healCleanse.val(5), ESB.healBoost.val(1), ESB.dmgWeaken.val(1), ESB.healCleave.val(3), ESB.blank})).spell((new SpellBill()).cost(1).title("salve").eff((new EffBill()).visual(VisualEffectType.HealBasic).heal(2)))); bills.add(((HTBill)((HTBill)((HTBill)(new HTBill(col, lv)).name("Wraith")).hp(9)).sides(new EntSide[]{ESB.dmgSelfHeal.val(4), ESB.giveSelfShieldSelfHeal, ESB.mana.val(2), ESB.mana.val(2), ESB.dodgeCantrip, ESB.blank})).spell((new SpellBill()).cost(1).title("Leech").eff((new EffBill()).friendly().keywords(new Keyword[]{Keyword.cooldown}).kill().bonusUntargeted(new EffBill[]{(new EffBill()).heal(5).group()})))); bills.add(((HTBill)((HTBill)((HTBill)(new HTBill(col, lv)).name("Surgeon")).hp(10)).sides(new EntSide[]{ESB.healMana.val(2), ESB.healMana.val(2), ESB.healShield.val(3), ESB.healShield.val(3), ESB.healDouble.val(3), ESB.healDouble.val(3)})).spell((new SpellBill()).cost(3).title("Operate").eff((new EffBill()).keywords(new Keyword[]{Keyword.deplete}).resurrect(1)))); bills.add(((HTBill)((HTBill)((HTBill)(new HTBill(col, lv)).name("Fate")).hp(8)).sides(new EntSide[]{ESB.healShieldMana.val(2), ESB.healShieldMana.val(2), ESB.wandMana.val(2), ESB.wandMana.val(2), ESB.dodge, ESB.blank})).spell((new SpellBill()).cost(4).title("Strand").eff((new EffBill()).friendly().heal(2).keywords(new Keyword[]{Keyword.spellRescue})))); List<HeroType> result = new ArrayList(); Iterator var4 = bills.iterator();
... B20: Keywords | C20: shield(Colours.grey, "shield the target for " + KUtils.describeN(), (String)null, KeywordAllowType.TARG_PIPS), damage(Colours.orange, "damage the target for " + KUtils.describeN(), (String)null, KeywordAllowType.TARG_PIPS), manaGain(Colours.blue, "gain " + KUtils.describeN() + " " + Words.manaString(), (String)null, KeywordAllowType.PIPS_ONLY), engage(Colours.yellow, "with full hp", StateConditionType.FullHP, false), pristine(Colours.light, "have full hp", StateConditionType.FullHP, true), cruel(Colours.orange, "on half or less hp", StateConditionType.HalfOrLessHP, false), deathwish(Colours.purple, "am dying " + KUtils.describeThisTurn(), StateConditionType.Dying, true), armoured(Colours.light, "have shields", StateConditionType.HasShields, true), wham(Colours.light, "with shields", StateConditionType.HasShields, false), moxie(Colours.yellow, "have the least hp of all", StateConditionType.LeastHP, true), bully(Colours.orange, "have the most hp of all", StateConditionType.MostHP, true), squish(Colours.yellow, "with the least hp of all", StateConditionType.LeastHP, false), uppercut(Colours.orange, "with the most hp of all", StateConditionType.MostHP, false), terminal(Colours.purple, "on 1 hp", new ParamCondition(ParamConType.ExactlyHp, 1, false)), ego(Colours.yellow, "myself", EnumConditionalRequirement.SelfTarget), serrated(Colours.red, "who have gained no shields this turn", StateConditionType.GainedNoShields, false), reborn(Colours.yellow, "died this fight", StateConditionType.Died, true), century(Colours.grey, "with 100+ hp", new ParamCondition(ParamConType.OrMoreHp, 100, false)), sixth(Colours.orange, "this is the 6th dice you use this turn", EnumConditionalRequirement.SixthDiceUsed), duel(Colours.blue, "those targeting me this turn", EnumConditionalRequirement.TargetTargetingMe), chain(Colours.pink, "this shares a keyword with the " + KUtils.describePreviousDice(), EnumConditionalRequirement.PreviousAbilitySharesKeyword), inspired(Colours.green, "the " + KUtils.describePreviousDice() + " was higher", EnumConditionalRequirement.PreviousAbilityHigher), tall(Colours.orange, "the topmost target", EnumConditionalRequirement.Top), underdog(Colours.yellow, "targets with more hp than me", EnumConditionalRequirement.LessHpThanTarget), overdog(Colours.yellow, "targets with less hp than me", EnumConditionalRequirement.MoreHpThanTarget), dog(Colours.yellow, "targets with equal hp to me", EnumConditionalRequirement.SameHpAsTarget), hyena(Colours.yellow, "targets with whom our hp is co-prime", EnumConditionalRequirement.CoprimeWithTarget), patient(Colours.light, "I was not used last turn", EnumConditionalRequirement.UnusedLastTurn), focus(Colours.orange, "the target of the " + KUtils.describePreviousDice(), EnumConditionalRequirement.PreviousAbilitySameTarget), alliteration(Colours.light, "targets with the same first letter as me", EnumConditionalRequirement.SameFirstLetterAsTarget), first(Colours.light, "no dice have been used this turn", EnumConditionalRequirement.NoOtherDice), step(Colours.grey, "x2 if " + KUtils.descStraight(2), "eg 12, 65", new ConditionalBonus(EnumConditionalRequirement.RunOfTwo, ConditionalBonusType.Multiply, 2)), run(Colours.yellow, "x3 if " + KUtils.descStraight(3), " eg 123, 654", new ConditionalBonus(EnumConditionalRequirement.RunOfThree, ConditionalBonusType.Multiply, 3)), sprint(Colours.orange, "x5 if " + KUtils.descStraight(5), "eg 12345, 65432", new ConditionalBonus(EnumConditionalRequirement.RunOfFive, ConditionalBonusType.Multiply, 5)), revDiff(Colours.red, "inverted pip delta", (String)null, KeywordAllowType.PIPS_ONLY), doubDiff(Colours.yellow, "doubled pip delta", (String)null, KeywordAllowType.PIPS_ONLY), pair(2), trio(3), quin(5), sept(7), rampage(Colours.purple, "can be reused if it was lethal", (String)null, KeywordAllowType.DEATHCHECK), rescue(Colours.yellow, "this side can be used again if it saves a hero", (String)null, KeywordAllowType.DEATHCHECK), guilt(Colours.orange, "if this is lethal, I die", (String)null, KeywordAllowType.DEATHCHECK), evil(Colours.red, "if this saves a hero, I die", (String)null, KeywordAllowType.DEATHCHECK), cantrip(Colours.pink, "activates during rolling if it lands face-up", "Targets chosen randomly. This one is a bit weird... Whilst rolling dice, if this side lands face-up, it gets used instantly without taking up that hero's turn. You can still reroll it and use it as normal.", KeywordAllowType.CANTRIP), stasis(Colours.blue, "this side cannot change", (String)null, KeywordAllowType.YES), fizz(Colours.blue, KUtils.describePipBonus("ability used this turn"), (String)null, new ConditionalBonus(ConditionalBonusType.AbilitiesUsed)), skill(Colours.light, KUtils.describePipBonus("equal to my level"), (String)null, new ConditionalBonus(ConditionalBonusType.MyTier)), bloodlust(Colours.red, KUtils.describePipBonus("damaged " + Words.entName(true, false, (Boolean)null)), "Pips on this side are increased by 1 for each damaged " + Words.entName(true, false, (Boolean)null), new ConditionalBonus(ConditionalBonusType.DamagedEnemies)), defy(Colours.yellow, KUtils.describePipBonus("incoming damage"), (String)null, new ConditionalBonus(ConditionalBonusType.IncomingDamage)), charged(Colours.blue, KUtils.describePipBonus("stored " + Words.manaString()), "Pips on this side are increased by 1 for each mana you have stored", new ConditionalBonus(ConditionalBonusType.CurrentMana)), steel(Colours.light, KUtils.describePipBonus("shield I have"), "Pips on this side are increased by an amount equal to my current shields", new ConditionalBonus(ConditionalBonusType.MyShields)), flesh(Colours.red, KUtils.describePipBonus("hp I have"), (String)null, new ConditionalBonus(ConditionalBonusType.CurrentHP)), rainbow(Colours.light, KUtils.describePipBonus("keyword on this side"), (String)null, new ConditionalBonus(ConditionalBonusType.NumKeywords)), hoard(Colours.orange, KUtils.describePipBonus("unequipped items"), (String)null, new ConditionalBonus(ConditionalBonusType.BagItems)), plague(Colours.green, KUtils.describePipBonus("poison on all characters"), "", new ConditionalBonus(ConditionalBonusType.TotalPoison)), acidic(Colours.green, KUtils.describePipBonus("poison on me"), "", new ConditionalBonus(ConditionalBonusType.MyPoison)), vigil(Colours.light, KUtils.describePipBonus("defeated ally"), (String)null, new ConditionalBonus(ConditionalBonusType.DeadAllies)), flurry(Colours.orange, KUtils.describePipBonus("time I have been used this turn"), (String)null, new ConditionalBonus(ConditionalBonusType.TimesUsedThisTurn)), fashionable(Colours.blue, KUtils.describePipBonus("equal to the total tier of all items I have equipped"), (String)null, new ConditionalBonus(ConditionalBonusType.TotalItemTier)), equipped(Colours.grey, KUtils.describePipBonus("item I have equipped"), (String)null, new ConditionalBonus(ConditionalBonusType.ItemsEquipped)), buffed(Colours.light, KUtils.describePipBonus("buff I have"), (String)null, new ConditionalBonus(ConditionalBonusType.Buffs)), affected(Colours.purple, KUtils.describePipBonus("'thing' affecting me"), (String)null, new ConditionalBonus(ConditionalBonusType.Triggers)), rite(Colours.green, "+1 for each unused ally, they become used", (String)null, new ConditionalBonus(ConditionalBonusType.UnusedAllies)), growth(Colours.green, "gets " + KUtils.describeBeingIncreased() + " " + KUtils.describeThisFight() + " after use", "Every time you use this side, the pips on it increase by 1 for this fight only", KeywordAllowType.PIPS_ONLY), hyperGrowth(Colours.green, "gets " + KUtils.describeN(true) + " pips " + KUtils.describeThisFight() + " after use", (String)null, KeywordAllowType.PIPS_TOUCHUSABLE), undergrowth(Colours.green, "After use, the opposite side gets " + KUtils.describeBeingIncreased() + " " + KUtils.describeThisFight(), (String)null, KeywordAllowType.NONBLANK), groooooowth(Colours.green, "After use, [b]all[b] my sides get " + KUtils.describeBeingIncreased() + " " + KUtils.describeThisFight(), (String)null, KeywordAllowType.NONBLANK), decay(Colours.purple, "gets " + KUtils.describeBeingDecreased() + " " + KUtils.describeThisFight() + " after use", (String)null, KeywordAllowType.PIPS_ONLY), era(Colours.blue, KUtils.describePipBonus("elapsed turn"), (String)null, new ConditionalBonus(ConditionalBonusType.ElapsedTurns)), lead(Colours.yellow, "After use, other hero's sides that share a type with this get " + KUtils.describeN(true) + " " + KUtils.describeThisTurn(), (String)null, KeywordAllowType.PIPS_ONLY), vulnerable(Colours.orange, "target takes " + KUtils.describeN(true) + " damage from dice & " + Words.spabKeyword(true) + " " + KUtils.describeOneTurn(), "The amount of extra damage taken is equal to the pips on this side.", KeywordAllowType.UNKIND_TARG_PIPS), regen(Colours.red, "heal for " + KUtils.describeN() + " at the end of each turn", "The amount of health regenerated is equal to the pips on the side.", KeywordAllowType.KIND_TARG_PIPS), poison(Colours.green, "also inflicts " + KUtils.describeN() + " unblockable damage at the end of each turn", "The amount of poison damage is equal to the pips on the side. The poison part of poison damage is unblockable. You can't prevent yourself from being poisoned except by using cleanse or killing the attacking monster.", KeywordAllowType.UNKIND_TARG_PIPS), weaken(Colours.green, "target gets " + KUtils.describeN(false) + " to all pips " + KUtils.describeOneTurn(), "The amount decreased is equal to the pips on this side.", KeywordAllowType.UNKIND_TARG_PIPS), boost(Colours.blue, "target gets " + KUtils.describeN(true) + " to all pips " + KUtils.describeOneTurn(), "The increase is equal to the pips on this side.", KeywordAllowType.KIND_TARG_PIPS), smith(Colours.light, "target gets " + KUtils.describeN(true) + " to damage and shield sides " + KUtils.describeOneTurn(), (String)null, KeywordAllowType.KIND_TARG_PIPS), permaBoost(Colours.pink, "target gets " + KUtils.describeN(true) + " to all pips " + KUtils.describeThisFight(), (String)null, KeywordAllowType.KIND_TARG_PIPS), petrify(Colours.yellow, "transforms " + KUtils.describeN() + " sides to stone " + KUtils.describeThisFight(), "Petrification order: [white][petrify-diagram]", KeywordAllowType.UNKIND_TARG_PIPS), hypnotise(Colours.orange, "set target's damage sides to 0 " + KUtils.describeThisTurn(), (String)null, KeywordAllowType.UNKIND_TARG), dispel(Colours.pink, "remove all traits from the target " + KUtils.describeThisFight(), "", KeywordAllowType.UNKIND_TARG), eliminate(Colours.red, "target must have the least hp", "if a monster has this, they include incoming damage in their calculations (and their targets are locked)", TargetingRestriction.LeastHp), heavy(Colours.yellow, "target must have the most hp", "if a monster has this, they include incoming damage in their calculations (and their targets are locked)", TargetingRestriction.MostHealth), generous(Colours.light, "cannot target myself", (String)null, TargetingRestriction.NotMe), scared(Colours.purple, "target must have " + KUtils.describeN() + " or less hp", (String)null, TargetingRestriction.OrLessHp), picky(Colours.blue, "target must have exactly " + KUtils.describeN() + " hp", (String)null, TargetingRestriction.ExactlyValue), unusable(Colours.grey, "cannot be used (manually)", cantrip.getColourTaggedString() + " is still allowed", KeywordAllowType.NONBLANK), vitality(Colours.light, "grants the target " + KUtils.describeN(true) + " empty max hp " + KUtils.describeThisFight(), (String)null, KeywordAllowType.KIND_TARG_PIPS), wither(Colours.green, "grants the target " + KUtils.describeN(false) + " max hp " + KUtils.describeThisFight(), (String)null, KeywordAllowType.UNKIND_TARG_PIPS), ranged(Colours.light, "can target enemies in the back row and avoids " + OnHit.ONHIT().toLowerCase() + " passives", "Some enemies start in the back row and others can move to the back row during combat. These can only be targeted by ranged abilities. It's also useful against certain enemy passives.", KeywordAllowType.ENEMY_TARG), fierce(Colours.yellow, "target flees if they have " + KUtils.describeN() + " or less hp [grey](after)", (String)null, KeywordAllowType.UNKIND_TARG_PIPS), fault(Colours.blue, KUtils.describeOthersSeeingNPips("[purple]-1[cu]"), (String)null, KeywordAllowType.PIPS_ONLY), plus(Colours.grey, KUtils.describeOthersSeeingNPips(KUtils.describeNP1()), (String)null, KeywordAllowType.PIPS_ONLY), doubled(Colours.blue, KUtils.describeOthersSeeingNPips(KUtils.describe2N()), (String)null, KeywordAllowType.PIPS_ONLY), squared(Colours.pink, KUtils.describeOthersSeeingNPips(KUtils.describeNSQ()), (String)null, KeywordAllowType.PIPS_ONLY), onesie(Colours.grey, KUtils.describeOthersSeeingNPips(KUtils.describeOne()), (String)null, KeywordAllowType.PIPS_ONLY), threesy(Colours.orange, KUtils.describeOthersSeeingNPips(KUtils.describeThree()), (String)null, KeywordAllowType.PIPS_ONLY), zeroed(Colours.grey, KUtils.describeOthersSeeingNPips("[grey]0[cu]"), (String)null, KeywordAllowType.PIPS_ONLY), treble(Colours.light, "Other keywords x2 -> x3", (String)null, KeywordAllowType.PIPS_ONLY), pain(Colours.red, "I take " + KUtils.describeN() + " damage", "Pain damage can be blocked. Damage is resolved in an order favourable to the player always (I hope)", KeywordAllowType.PIPS_ONLY), boned(Colours.light, "Summon a bones", (String)null, KeywordAllowType.PIPS_ONLY), hyperBoned(Colours.light, "Summon " + KUtils.describeN() + " bones", (String)null, KeywordAllowType.PIPS_ONLY), potion(Colours.purple, "I discard my topmost 'potion' item permanently", (String)null, KeywordAllowType.NONBLANK), singleUse(Colours.orange, "after I use this side, replace it with a blank " + KUtils.describeThisFight(), (String)null, KeywordAllowType.NONBLANK), doubleUse(Colours.orange, "can be used twice in a turn", (String)null, KeywordAllowType.NONBLANK_TOUCHUSABLE), quadUse(Colours.orange, "can be used 4 times in a turn", (String)null, KeywordAllowType.NONBLANK_TOUCHUSABLE), hyperUse(Colours.orange, "can be used " + KUtils.describeN() + " times in a turn", (String)null, KeywordAllowType.PIPS_TOUCHUSABLE), cleave(Colours.light, "also hits both sides of the target", "can be used to hit " + Words.entName(false, true) + " in the back row indirectly", KeywordAllowType.SINGLE_TARGET), descend(Colours.light, "also hits below the target", (String)null, KeywordAllowType.SINGLE_TARGET), repel(Colours.orange, KUtils.describeN() + " damage to all " + Words.entName(false, true) + " attacking the target", (String)null, KeywordAllowType.ALLY_TARG_PIPS), cleanse(Colours.light, "reduce target's negative effects by " + KUtils.describeN() + "[n][grey]([p]" + Tann.commaList(Arrays.asList("poisoned", "weakened", "petrified", "inflicted"), "[p], ", " and ") + "[p])", "Cleanse can remove poisoned, weakened, petrified and inflicted. It also affects incoming negative effects.", KeywordAllowType.TARG_PIPS), duplicate(Colours.blue, "copy this onto all allied sides " + KUtils.describeOneTurn(), "this one's a bit complicated, you'll have figure it out yourself. Bonuses are usually copied, but not for static bonuses like " + charged.getColourTaggedString() + " (or something...)", KeywordAllowType.NONBLANK), selfRepel(repel, new long[0]), selfPetrify(petrify, new long[0]), selfPoison(poison, new long[0]), selfRegen(regen, new long[0]), selfCleanse(cleanse, new long[0]), selfVulnerable(vulnerable, new long[0]), selfShield(Colours.light, "shield myself for " + KUtils.describeN(), (String)null, KeywordAllowType.PIPS_ONLY), selfHeal(Colours.red, "heal myself for " + KUtils.describeN(), (String)null, KeywordAllowType.PIPS_ONLY), death(Colours.light, "I die", "everyone has to some day", KeywordAllowType.NONBLANK), exert(Colours.purple, "replace all sides with blanks until the end of next turn", (String)null, KeywordAllowType.NONBLANK), mandatory(Colours.red, "must be used (if possible)", (String)null, KeywordAllowType.NONBLANK), manacost(Colours.purple, "costs " + KUtils.describeN() + " mana", (String)null, KeywordAllowType.PIPS_ONLY), permissive(Colours.pink, "any keyword can be added to this", (String)null, KeywordAllowType.YES), sticky(Colours.purple, "cannot be rerolled", (String)null, KeywordAllowType.YES), enduring(Colours.grey, KUtils.describedRemainingWhenReplaced("keywords"), (String)null, KeywordAllowType.YES), dogma(Colours.yellow, "Only pips change when the side is replaced", (String)null, KeywordAllowType.YES), resilient(Colours.orange, KUtils.describedRemainingWhenReplaced("pips"), (String)null, KeywordAllowType.YES), spy(Colours.grey, "copy all keywords from the first enemy attack", "I don't know", KeywordAllowType.NONBLANK), dejavu(Colours.pink, "copy the keywords from the sides I used last turn", (String)null, KeywordAllowType.NONBLANK), echo(Colours.blue, "copy the pips of the " + KUtils.describePreviousDice(), (String)null, KeywordAllowType.PIPS_ONLY), copycat(Colours.light, "copy the keywords from the " + KUtils.describePreviousDice(), (String)null, KeywordAllowType.NONBLANK), resonate(Colours.pink, "copy the effect of the " + KUtils.describePreviousDice() + ", retaining this side's pips and the [pink]resonate[cu] keyword", (String)null, KeywordAllowType.YES), share(Colours.light, "targets gain all my keywords " + KUtils.describeThisTurn() + " [grey](except share)", (String)null, KeywordAllowType.TARGET_ONLY_NOT_SELF), annul(Colours.grey, "targets lose all keywords this turn", (String)null, KeywordAllowType.TARGET_ONLY), possessed(Colours.purple, "targets as if used by the other side", (String)null, KeywordAllowType.TARGET_ONLY_NOT_SELF), shifter(Colours.pink, "this side has a random extra keyword, changes each turn", (String)null, KeywordAllowType.NONBLANK), lucky(Colours.red, "pips are randomised to between 0 and current pips, changes each turn", (String)null, KeywordAllowType.PIPS_ONLY), critical(Colours.yellow, "50% chance for +1, rechecks each turn", (String)null, KeywordAllowType.PIPS_ONLY), fluctuate(Colours.blue, "changes to a random side each turn, retaining keywords and pips", (String)null, KeywordAllowType.YES), fumble(Colours.grey, "50% chance to be blank each turn", (String)null, KeywordAllowType.NONBLANK), nothing(Colours.grey, "this keyword has no effect", (String)null, KeywordAllowType.YES), tactical(Colours.orange, "counts twice for tactic costs", (String)null, KeywordAllowType.YES), groupExert(exert, false), groupGrowth(growth, true), groupDecay(decay, true), groupSingleUse(singleUse, true), groupGroooooowth(groooooowth, false), doubleGrowth(growth, 0.0F, 0.0F), halveEngage(engage, new float[0]), halveDeathwish(deathwish, new float[0]), halveDuel(duel, new float[0]), antiEngage(engage, 1.0D), antiPristine(pristine, 1.0D), antiDog(dog, 1.0D), antiDeathwish(deathwish, 1.0D), antiPair(pair, 1.0D), swapDeathwish(deathwish, new int[0]), swapCruel(cruel, new int[0]), swapEngage(engage, new int[0]), swapTerminal(terminal, new int[0]), minusFlesh(flesh, 1.0F), minusEra(era, 1.0F), engarged(engage, charged, KeywordCombineType.ConditionBonus), cruesh(cruel, flesh, KeywordCombineType.ConditionBonus), pristeel(pristine, steel, KeywordCombineType.ConditionBonus), deathlust(deathwish, bloodlust, KeywordCombineType.ConditionBonus), trill(trio, skill, KeywordCombineType.ConditionBonus), duegue(duel, plague, KeywordCombineType.ConditionBonus), engine(engage, pristine, KeywordCombineType.TC4X), underocus(underdog, focus, KeywordCombineType.TC4X), priswish(pristine, deathwish, KeywordCombineType.TC4X), paxin(pair, chain, KeywordCombineType.XOR), inflictSelfShield(selfShield), inflictBoned(boned), inflictExert(exert), inflictPain(pain), inflictDeath(death), inflictSingleUse(singleUse), inflictNothing(nothing), inflictInflictNothing(inflictNothing), inflictInflictDeath(inflictDeath), singleCast(Colours.purple, "can only be cast once each fight", (String)null, KeywordAllowType.SPELL), cooldown(Colours.orange, "can only be cast once each turn", (String)null, KeywordAllowType.SPELL), deplete(Colours.orange, "costs +1 mana each time it is cast", (String)null, KeywordAllowType.SPELL), channel(Colours.green, "costs -1 mana each time it is cast (minimum 1)", (String)null, KeywordAllowType.SPELL), spellRescue(Colours.yellow, "cost is refunded if it saves a hero", (String)null, KeywordAllowType.SPELL), future(Colours.blue, "effect is delayed until the start of next turn", (String)null, KeywordAllowType.SPELL), removed(Colours.light, "something has been removed, you probably shouldn't be seeing this...", (String)null, KeywordAllowType.NO);
C21: private final KeywordAllowType allowType; private final String name; private final Color col; private final String rules; private final String extraRules; private final TextureRegion corner; private final TextureRegion cornerTiny; private final boolean flipCorner; private boolean doubleAct; private ConditionalRequirement targetingRequirement; private ConditionalBonus conditionalBonus; private Keyword inflict; private Keyword groupAct; private Keyword metaKeyword; private Keyword metaKeyword2; private Keyword(Color col, String rules, String extraRules, KeywordAllowType kat) { if (kat == null) { throw new RuntimeException("Invalid keyword kat: " + this.name()); } else { this.allowType = kat; this.name = this.name(); this.rules = rules; this.col = col; this.extraRules = extraRules; String texName = this.name().toLowerCase(); List<AtlasRegion> regions = Tann.getRegionsStartingWith(Main.atlas_3d, "keyword/" + texName.replaceAll(" ", "-")); if (regions.size() == 1) { this.corner = (TextureRegion)regions.get(0); this.flipCorner = !((AtlasRegion)regions.get(0)).name.contains("xx"); } else if (regions.size() == 0) { this.corner = KUtils.makePlaceholderCorner(this); this.flipCorner = true; } else { this.corner = (TextureRegion)regions.get(0); this.flipCorner = !((AtlasRegion)regions.get(0)).name.contains("xx"); } this.cornerTiny = ImageUtils.loadExt3d("keyword/small/" + TextWriter.getNameForColour(col)); } } private Keyword(Color col, String rules, String extraRules, ConditionalBonus bonus) { this(col, rules, extraRules, bonus, katFromBonus(bonus)); } private static KeywordAllowType katFromBonus(ConditionalBonus bonus) { if (bonus.requirement == EnumConditionalRequirement.SelfTarget) { return KeywordAllowType.ALLY_TARG_PIPS; } else if (bonus.requirement == EnumConditionalRequirement.TargetTargetingMe) { return KeywordAllowType.ENEMY_TARG_PIPS; } else { return bonus.requirement.preCalculate() ? KeywordAllowType.PIPS_ONLY : KeywordAllowType.TARG_PIPS; } } private Keyword(Color col, String rules, String extraRules, ConditionalBonus bonus, KeywordAllowType kat) { this(col, rules, extraRules, kat); this.conditionalBonus = bonus; } private Keyword(Keyword toInvertBonus, float sigInvertBonusAmount) { this(toInvertBonus.col, NotRequirement.transform(toInvertBonus.rules), (String)null, (ConditionalBonus)(new InvertBonus(toInvertBonus.conditionalBonus.bonusType))); this.metaKeyword = toInvertBonus; } private Keyword(Keyword toAntiRequirement, double sigAntiRequirement) { this(toAntiRequirement.col, NotRequirement.transform(toAntiRequirement.rules), (String)null, (ConditionalBonus)toAntiRequirement.getConditionalBonus().antiRequirement()); this.metaKeyword = toAntiRequirement; } private Keyword(Keyword toHalve, float[] sigHalve) { this(toHalve.col, toHalve.getRules().replaceAll("x2", "x0.5 (rounded down)"), (String)null, (ConditionalBonus)toHalve.getConditionalBonus().halveVersion()); this.metaKeyword = toHalve; } private Keyword(Keyword toSwap, int[] sigSwap) { this(toSwap.col, KUtils.swapRules(toSwap), (String)null, KUtils.getSwapBonus(toSwap), KUtils.getSwapRequirement(toSwap)); this.metaKeyword = toSwap; } private Keyword(Keyword inflict) { this(inflict.col, KUtils.describeAdding(inflict), (String)null, (ConditionalBonus)null, KeywordAllowType.TARGET_ONLY); this.inflict = inflict; this.metaKeyword = inflict; } private Keyword(Keyword groupAct, boolean side) { this(groupAct.col, KUtils.describeGroupActivate(groupAct, side), (String)null, (ConditionalBonus)null, KeywordAllowType.NONBLANK); this.groupAct = groupAct; this.metaKeyword = groupAct; } private Keyword(Keyword toDouble, float siga, float sigb) { this(toDouble.col, "Like " + toDouble.getColourTaggedString() + " but activates twice", (String)null, (KeywordAllowType)toDouble.allowType); this.doubleAct = true; this.metaKeyword = toDouble; } private Keyword(Keyword metaHitSelf, long[] hitSelfSig) { this(metaHitSelf.col, "Like " + metaHitSelf.getColourTaggedString() + " but hits me instead of the target", "", KeywordAllowType.PIPS_ONLY); this.metaKeyword = metaHitSelf; } private Keyword(Keyword a, Keyword b, KeywordCombineType kct) { this(a.col, KUtils.describeCombination(a, b, kct), (String)null, (ConditionalBonus)KUtils.getConditionalBonus(a, b, kct)); this.metaKeyword = a; this.metaKeyword2 = b; } private Keyword(int ofAKind) { this(Colours.light, "x" + ofAKind + " if " + KUtils.describeHavingSameValueAsLastNDice(ofAKind - 1), (String)null, (ConditionalBonus)(new ConditionalBonus(EnumConditionalRequirement.previousNSame(ofAKind - 1), ConditionalBonusType.Multiply, ofAKind))); } private Keyword(Color col, String rules, String extraRules, ConditionalRequirement targetingRequirement) { this(col, rules, extraRules, (ConditionalBonus)null, KUtils.getKATFromTargetingRequirement(targetingRequirement)); this.targetingRequirement = targetingRequirement; } private Keyword(Color col, String x2if, StateConditionType condType, boolean source) { this(col, source ? "x2 if I " + x2if : "x2 vs targets " + x2if, (String)null, (ConditionalBonus)(new ConditionalBonus(condType, source))); } private Keyword(Color col, String x2if, ParamCondition x2Condition) { this(col, x2Condition.isSource() ? "x2 if I " + x2if : "x2 vs targets " + x2if, (String)null, (ConditionalBonus)(new ConditionalBonus(x2Condition))); } private Keyword(Color col, String x2if, EnumConditionalRequirement x2Condition) { this(col, (x2Condition.preCalculate() ? "x2 if " : "x2 vs ") + x2if, (String)null, (ConditionalBonus)(new ConditionalBonus(x2Condition))); } public static List<Keyword> search(String text) { text = text.toLowerCase(); List<Keyword> result = new ArrayList(); Keyword[] var2 = values(); int var3 = var2.length; for(int var4 = 0; var4 < var3; ++var4) { Keyword k = var2[var4]; if (k.name.toLowerCase().contains(text)) { result.add(k); } } return result; } public static Keyword byName(String text) { text = text.toLowerCase(); Keyword[] var1 = values(); int var2 = var1.length; for(int var3 = 0; var3 < var2; ++var3) { Keyword k = var1[var3]; if (k.name.toLowerCase().equals(text)) { return k; } if (k.name().toLowerCase().equals(text)) { return k; } } return null; } public String toString() { return this.name != null ? this.name : super.toString(); } public String getRules() { return this.getRules((Eff)null); } public String getRules(Eff source) { String colTag = TextWriter.getTag(this.getColour()); if (source != null && source.getValue() != -999) { int val = KUtils.getValue(source); if (this.rules.contains("ther keywords see ")) { val = source.getValue(); } String tmp = this.rules; if (source.hasKeyword(treble) && this != treble) { tmp = tmp.replaceAll("x2", "x3"); } return tmp.replace("!N!", colTag + val + "[cu]").replace("!2N!", colTag + val * 2 + "[cu]").replace("!NP1!", colTag + (val + 1) + "[cu]").replace("!N2!", colTag + val * val + "[cu]"); } else { return this.rules.replaceAll("!N!", colTag + "N[cu]").replaceAll("!2N!", colTag + "2N[cu]").replaceAll("!NP1!", colTag + "N+1[cu]").replaceAll("!N2!", colTag + "N-squared[cu]"); } } public String getColourTaggedString() { String n; if (this == rainbow) { n = "[p][cu]"; String[] cols = new String[]{"[red]", "[orange]", "[yellow]", "[green]", "[blue]", "[pink]", "[purple]"}; String word = "rainbow"; String result = ""; for(int i = 0; i < "rainbow".length(); ++i) { result = result + cols[i] + "rainbow".charAt(i) + "[p][cu]"; } return result; } else { n = this.getName(); if (n.startsWith("self")) { return "[grey]self[cu][p]" + TextWriter.getTag(this.getColour()) + n.substring(4).toLowerCase() + "[cu]"; } else if (this.metaKeyword2 != null) { return KUtils.makeName(n, this.metaKeyword, this.metaKeyword2); } else { List<TP<String, String>> metaRep = Arrays.asList(new TP("hyper", "[pink]")); int i; TP tp; for(i = 0; i < metaRep.size(); ++i) { tp = (TP)metaRep.get(i); if (n.startsWith((String)tp.a)) { String secondPart = n.substring(((String)tp.a).length()); return (String)tp.b + (String)tp.a + "[p][cu]" + TextWriter.getTag(this.getColour()) + secondPart.toLowerCase() + "[cu]"; } } if (this.metaKeyword != null) { metaRep = Arrays.asList(new TP("group", "[yellow]"), new TP("anti", "[blue]"), new TP("halve", "[grey]"), new TP("swap", "[light]"), new TP("minus", "[green]"), new TP("inflict", "[purple]"), new TP("double", "[orange]"), new TP("hyper", "[pink]")); for(i = 0; i < metaRep.size(); ++i) { tp = (TP)metaRep.get(i); if (n.startsWith((String)tp.a)) { return (String)tp.b + (String)tp.a + "[p][cu]" + this.metaKeyword.getColourTaggedString(); } } System.out.println("hmm unable to find autometa: " + n); } String tag = TextWriter.getTag(this.getColour()); return tag + this + "[cu]"; } } } public boolean spellOnly() { return this.abilityOnly() || this.reallySpellOnly(); } public boolean reallySpellOnly() { return this == deplete || this == channel || this == spellRescue; } public boolean abilityOnly() { return this == singleCast || this == cooldown || this == future; } public boolean skipStats() { return this == removed; } public boolean skipDebug() { return this.spellOnly() || this == removed; } public String getExtraRules() { return this.extraRules; } public TextureRegion getImage() { return this.getImage(EntSize.reg); } public TextureRegion getImage(EntSize size) { return size == EntSize.small ? this.cornerTiny : this.corner; } public Color getColour() { return this.col; } public String getName() { return this.name; } public ConditionalBonus getConditionalBonus() { return this.conditionalBonus; } public ConditionalRequirement getTargetingConditionalRequirement() { return this.targetingRequirement; } public boolean isFlipCorner() { return this.flipCorner; } public Keyword getInflict() { return this.inflict; } public Keyword getGroupAct() { return this.groupAct; } public long getCollisionBits() { switch(this) { case regen: return Collision.HEAL | Collision.POISON; case heal: case selfHeal: return Collision.HEAL; case shield: case selfShield: case steel: return Collision.SHIELD; case poison: case plague: return Collision.POISON; case fizz: case charged: case manacost: case manaGain: return Collision.SPELL; case ranged: case heavy: return Collision.RANGED; default: return 0L; } } public KeywordAllowType getAllowType() { return this.allowType; } public Keyword getMetaKeyword() { return this.metaKeyword; } public boolean isDoubleAct() { return this.doubleAct; } public int getSortPriority() { switch(this) { case fumble: case fluctuate: case resonate: return -3; case copycat: case shifter: case spy: case dejavu: return -1; case doubDiff: case revDiff: case lucky: case critical: case echo: return 1; default: if (this.conditionalBonus == null) { return 0; } else if (this.conditionalBonus.requirement == null) { return 1; } else { return this.conditionalBonus.requirement.preCalculate() ? 1 : 2; } } } }

Sheet ~Info+Links~ 
A1: On 21 Sep Pitor4k, Hollowdice, Pibonacci, Tulex aka WR holders and strong top 10 players came together to update the tierlist with the newest insights!
A2: Biggest changes: Enchantress Slightly Happy->Slightly Sad. The only hero that changed 2 tiers.
A3: Blue Heroes we went pretty black and white on to reflect the fact we all basically force the same blue heroes every run and almost never pick the others until we see them.
A4: Most changes were in the heroes, Curses the biggest changes were monster.pristine from Slightly Happy to Unpickable (3.1 added a few nasty enemies like Golems and you have to pick bad heroes to counter the curse
A5: Add.Shade from Slightly Happy to Big Sad (extremely hard to get out of death spirals)
A6: Can watch the discussion back in my Twitch Vod: https://www.twitch.tv/videos/2571393764
A10: Streams/Youtube (Bookclub members): | C10: Notes:
A11: Bookclub | B11: https://www.twitch.tv/japaneseexport | C11: Where you can find Bookclub play live, a co-op between 2 to 3 players on call depending on who's available :)
B12: https://www.youtube.com/@JapaneseExport/videos | C12: Find the tierlists discussion and some of the Bookclub games here. Any new Bookclub content will be uploaded here!
A14: JapaneseExport | B14: https://www.twitch.tv/japaneseexport | C14: The pilot and streamer of the Bookclub runs (also streams Slay the Spire)
A15: Pitor4k | B15: https://www.twitch.tv/Pitor4k | C15: Backseater and Seatbelt #1 for Bookclub. Solo name Bookchef. BIG new Unfair WR of 41 :) as of 2nd of June. Currently working on Generate Unfair WR (21st Sep)
B16: ^The only one currently still streaming Slice (21st sep) | C16: Classic Hell win :)
A17: vmService | B17: https://www.twitch.tv/vmservice | C17: Backseater and Seatbelt #2 for Bookclub. Solo name Bookshelf. Classic Unfair, usually weird teams :)
A19: The tierlists are made assuming:
A20: -Classic Unfair
A21: -Basic Team
A22: -Myriad offers (+50% options on curse selection screen, but need 11 points instead of 10)
A23: -20% generated items (Recently turned off at tier T7+ because high tier generated items seem worse than normal ones)
A25: -Bypass unlocks (aka everything is unlocked)
A26: -0.16667 because why not
A28: Discussions (3.1)
A29: The tierlists were made by Bookclub+ the top 5 players at that moment for more discussion!!
A30: Bookclub took #1 with a 23 streak on their first try and ended their 50 sample with 47W-3L. But we kept playing and got another big streak and ended on the then WR of 27 wins :) Congrats to your friend Hollowdice for beating us with 29 wins!
A31: We invited #2 Grimmy, #3 HollowDice, #4 Benedict as well as #5 IHateBooks (Xecnar) :) Many thanks for joining
A33: Heroes 3.1 | B33: Hero tierlist discussion (youtube) by Bookclub+Xecnar+Hollowdice
A34: Items 3.1 | B34: Item tierlist discussion (twitch) by Bookclub
A35: Curses 3.1 | B35: Curses tierlist discussion (youtube) Part 1 by Bookclub+Top 5 Unfair players
B36: Curses tierlist discussion (youtube) Part 2 by Bookclub-vm+Hollowdice+Benedict
A37: Blessings 3.1 | B37: Blessings tierlist discussion (youtube) by Bookclub-vm+Tulex
A39: Full almanac: | B39: https://docs.google.com/spreadsheets/d/1hAjtpz4afePzlzwhJCXWM629saGS8SZ2PyvNH1PP3eE
A40: Updated to 3.1 | B40: Credit to: "Not taodauheo" on Discord
A43: Archived from 3.0:
A45: Discussions: | B45: Discussions assume Classic Unfair, basic formation. Myriad offers enabled (double curse choices for +15% curse points).
B46: No other options were on for the 50 streak. Though Wild Items 20% is probably optimal.
A47: Heroes 3.0 | B47: https://youtu.be/xreQmeCmBwE | C47: Discussion with Bookclub+friends
A48: Curses 3.0 Part 1 | B48: https://youtu.be/6AIUWnkAqcc | C48: Discussion with Bookclub+friends
A49: Curses 3.0 Part 2 | B49: https://youtu.be/iJ-DlLA3GLs | C49: Discussion with Bookclub+friends
A51: Streams/other cool links | B51: *Are the people in Bookclub in 3.0, others are top players who helped with the tierlists :)
A52: JapaneseExport* | B52: https://www.twitch.tv/japaneseexport | C52: Where Bookclub got their 50 streak live on stream :)
B53: https://www.youtube.com/@JapaneseExport/videos | C53: Find all 3.0 discussions here (also linked separately above)
A54: Pitor4k* | B54: https://www.twitch.tv/Pitor4k | C54: Classic Hell cool win (3.0) | D54: Classic Brutal 3&4 streaks VODS (3.0)
A55: vmService* | B55: https://www.twitch.tv/vmservice
A56: Goddy* | B56: https://www.twitch.tv/its_goddy
A57: XecnaR | B57: https://www.twitch.tv/xecnar | C57: The first BookShelf to reach number 1 (3.0)
A58: RushSecond | B58: https://www.twitch.tv/rushsecond | C58: RushSecond's Slice & Dice Unfair Logs
A59: DarkTwinge | B59: https://www.twitch.tv/darktwinge | C59: Curse Valuations & Balancing Thoughts (3.0)
A60: *These players +Xecnar+other (mostly Slay the Spire players) individual accounts all named themself Bookshelf on the leaderboards. An inside joke.
A62: Classic Hard:
A63: Voyix 98%+ Tier Lists (3.0) | B63: https://docs.google.com/spreadsheets/d/1ejbZ8QkyzUo6pGk54R7OIcNnDGOisg_UEuk4_9jRdqg/edit?gid=1149433075#gid=1149433075
B64: Our Unfair tierlists translate well to Hard for the most part but if you want Hard specific Tierlists we recommend Voyix' as he understands the same overall strategic plan to win every game.

Sheet All Curses 3.1 A-Z 
B1: Rarity | C1: Generated? | D1: Effect | E1: Tier | F1: Ranking | G1: Ranking Count | H1: Notes | I1: Changes from 3.0 | J1: Total Counts
A2: 11-20.add.Archer | C2: True | D2: During fights 11-20: Add an Archer | E2: 1 | F2: Big Sad
A3: 11-20.add.Bee | C3: True | D3: During fights 11-20: Add a Bee | E3: 1 | F3: Biggest Happy | H3: Blessing. Stops other spawns
A4: 11-20.add.Illusion | C4: True | D4: During fights 11-20: Add an Illusion | E4: 1 | F4: Slightly Happy
A5: 11-20.add.Rat | C5: True | D5: During fights 11-20: Add a Rat | E5: 1 | F5: Big Sad | J5: Biggest Happy
A6: 11-20.add.Seed | C6: True | D6: During fights 11-20: Add a Seed | E6: 1 | F6: Big Happy | J6: Big Happy
A7: 11-20.add.Slimelet | C7: True | D7: During fights 11-20: Add a Slimelet | E7: 1 | F7: Big Happy | H7: Blessing sometimes, same as bee | J7: Slightly Happy
A8: 2 less max mana | D8: -2 max stored mana | E8: 1 | F8: Whatever | J8: Whatever
A9: 3rd.Bee | C9: True | D9: Summon a Bee every 3rd turn | E9: 1 | F9: Whatever | J9: Slightly Sad
A10: 3rd.Illusion | C10: True | D10: Summon an Illusion every 3rd turn | E10: 1 | F10: Whatever | I10: Tier: 2 -> 1 | J10: Big sad
A11: 3rd.Seed | C11: True | D11: Summon a Seed every 3rd turn | E11: 1 | F11: Whatever | I11: Tier: 2 -> 1 | J11: Unpickable
A12: 3rd.Slimelet | C12: True | D12: Summon a Slimelet every 3rd turn | E12: 1 | F12: Whatever | I12: Tier: 2 -> 1
A13: add.Bee | C13: True | D13: Add a Bee to each fight | E13: 1 | F13: Slightly Sad
A14: add.Illusion | C14: True | D14: Add an Illusion to each fight | E14: 1 | F14: Slightly Sad | I14: Tier: 2 -> 1
A15: add.Seed | C15: True | D15: Add a Seed to each fight | E15: 1 | F15: Slightly Happy | I15: Tier: 2 -> 1
A16: add.Slimelet | C16: True | D16: Add a Slimelet to each fight | E16: 1 | F16: Slightly Sad | I16: Tier: 2 -> 1
A17: Archery Training | D17: Archers & Snipers: +2 pips to all sides | E17: 1 | F17: Big Sad
A18: Armour^1/2 | B18: 33% | D18: At the start of the 2nd turn, shield 1 to all enemies | E18: 1 | F18: Whatever
A19: Arthritis^1 | D19: Tier 3 heroes get -1 hp | E19: 1 | F19: Whatever
A20: Big Hitter^11 | D20: All monsters: Double the pips of all sides with 11 or more pips | E20: 1 | F20: Unpickable | I20: Added in 3.1
A21: Bonezone | B21: 0.1% | D21: Bones: Replace all sides with 'Summon 2 bones' | E21: 1 | F21: Unpickable
A22: Boss Armour^2/1 | B22: 33% | D22: During boss fights: At the start of the first turn, shield 2 to all enemies | E22: 1 | F22: Big Sad | H22: Boss fights are already the hardest fights
A23: Boss Bones | D23: During boss fights : Add a bones | E23: 1 | F23: Big Sad | H23: Boss fights are already the hardest fights
A24: Bossilisk | D24: During fight 4: Fight 2x basilisk instead | E24: 1 | F24: Big Sad | H24: Can pick with acolyte or some op blessings
A25: bot.pain | C25: True | D25: All heroes: Add pain to the bottom side | E25: 1 | F25: Big Sad
A26: Bottom Poison^1/1 | B26: 33% | D26: Bottom hero: Start poisoned | E26: 1 | F26: Big Happy
A27: Doom^8/7 | B27: 5% | D27: At the end of the 7th turn, 8 damage to all heroes | E27: 1 | F27: Big Sad | I27: Tier: 2 -> 1
A28: Exposed middle | B28: 66% | D28: Middle hero: x2 to incoming damage if gained no shields | E28: 1 | F28: Slightly Sad | H28: Just get ghost shield
A29: hero.generous | C29: True | D29: All heroes: Add generous to all sides | E29: 1 | F29: Unpickable | H29: Hero sides cannot target self
A30: hero.mandatory | C30: True | D30: All heroes: Add mandatory to all sides | E30: 1 | F30: Big Happy
A31: Horde | B31: 20% | D31: +50% space for enemies (before becoming reinforcements) | E31: 1 | F31: Big Happy | H31: Avoid in dream | I31: 30% -> 50%
A32: Hurried^1 | D32: -1 levelup choice | E32: 1 | F32: Unpickable
A33: i.Affliction | C33: True | D33: Gain the 'Affliction' item ("Must be equipped Add pain to the two left sides") | E33: 1 | F33: Slightly Happy
A34: i.Barrel Hoops | C34: True | D34: Gain the 'Barrel Hoops' item ("Must be equipped 5 damage to adjacent allies upon death") | E34: 1 | F34: Big Happy | H34: Fate
A35: i.Brittle | C35: True | D35: Gain the 'Brittle' item ("Must be equipped Death is permanent") | E35: 1 | F35: Slightly Happy
A36: i.Broken Heart | C36: True | D36: Gain the 'Broken Heart' item ("Must be equipped Immune to healing") | E36: 1 | F36: Whatever
A37: i.Coiled Snake | C37: True | D37: Gain the 'Coiled Snake' item ("Must be equipped Start poisoned") | E37: 1 | F37: Big Happy
A38: i.D4 | C38: True | D38: Gain the 'D4' item ("Must be equipped Replace the right side with '1 self damage cantrip'") | E38: 1 | F38: Whatever
A39: i.Handcuffs | C39: True | D39: Gain the 'Handcuffs' item ("Must be equipped -1 item slot") | E39: 1 | F39: Big Happy
A40: i.Lead Weight | C40: True | D40: Gain the 'Lead Weight' item ("Must be equipped Replace the top and bottom sides with 'blank'") | E40: 1 | F40: Big Sad
A41: i.Martyr | C41: True | D41: Gain the 'Martyr' item ("Must be equipped Add death & +2 pips to the two left sides") | E41: 1 | F41: Big Sad
A42: i.Mould | C42: True | D42: Gain the 'Mould' item ("Must be equipped Add decay to all sides") | E42: 1 | F42: Slightly Happy
A43: i.Tracked | C43: True | D43: Gain the 'Tracked' item ("Must be equipped Upon death: summon 2 wolves") | E43: 1 | F43: Big Happy | I43: Item: 1 wolf -> 2 wolves
A44: i.Weariness | C44: True | D44: Gain the 'Weariness' item ("Must be equipped Add exert to the two left sides") | E44: 1 | F44: Slightly Happy
A45: Left Sticky | D45: All heroes: Add sticky to the left side | E45: 1 | F45: Unpickable
A46: Lightning^1/3 | D46: At the end of the 3rd turn, 1 damage to all heroes | E46: 1 | F46: Whatever
A47: Mana Debt^1/3 | B47: 33% | D47: The 3rd spell you cast each fight costs +1 mana | E47: 1 | F47: Whatever | I47: +3 mana -> +1 mana
A48: Monster HP Per^1/7 | D48: All monsters: +1 hp for each 7 hp | E48: 1 | F48: Slightly Sad
A49: Monster Left^1 | D49: All monsters: +1 pip to the left side | E49: 1 | F49: Whatever
A50: Monster Regen^1/5 | D50: All monsters with 5 or less hp: Start with 1 regen | E50: 1 | F50: Slightly Happy
A51: Mortal^13 | B51: 5% | D51: All heroes: Shields, health and pips limited to 13 | E51: 1 | F51: Big Happy | I51: Added in 3.1
A52: Ouroboros | B52: 0.2% | D52: Imp: Replace the two right sides with 'Summon a hexia death' | E52: 1 | F52: Slightly Sad | H52: Must pick it if you see it
A53: right.death | C53: True | D53: All heroes: Add death to the right side | E53: 1 | F53: Unpickable
A54: right.pain | C54: True | D54: All heroes: Add pain to the right side | E54: 1 | F54: Slightly Happy
A55: right2.pain | C55: True | D55: All heroes: Add pain to the two right sides | E55: 1 | F55: Slightly Sad
A56: rightmost.Blank | C56: True | D56: All heroes: Replace the rightmost side with 'blank' | E56: 1 | F56: Slightly Happy | H56: rip eccentric
A57: rightmost.death | C57: True | D57: All heroes: Add death to the rightmost side | E57: 1 | F57: Slightly Happy | H57: clumsy alloy meddler
A58: rightmost.Jammed | C58: True | D58: All heroes: Replace the rightmost side with 'blank stasis' | E58: 1 | F58: Whatever
A59: Rushed^1 | D59: -1 offered item | E59: 1 | F59: Whatever
A60: Skulk^3 | D60: During the 3rd turn, +1 pip to enemy sides | E60: 1 | F60: Big Sad
A61: Slippery Dice^3 | D61: Cannot lock more than 3 dice at a time | E61: 1 | F61: Slightly Sad
A62: Slow Spells^4 | D62: Maximum of 4 spells cast per turn | E62: 1 | F62: Slightly Happy | H62: Tactics count!! (Bard)
A63: Spiky Monsters^1/20 | B63: 33% | D63: All monsters with 20 or more hp: On-hit: damage the attacker for 1 | E63: 1 | F63: Big Happy
A64: Start Damaged^1/6 | B64: 33% | D64: All heroes: 1 of every 6 hp starts empty | E64: 1 | F64: Whatever
A65: Summon.Log | C65: True | D65: Summon a Log every turn | E65: 1 | F65: Unpickable | I65: Added in 3.1
A66: top.pain | C66: True | D66: All heroes: Add pain to the top side | E66: 1 | F66: Big Sad
A67: Tower^3 | B67: 33% | D67: All huge enemies: +3 hp | E67: 1 | F67: Unpickable | H67: Way better from Boss Curses (Only Slime Queen is scary) | I67: +4 hp -> +3 hp
A68: Training | D68: All hero-sized enemies: Replace the left side with '6 damage' | E68: 1 | F68: Big Happy
A69: Worse Items^1 | D69: -1 item quality | E69: 1 | F69: Slightly Sad
A70: Wurst | D70: The 2nd turn: No burst | E70: 1 | F70: Unpickable | I70: 3.0 effect: Add cooldown to burst
A71: 11-20.add.Bones | C71: True | D71: During fights 11-20: Add a Bones | E71: 2 | F71: Whatever
A72: 11-20.add.Goblin | C72: True | D72: During fights 11-20: Add a Goblin | E72: 2 | F72: Big Sad
A73: 11-20.add.Grandma | C73: True | D73: During fights 11-20: Add a Grandma | E73: 2 | F73: Big Sad | I73: Tier: 3 -> 2
A74: 11-20.add.Spider | C74: True | D74: During fights 11-20: Add a Spider | E74: 2 | F74: Slightly Sad
A75: 11-20.add.Wisp | C75: True | D75: During fights 11-20: Add a Wisp | E75: 2 | F75: Big Sad
A76: 11-20.add.Wolf | C76: True | D76: During fights 11-20: Add a Wolf | E76: 2 | F76: Big Sad | I76: Tier: 3 -> 2
A77: 3 less max mana | D77: -3 max stored mana | E77: 2 | F77: Slightly Sad
A78: 3 pip pain | D78: All heroes: Add pain to all sides with exactly 3 pips | E78: 2 | F78: Slightly Sad | I78: Tier: 1 -> 2
A79: 3rd.Archer | C79: True | D79: Summon an Archer every 3rd turn | E79: 2 | F79: Unpickable
A80: 3rd.Rat | C80: True | D80: Summon a Rat every 3rd turn | E80: 2 | F80: Slightly Sad
A81: 4th singleUse | B81: 33% | D81: Every 4th dice you use each turn gains singleUse | E81: 2 | F81: Whatever
A82: 5th pain | B82: 33% | D82: Every 5th dice you use each turn gains pain | E82: 2 | F82: Big Happy
A83: add.Archer | C83: True | D83: Add an Archer to each fight | E83: 2 | F83: Unpickable
A84: add.Rat | C84: True | D84: Add a Rat to each fight | E84: 2 | F84: Big Sad
A85: Armour^1/1 | B85: 33% | D85: At the start of the 1st turn, shield 1 to all enemies | E85: 2 | F85: Slightly Happy
A86: Arthritis^2 | D86: Tier 3 heroes get -2 hp | E86: 2 | F86: Big Sad
A87: Big Hitter^9 | D87: All monsters: Double the pips of all sides with 9 or more pips | E87: 2 | F87: Unpickable | I87: Tier: 1 -> 2
A88: Boar.spirit | C88: True | D88: All monsters: The inner hp: Must be removed individually | E88: 2 | F88: Big Sad
A89: Bones Bones | B89: 0.2% | D89: All heroes: 1 damage to adjacent allies upon death | E89: 2 | F89: Big Happy
A90: Boss Armour^4/1 | B90: 33% | D90: During boss fights: At the start of the first turn, shield 4 to all enemies | E90: 2 | F90: Unpickable | H90: Boss fights are already the hardest fights
A91: Bottom Poison^2/1 | B91: 33% | D91: Bottom hero: Start poisoned for 2 | E91: 2 | F91: Whatever
A92: Contagion | B92: 1% | D92: All most-hp allies: Start poisoned | E92: 2 | F92: Big Happy | H92: Don't pick it with wrong starting team
A93: Cooldown Spells | D93: Add cooldown to all spells | E93: 2 | F93: Big Sad | H93: Cooldown burst is also 2 points lol
A94: Death Shield^1 | D94: All monsters: Upon death: shield 1 to all allies | E94: 2 | F94: Slightly Happy | H94: Combo with curses that already make enemies tanky
A95: Flighty | D95: Damaged monsters: Move back | E95: 2 | F95: Big Happy
A96: Heal Reduced | B96: 10% | D96: All heroes: -1 pip to all heal/selfheal sides | E96: 2 | F96: Unpickable
A97: Heavy Dice^3 | D97: Cannot roll more than 3 dice at a time | E97: 2 | F97: Big Happy
A98: Hefty | D98: The top non-magic hero: Add heavy to all sides | E98: 2 | F98: Big Sad | I98: Added in 3.1
A99: hero.halveduel | C99: True | D99: All heroes: Add halveduel to all sides | E99: 2 | F99: Unpickable
A100: Hurried^2 | D100: -2 levelup choice | E100: 2 | F100: Unpickable
...

Sheet Heroes 3.1 
A2: 128 normal heroes (+2 special cases)
A3: Color | B3: Tier | C3: Icon | D3: Hero | E3: HP | F3: Sides | L3: Ability | M3: Passive Ability | N3: Rank | O3: Ranking Count | P3: Changes from 3.0 | Q3: Note | S3: Total Counts (excl. Greens)
F4: L | G4: M | H4: T | I4: B | J4: R | K4: RM
A5: Orange | B5: 1 | D5: Thief | E5: 4 | N5: Slightly Happy | S5: Big Happy | T5: =countif($O$3:$O$111,1) -> 0
A6: Orange | B6: 1 | D6: Scoundrel | E6: 7 | N6: Slightly Sad | P6: HP 6 -> 7 | S6: Slightly Happy | T6: =countif($O$3:$O$111,2) -> 0
A7: Orange | B7: 1 | D7: Lost | E7: 3 | N7: Big Happy | S7: Whatever | T7: =countif($O$3:$O$111,3) -> 0
A8: Orange | B8: 1 | D8: Dabble | E8: 6 | N8: Big Happy | S8: Slightly Sad | T8: =countif($O$3:$O$111,4) -> 0
A9: Orange | B9: 1 | D9: Clumsy | E9: 6 | N9: Big Sad | P9: HP 5 -> 6 | S9: Big sad | T9: =countif($O$3:$O$111,5) -> 0
A10: Orange | B10: 2 | D10: Spellblade | E10: 7 | N10: Big Happy | R10: Big Happy
A11: Orange | B11: 2 | D11: Trapper | E11: 8 | N11: Slightly Happy
A12: Orange | B12: 2 | D12: Juggler | E12: 7 | N12: Big Happy
A13: Orange | B13: 2 | D13: Ninja | E13: 6 | N13: Big Sad
A14: Orange | B14: 2 | D14: Rogue | E14: 7 | N14: Big Sad
A15: Orange | B15: 2 | D15: Dabbler | E15: 8 | N15: Big Happy | P15: HP 9 -> 8
A16: Orange | B16: 2 | D16: Ranger | E16: 7 | N16: Slightly Happy
A17: Orange | B17: 2 | D17: Gambler | E17: 7 | N17: Whatever | P17: mid: 2 damage -> 3 damage
A18: Orange | B18: 3 | D18: Venom | E18: 8 | N18: Slightly Sad | Q18: Can be good if you don't have a win condition for floor 20
A19: Orange | B19: 3 | D19: Assassin | E19: 9 | N19: Big Happy
A20: Orange | B20: 3 | D20: Dancer | E20: 8 | N20: Big Sad
A21: Orange | B21: 3 | D21: Roulette | E21: 8 | N21: Big Sad | Q21: Whatever with left replacer
A22: Orange | B22: 3 | D22: Ludus | E22: 7 | N22: Slightly Sad | P22: HP 6 -> 7
A23: Orange | B23: 3 | D23: Fencer | E23: 9 | N23: Slightly Happy
A24: Orange | B24: 3 | D24: Dabblest | E24: 9 | N24: Slightly Happy
A25: Orange | B25: 3 | D25: Sharpshot | E25: 8 | N25: Whatever
A26: Orange | B26: 3 | D26: Agent | E26: 8 | N26: Big Happy | P26: HP 9 -> 8
A27: Yellow | B27: 1 | D27: Fighter | E27: 5 | N27: Slightly Happy
A28: Yellow | B28: 1 | D28: Brigand | E28: 5 | N28: Big Happy
A29: Yellow | B29: 1 | D29: Ruffian | E29: 4 | N29: Big Sad
A30: Yellow | B30: 1 | D30: Hoarder | E30: 6 | N30: Slightly Happy
A31: Yellow | B31: 1 | D31: Lazy | E31: 6 | M31: rolling blanks lol | N31: Slightly Sad | P31: HP 5 -> 6
A32: Yellow | B32: 2 | D32: Berserker | E32: 8 | N32: Whatever
A33: Yellow | B33: 2 | D33: Scrapper | E33: 7 | N33: Slightly Happy | P33: HP 8 -> 7
A34: Yellow | B34: 2 | D34: Brute | E34: 8 | N34: Slightly Happy
A35: Yellow | B35: 2 | D35: Sinew | E35: 8 | N35: Slightly Sad
A36: Yellow | B36: 2 | D36: Gladiator | E36: 7 | N36: Big Happy
A37: Yellow | B37: 2 | D37: Whirl | E37: 8 | N37: Big Sad | P37: HP 7 -> 8
A38: Yellow | B38: 2 | D38: Collector | E38: 8 | N38: Big Sad
A39: Yellow | B39: 2 | D39: Soldier | E39: 7 | N39: Slightly Happy
A40: Yellow | B40: 3 | D40: Barbarian | E40: 10 | N40: Slightly Sad | P40: HP 12 -> 10
A41: Yellow | B41: 3 | D41: Brawler | E41: 9 | N41: Slightly Happy
A42: Yellow | B42: 3 | D42: Eccentric | E42: 9 | N42: Big Sad | P42: HP 8 -> 9
A43: Yellow | B43: 3 | D43: Leader | E43: 9 | N43: Big Sad | Q43: Extra bad as an early t3, better a bit later (extra re-use/smith value)
A44: Yellow | B44: 3 | D44: Wanderer | E44: 10 | N44: Biggest Happy | P44: left: 1 damage defy -> Shield 2 copycat rightmost: Shield 2 copycat -> blank
A45: Yellow | B45: 3 | D45: Bash | E45: 10 | N45: Whatever
A46: Yellow | B46: 3 | D46: Veteran | E46: 11 | N46: Slightly Sad
A47: Yellow | B47: 3 | D47: Curator | E47: 9 | N47: Big Happy
A48: Yellow | B48: 3 | D48: Captain | E48: 10 | N48: Slightly Sad | Q48: If you have consistent 3 dmg (usually from Orange) he's at least Whatever | R48: Big Happy
A49: Grey | B49: 1 | D49: Defender | E49: 7 | N49: Big Happy
A50: Grey | B50: 1 | D50: Buckle | E50: 6 | N50: Big Happy
A51: Grey | B51: 1 | D51: Squire | E51: 5 | N51: Slightly Happy
A52: Grey | B52: 1 | D52: Alloy | E52: 4 | N52: Big Sad | P52: left: 1 damage selfshield -> Shield 1 copycat | Q52: Copycat can copy meddler bones and lose you the run
A53: Grey | B53: 1 | D53: Wallop | E53: 5 | N53: Whatever | Q53: Strong on normal fights but can be pretty useless against the Boss (Mainly Troll)
A54: Grey | B54: 2 | D54: Knight | E54: 7 | N54: Big Happy | P54: HP 9 -> 7 | R54: Big Happy
A55: Grey | B55: 2 | D55: Warden | E55: 10 | N55: Slightly Happy
A56: Grey | B56: 2 | D56: Armorer | E56: 9 | N56: Slightly Sad
A57: Grey | B57: 2 | D57: Monk | E57: 9 | N57: Slightly Sad
A58: Grey | B58: 2 | D58: Cleric | E58: 8 | N58: Slightly Happy | R58: Big Happy
A59: Grey | B59: 2 | D59: Guardian | E59: 8 | N59: Big Happy
A60: Grey | B60: 2 | D60: Bard | E60: 6 | N60: Big Sad | P60: left: Shield 1 cantrip -> Shield 2 cantrip | Q60: Big happy with survive+ | R60: Big Happy
A61: Grey | B61: 2 | D61: Pilgrim | E61: 8 | N61: Whatever | P61: HP 9 -> 8
A62: Grey | B62: 3 | D62: Valkyrie | E62: 9 | N62: Big Sad | P62: rightmost: blank -> Revive ally
A63: Grey | B63: 3 | D63: Keeper | E63: 10 | N63: Big Happy
A64: Grey | B64: 3 | D64: Prince | E64: 9 | N64: Slightly Happy | P64: HP 11 -> 9; right: Heal and shield 3 -> blank topbot: blank -> Heal and shield 3 | R64: Slightly Happy
A65: Grey | B65: 3 | D65: Stoic | E65: 15 | N65: Whatever
A66: Grey | B66: 3 | D66: Stalwart | E66: 11 | N66: Big Happy | P66: Cleanse
A67: Grey | B67: 3 | D67: Poet | E67: 8 | N67: Big Happy | P67: HP 9 -> 8 | R67: Whatever
A68: Grey | B68: 3 | D68: Paladin | E68: 11 | N68: Whatever
A69: Red | B69: 1 | D69: Healer | E69: 5 | N69: Biggest Happy | R69: Big Happy
A70: Red | B70: 1 | D70: Acolyte | E70: 5 | N70: Slightly Happy | R70: Big Happy
A71: Red | B71: 1 | D71: Mystic | E71: 4 | N71: Whatever | R71: Slightly Happy
A72: Red | B72: 1 | D72: Splint | E72: 4 | N72: Big Happy | R72: Big Happy
A73: Red | B73: 1 | D73: Gardener | E73: 5 | N73: Slightly Happy | R73: Slightly Happy
A74: Red | B74: 2 | D74: Druid | E74: 7 | N74: Whatever | R74: Big Happy
A75: Red | B75: 2 | D75: Herbalist | E75: 7 | N75: Whatever | R75: Big Happy
A76: Red | B76: 2 | D76: Fey | E76: 6 | N76: Big Sad | P76: HP 5 -> 6 | Q76: Need some broken items | R76: Slightly Happy
A77: Red | B77: 2 | D77: Disciple | E77: 8 | N77: Biggest Happy | R77: Big Happy
A78: Red | B78: 2 | D78: Vampire | E78: 7 | N78: Big Happy | P78: Spell keyword changed from cruel to terminal | R78: Big Happy
A79: Red | B79: 2 | D79: Medic | E79: 7 | N79: Slightly Happy | R79: Big Happy
A80: Red | B80: 2 | D80: Priestess | E80: 5 | N80: Slightly Sad | R80: Slightly Happy
A81: Red | B81: 2 | D81: Enchanter | E81: 7 | N81: Slightly Sad | P81: HP 6 -> 7 right2: blank -> Add selfheal | Q81: Very context dependant. It's a bad 1st/2nd pick, also need 2 mana from your blue. Scales very strongly into the lategame, the later the pick the better usually. | R81: Slightly Happy
A82: Red | B82: 3 | D82: Doctor | E82: 9 | N82: Big Happy | P82: HP 10 -> 9 | R82: Big Happy
A83: Red | B83: 3 | D83: Fate | E83: 7 | N83: Slightly Sad | P83: HP 8 -> 7 | Q83: Too hardcountered by hexia. Can pick it with Warlock. Funny barrel synergy | R83: Big Happy
A84: Red | B84: 3 | D84: Surgeon | E84: 9 | N84: Slightly Happy | P84: HP 10 -> 9 | R84: Big Happy
A85: Red | B85: 3 | D85: Witch | E85: 10 | N85: Big Sad | R85: Big Happy
A86: Red | B86: 3 | D86: Prophet | E86: 8 | N86: Big Happy | Q86: better than doctor if you have cleanse | R86: Big Happy
A87: Red | B87: 3 | D87: Forsaken | E87: 9 | N87: Big Sad | R87: Big Happy
A88: Red | B88: 3 | D88: Wraith | E88: 9 | N88: Biggest Sad | Q88: Great with valk (why do you have Valk?) | R88: Big Sad
A89: Red | B89: 3 | D89: Shaman | E89: 11 | N89: Whatever | Q89: Mana dependant from Blue, usually later pick. If you have mana very strong. | R89: Big Happy
A90: Blue | B90: 1 | D90: Mage | E90: 4 | N90: Big Happy | R90: Big Happy
A91: Blue | B91: 1 | D91: Student | E91: 5 | N91: Whatever | R91: Slightly Happy
A92: Blue | B92: 1 | D92: Initiate | E92: 4 | N92: Whatever | R92: Whatever
A93: Blue | B93: 1 | D93: Cultist | E93: 5 | N93: Big Happy | P93: left: +4 mana pain -> +3 mana pain rightmost: +1 mana pain -> +2 mana pain | R93: Whatever
A94: Blue | B94: 1 | D94: Prodigy | E94: 4 | N94: Big Happy | P94: 3.0 Prodigy: HP 4 left2: +3 mana singleUse; others: blank | R94: Slightly Happy
A95: Blue | B95: 1 | D95: Meddler | E95: 6 | N95: Whatever | Q95: Can be broken or big sad with curses | R95: Big Happy
A96: Blue | B96: 2 | D96: Caldera | E96: 6 | N96: Big Happy | R96: Big Happy
A97: Blue | B97: 2 | D97: Fiend | E97: 6 | N97: Big Sad | R97: Slightly Happy
A98: Blue | B98: 2 | D98: Jester | E98: 7 | N98: Big Sad | P98: HP 6 -> 7 | Q98: Rushsecond always rolls 3 | R98: Big Happy
A99: Blue | B99: 2 | D99: Myco | E99: 8 | N99: Big Sad | R99: Big Happy
A100: Blue | B100: 2 | D100: Sparky | E100: 7 | N100: Whatever | Q100: Obvious synergy with curses. Otherwise would like to see mana gen on red/spellblade first. | R100: Big Happy
A101: Blue | B101: 2 | D101: Glacia | E101: 9 | N101: Slightly Happy | R101: Big Happy
...

Sheet Items Tier 1-9 3.1 
A1: Click link to jump to tier | E1: S | G1: Very Happy
B2: Tier 1 | C2: Tier 6 | D2: Note: "random" assumes an item of same tier or tier -1/+1 is offered. | E2: A | G2: Happy
B3: Tier 2 | C3: Tier 7 | D3: Worse random offers ofc change the evaluation of when to random | E3: B | G3: Slightly Happy
B4: Tier 3 | C4: Tier 8 | E4: C | G4: Whatever but with synergy often stronger than higher tiers. Use your brain!
B5: Tier 4 | C5: Tier 9 | E5: D | G5: Too little impact. Only niche synergies make this pickable
B6: Tier 5 | E6: F | G6: Almost always random
A8: Item | B8: Tier | C8: Icon | D8: Effect | E8: Tier | F8: Unlock condition | G8: Tier Help | H8: Notes | I8: Changes from 3.0
A9: Anchor | B9: 1 | D9: Start of turn 1: self-shield 1 | E9: A | G9: 2 | H9: Steel/Survivability | I9: Self-shield 2 -> Self-shield 1
A10: Arrow | B10: 1 | D10: Replace damage sides with 'Kill an enemy with 2 or less hp ranged' | E10: C | F10: Complete "70 Achievements" achievement | G10: 4 | H10: Tough Hp/Thorn, Grave etc killer
A11: Autumn Leaf | B11: 1 | D11: Add growth to the rightmost side | E11: D | G11: 5 | I11: Tier: 2 -> 1
A12: Balisong | B12: 1 | D12: Replace the left side with '1 damage cantrip' | E12: C | G12: 4 | H12: Roulette
A13: Ballet Shoes | B13: 1 | D13: Swap the left side with the rightmost side | E13: C | F13: Complete "Dancer-Pick" achievement | G13: 4 | H13: Don't pick if weak early
A14: Barkskin | B14: 1 | D14: Immune to shields +2 hp | E14: C | G14: 4 | H14: If you need help early
A15: Basilisk Scale | B15: 1 | D15: Start petrified for 1 +3 pips to the top side | E15: D | F15: Complete "Petrified" achievement | G15: 5 | H15: Polearm/Consistent cleanse
A16: Big Heart | B16: 1 | D16: Replace the middle side with 'Heal 7' | E16: B | G16: 3 | H16: Clumsy, decent side with some synergys like dogma and enduring
A17: Big Shield | B17: 1 | D17: Replace the left side with 'Shield 4' | E17: S | G17: 1 | H17: Upgrade for many t1s, makes Armorer great, can put on Reds like Disciple, later on Ghast/Doctor
A18: Bone Charm | B18: 1 | D18: No hp penalty when defeated | E18: A | G18: 2 | H18: Pain/Death synergy. Not caring about having a hero die can simplify fights (like thorns)
A19: Bowl | B19: 1 | D19: Revert all changes to the middle column (Replace middle column with my base middle column) | E19: F | F19: Complete "70 Achievements" achievement | G19: 6 | H19: Unless Curses
A20: Castor Root | B20: 1 | D20: Replace blank sides with 'Heal 1' | E20: F | G20: 6
A21: Change of Heart | B21: 1 | D21: Replace heal/selfheal sides with 'basic shield' sides, retaining their original pips and other keywords | E21: S | F21: Complete "Change of Heart" achievement | G21: 1 | H21: Improves Red t1 immensely, many synergies including Steel
A22: Cheating Sleeves | B22: 1 | D22: Add quin to the top and bottom sides | E22: F | F22: Complete "Ace-Pick" achievement | G22: 6
A23: Cloak | B23: 1 | D23: Replace the middle side with 'Dodge all damage and enemy effects this turn' | E23: F | G23: 6 | H23: Dodge vs the Hand/Tarantus but too niche
A24: Clumsy Shoes | B24: 1 | D24: Add heavy & eliminate & +1 pip to all targeted sides | E24: F | F24: Complete "70 Achievements" achievement | G24: 6 | H24: Maybe if you're super afraid of Floor 4 Troll
A25: Coin | B25: 1 | D25: Add fumble & +1 pip to the left side | E25: F | F25: Complete "70 Achievements" achievement | G25: 6 | H25: Statis | I25: 3.0 Coin: Add +4 to the left side -1 reroll
A26: Compass | B26: 1 | D26: Rotate sides clockwise around the middle side (Left side moves to top side, top side moves to right side, right side moves to bottom side and bottom side moves to left side) | E26: F | F26: Complete "45 Achievements" achievement | G26: 6
A27: Copper Ring | B27: 1 | D27: +1 empty hp +1 max stored mana | E27: B | G27: 3 | H27: 1 max mana is nice
A28: Corset | B28: 1 | D28: Replace the left side with 'blank' +1 pip to the middle side | E28: F | G28: 6
A29: Courage Potion | B29: 1 | D29: Add potion & +3 pips to the left side | E29: F | F29: Complete "Herbalist-Pick" achievement | G29: 6
A30: Doll | B30: 1 | D30: Replace the left side with the above hero's base side -1 pip to the five right sides | E30: F | F30: Complete "70 Achievements" achievement | G30: 6
A31: Doom Blade | B31: 1 | D31: Replace blank sides with '3 damage death' | E31: F | F31: Complete "70 Achievements" achievement | G31: 6 | H31: Knight tactic
A32: Emerald Shard | B32: 1 | D32: Gain the effects of all tier 2 items on other heroes (Can copy the effects of items that are exclusive to a certain hero color) | E32: F | F32: Complete "Hidden Emerald" achievement | G32: 6 | H32: Golden thread/polearm no longer works
A33: Fletching | B33: 1 | D33: Add ranged to the left side | E33: D | G33: 6 | H33: Maybe spiky/add archer | I33: Tier: 2 -> 1
A34: Glass Helm | B34: 1 | D34: +3 hp Death is permanent | E34: S | F34: Complete "Oops+" achievement | G34: 1
A35: Healing Wand | B35: 1 | D35: Replace the rightmost side with 'Heal 4 single-use' | E35: B | G35: 3
A36: Infused Herbs | B36: 1 | D36: Replace the bottom side with 'Heal 2 cleanse boost manacost' | E36: F | F36: Complete "45 Achievements" achievement | G36: 6 | H36: Boost is better than regen but still doesn't do enough | I36: Heal 2 regen cleanse manacost -> Heal 2 cleanse boost manacost
A37: Iron Heart | B37: 1 | D37: Add exert & +1 pip to all sides | E37: A | F37: Complete "70 Achievements" achievement | G37: 2 | H37: Put on any 1 pip hero to get a turn ahead on t1/3. Synergy with Disciple, Hack, Stasis, Inner Str.
A38: Knife Bag | B38: 1 | D38: Replace blank sides with '1 damage cantrip, pain' | E38: C | F38: Complete "Draw" achievement | G38: 4 | H38: Can be picked with lazy/scoundrel protect against evoker low roll
A39: Learn Poultice | B39: 1 | D39: Learn the spell: Poultice (Cost: 1 mana - Heal 2 singleCast) | E39: B | G39: 3
A40: Leather Vest | B40: 1 | D40: +1 hp | E40: A | G40: 2
A41: Memory | B41: 1 | D41: Revert all changes to the left side (Replace left side with my base left side) | E41: F | F41: Complete "45 Achievements" achievement | G41: 6 | H41: Unless Curses (left blank)
A42: Necromancer Tome | B42: 1 | D42: You can cast spells from defeated heroes Replace the left side with '3 mana pain' | E42: A | F42: Complete "45 Achievements" achievement | G42: 2 | H42: Roulette and generally good
A43: Pendulum | B43: 1 | D43: Swap the left side with the middle side | E43: F | F43: Complete "70 Achievements" achievement | G43: 6
A44: Pillow | B44: 1 | D44: Add patient to the left side | E44: F | G44: 6 | I44: Tier: 2 -> 1
A45: Quiver | B45: 1 | D45: Replace the five right sides with '1 damage ranged' | E45: F | G45: 6
A46: Reagents | B46: 1 | D46: Replace the two right sides with 'blank' & 'Heal 1 regen' | E46: D | G46: 5 | H46: Juggler/Meddler
A47: Revive Potion | B47: 1 | D47: Replace the right side with 'Revive the 5 top-most defeated allies potion' | E47: D | F47: Complete "Herbalist-Pick" achievement | G47: 5 | H47: Juggler/Meddler
A48: Rusty Plate | B48: 1 | D48: Replace the middle side with 'blank' +3 hp | E48: B | G48: 3
A49: Scar | B49: 1 | D49: +5 empty hp | E49: S | F49: Complete "Heal" achievement | G49: 1 | H49: Quite great with Splint, Healer. Many t2 reds.
A50: Seedling | B50: 1 | D50: Replace the left side with '2 damage growth' | E50: C | G50: 4
A51: Sorcery Notes | B51: 1 | D51: Replace the two left sides with '+1 mana cantrip' & 'blank' | E51: D | F51: Complete "45 Achievements" achievement | G51: 5 | H51: Clumsy
A52: Tankard | B52: 1 | D52: Add acidic to the middle side | E52: F | F52: Complete "45 Achievements" achievement | G52: 6 | H52: Unless item poison
A53: Tattered Robes | B53: 1 | D53: Replace the three right sides with '+1 mana' +1 max stored mana | E53: C | G53: 4 | H53: Meddler/Clumsy/Lazy
A54: Tincture | B54: 1 | D54: Add cleanse to the rightmost side | E54: D | F54: Complete "45 Achievements" achievement | G54: 6
A55: Titanbane Potion | B55: 1 | D55: Add dispel & potion to the middle side | E55: B | F55: Complete "Herbalist-Pick" achievement | G55: 3 | H55: Hexia, Inevitable, Tarantus, Wendigo etc.
A56: Trowel | B56: 1 | D56: Replace the middle side with 'Revive the top-most defeated ally' | E56: F | G56: 6 | H56: Clumsy | I56: Replace middle -> left
A57: Wand of Wand | B57: 1 | D57: Replace the left side with '1 damage singleUse inflictsingleUse' | E57: F | F57: Complete "70 Achievements" achievement | G57: 6
A58: Whey | B58: 1 | D58: Add vitality to the left side | E58: B | F58: Complete "70 Achievements" achievement | G58: 3 | H58: Mostly on reds, less useful on grey. Also possible to give enemy max hp for Cruel value and get around "Last hp traits" (removes steel pips from Sarcophagus)
A59: Wolf Ears | B59: 1 | D59: Set hp to 6 | E59: C | G59: 4 | H59: Helps early
A60: Ace of Spades | B60: 2 | D60: +2 to the left side -2 to the five right sides | E60: F | F60: Complete "Gambler-Pick" achievement | G60: 6
A61: Big Hammer | B61: 2 | D61: Replace the two left sides with '5 damage heavy' & 'blank' | E61: B | G61: 3
A62: Blessed Ring | B62: 2 | D62: Replace the rightmost side with 'Shield 1 rescue' | E62: D | F62: Complete "Blessed Ring" achievement | G62: 5
A63: Blessed Water | B63: 2 | D63: Replace the middle side with 'Heal 3 vitality' | E63: C | G63: 4
A64: Burning Blade | B64: 2 | D64: Replace the left side with '4 damage' -2 hp | E64: D | G64: 5
A65: Citrine Ring | B65: 2 | D65: +1 pip to the rightmost side | E65: D | G65: 5
A66: Clef | B66: 2 | D66: Add treble to the two left sides | E66: D | F66: Complete "70 Achievements" achievement | G66: 5 | H66: Pick with Gladiator | I66: left side -> 2 left sides
A67: Clover | B67: 2 | D67: +1 to the left side -2 to the middle side | E67: F | G67: 6 | I67: Tier: 3 -> 2
A68: Clumsy Hammer | B68: 2 | D68: Replace the top side with '5 damage heavy eliminate' | E68: F | F68: Complete "70 Achievements" achievement | G68: 6 | I68: 4 damage -> 5 damage
A69: Duvet | B69: 2 | D69: Add patient to the three right sides | E69: F | F69: Complete "45 Achievements" achievement | G69: 6 | I69: Tier: 3 -> 2
A70: Faint Halo | B70: 2 | D70: +1 hp this fight whenever I save a hero | E70: B | G70: 3
A71: First aid Kit | B71: 2 | D71: Replace the bottom side with 'Heal 2 cleanse' if equipped to an orange hero | E71: C | F71: Complete "45 Achievements" achievement | G71: 4
A72: Friendship Bracelet | B72: 2 | D72: +2 empty hp Monsters flee if you have 5x as much hp as them instead of 10x | E72: C | F72: Complete "Benevolence" achievement | G72: 4 | H72: Picked pretty much only for empty max hp
A73: Garnet | B73: 2 | D73: +1 to incoming healing | E73: D | G73: 5
A74: Golden Thread | B74: 2 | D74: +1 pip to all non-damage sides if equipped to a yellow hero | E74: C | F74: Complete "70 Achievements" achievement | G74: 4 | H74: Can no longer be copied
A75: Ice Cube | B75: 2 | D75: Add stasis to the left side | E75: D | F75: Complete "45 Achievements" achievement | G75: 5
A76: Learn Remedy | B76: 2 | D76: Learn the spell: Remedy (Cost: 1 mana - Heal 1 cleanse singleCast) | E76: B | F76: Complete "45 Achievements" achievement | G76: 3
A77: Learn Wings | B77: 2 | D77: Learn the spell: Wings (Cost: 2 mana - Heal 3 to the top and bottom allies) | E77: D | G77: 5
A78: Leather Gloves | B78: 2 | D78: Copy the rightmost side onto the top and bottom sides | E78: D | F78: Complete "45 Achievements" achievement | G78: 5
A79: Liqueur | B79: 2 | D79: Swap the top side with the rightmost side +2 max stored mana | E79: C | F79: Complete "70 Achievements" achievement | G79: 4
A80: Needle | B80: 2 | D80: Add picky & +2 pips to all targeted sides | E80: S | F80: Complete "70 Achievements" achievement | G80: 1 | H80: Very strong on mana/dmg sides (Caldera/Spellblade eg, generally can be taken on and off on 2/3 dmg to deal 4/5. Can put this on mystic and suicide your 6/7 HP hero
A81: Origami | B81: 2 | D81: Swap each side with its opposite (Swap top side with bottom side, left side with right side, middle side with rightmost side) | E81: D | F81: Complete "45 Achievements" achievement | G81: 5
A82: Peaked Cap | B82: 2 | D82: Copy the middle side onto the left side | E82: C | G82: 4
A83: Powdered Mana | B83: 2 | D83: Replace blank sides with '+1 mana' | E83: B | G83: 3
A84: PowerStone | B84: 2 | D84: Replace the middle side with '+0 mana steel' if equipped to a grey hero | E84: F | F84: Complete "70 Achievements" achievement | G84: 6 | I84: Tier: 4 -> 2 Replace middle instead of left
A85: Quicksilver | B85: 2 | D85: Keep unused shields | E85: B | F85: Complete "Ironclad" achievement | G85: 3
A86: Rain of Arrows | B86: 2 | D86: Replace the top side with '1 damage ranged duplicate' | E86: F | G86: 6
A87: Rejuvenation Wand | B87: 2 | D87: Replace the top and bottom sides with 'Heal 10 singleUse' | E87: B | G87: 3
A88: Sapphire | B88: 2 | D88: Replace the middle side with '+2 mana' | E88: S | G88: 1
A89: Sapphire Skull | B89: 2 | D89: Upon death: +2 mana | E89: D | G89: 5
A90: Silver Imp | B90: 2 | D90: Replace the top and bottom sides with 'Gain 1 reroll cantrip pain' | E90: C | F90: Complete "Spines+" achievement | G90: 4 | H90: Often incredibly strong lategame! 1 extra reroll is invaluable
A91: Spinach | B91: 2 | D91: Start of turn 1: Self-heal 3 | E91: B | F91: Complete "45 Achievements" achievement | G91: 3
A92: Square Wheel | B92: 2 | D92: Replace the three right sides with 'Gain 1 reroll cantrip', 'blank' & 'blank' | E92: C | F92: Complete "70 Achievements" achievement | G92: 4
A93: Static Tome | B93: 2 | D93: Replace the top and bottom sides with '+1 mana pair' | E93: S | F93: Complete "70 Achievements" achievement | G93: 1
A94: Statuette | B94: 2 | D94: Replace the middle row with 'blank' +6 hp | E94: C | F94: Complete "Statue-Pick" achievement | G94: 4 | H94: If you have an item that replaces a side on the middle row this is often worth to equip. Possibly without the item on something like a Monk. 6 hp is a lot!
A95: Syringe | B95: 2 | D95: Add cantrip to all sides if there are 2 or fewer living heroes | E95: D | F95: Complete "45 Achievements" achievement | G95: 5 | I95: Tier: 3 -> 2
A96: Tower Shield | B96: 2 | D96: Replace the middle side with 'Shield 10 heavy' | E96: C | F96: Complete "70 Achievements" achievement | G96: 4 | I96: Shield 7 -> Shield 10
A97: Twin Daggers | B97: 2 | D97: Replace the top and bottom sides with '1 damage cantrip' | E97: A | G97: 2
A98: Wandify | B98: 2 | D98: Add singleUse & +1 pip to the two right sides | E98: A | G98: 2
A99: Wild Seeds | B99: 2 | D99: Add undergrowth to the two left sides | E99: F | F99: Complete "70 Achievements" achievement | G99: 6 | I99: Tier: 3 -> 2
A100: Worn Arms | B100: 2 | D100: Replace the top and bottom sides with '2 damage' & Shield 2' | E100: A | G100: 2
A101: Abacus | B101: 3 | D101: Shift my middle row across by 1 +1 hp | E101: C | F101: Complete "45 Achievements" achievement | G101: 4
...

Sheet Blessings 3.1 
A1: Blessing | B1: Effect | C1: Tier | D1: Ranking | E1: Rarity | F1: Notes
A2: 2 Extra rerolls | B2: +2 reroll | C2: 6 | D2: Whatever
A3: 2 hero hp | B3: All heroes: +2 hp | C3: 4 | D3: Big Happy
A4: 2nd selfHeal | B4: Every 2nd dice you use each turn gains selfheal | C4: 3 | D4: Slightly Happy | E4: 33%
A5: 2nd selfShield | B5: Every 2nd dice you use each turn gains selfshield | C5: 5 | D5: Slightly Sad | E5: 33%
A6: 3rd deathwish | B6: Every 3rd dice you use each turn gains deathwish | C6: 3 | D6: Big Happy | E6: 33%
A7: 3rd selfHeal | B7: Every 3rd dice you use each turn gains selfheal | C7: 2 | D7: Slightly Happy | E7: 33%
A8: 3rd selfShield | B8: Every 3rd dice you use each turn gains selfshield | C8: 3 | D8: Big Happy | E8: 33%
A9: 4 hero hp | B9: 2x [All heroes: +2 hp] | C9: 8 | D9: Slightly Sad | E9: 1% | F9: Good to trade for something like add.Ghost
A10: 5 max mana | B10: +5 max stored mana | C10: 1 | D10: Big Sad
A11: 5th copycat | B11: Every 5th dice you use each turn gains copycat | C11: 3 | D11: Big Happy | E11: 33%
A12: 5th growth | B12: Every 5th dice you use each turn gains growth | C12: 1 | D12: Whatever | E12: 33%
A13: 5th selfHeal | B13: Every 5th dice you use each turn gains selfheal | C13: 1 | D13: Big Happy | E13: 33%
A14: 5th selfShield | B14: Every 5th dice you use each turn gains selfshield | C14: 2 | D14: Big Happy | E14: 33%
A15: Absorb bosses | B15: For each defeated boss: All heroes: +1 pip to all sides | C15: 10 | D15: Big Sad | E15: 10%
A16: add.[Tier 1 hero] | B16: Add a [Tier 1 hero] to your party | C16: 6 | D16: Slightly Happy | F16: ofc depends on hero, but strong
A17: add.[Tier 2 hero] | B17: Add a [Tier 2 hero] to your party | C17: 9 | D17: Big Happy | F17: ofc depends on hero, but very strong
A18: Basalt.spirit | B18: All monsters: The first time I take exactly 1 damage, double it to 2, then increase 1 to 2 | C18: 2 | D18: Big Happy | F18: Bonkers
A19: Better Items^1 | B19: +1 item quality | C19: 2 | D19: Slightly Sad
A20: Better Items^2 | B20: +2 item quality | C20: 4 | D20: Big Sad
A21: Better Items^3 | B21: +3 item quality | C21: 6 | D21: Big Sad
A22: Better Items^4 | B22: +4 item quality | C22: 8 | D22: Big Sad
A23: Better Items^5 | B23: +5 item quality | C23: 10 | D23: Big Sad
A24: Blessings (that don't immediatly take effect), for example Better Items are much more pickable if you can trade them for curses that also mostly take effect later. For example Better Items, add monster floor 11-20.
A25: Bolt Spell | B25: Learn Spell 'Bolt' (Cost: 3 mana - 5 damage) | C25: 4 | D25: Big Sad
A26: Bone Math | B26: All monsters: 1 damage to adjacent allies upon death | C26: 5 | D26: Big Sad
A27: Bones.spirit | B27: All monsters: 1 damage to adjacent allies upon death | C27: 8 | D27: Unpickable | F27: Bonemath but 8 points :)
A28: Boss Smash^1 | B28: During boss levels: All heroes: +1 pip to all sides | C28: 3 | D28: Whatever
A29: Boss Smash^3 | B29: During boss levels: All heroes: +3 pips to all sides | C29: 6 | D29: Unpickable
A30: Boss Smash^99 | B30: During boss levels: All heroes: +99 pips to all sides | C30: 9 | D30: Unpickable
A31: Cataclysm | B31: At the end of the 7th turn, kill all enemies (except reinforcements) | C31: 3 | D31: Unpickable
A32: Challenge each fight | B32: Before each fight: standard challenge | C32: 2 | D32: Big Sad
A33: Crackling | B33: At the start of the 1st turn, +4 mana | C33: 6 | D33: Big Sad
A34: Cyclops.spirit | B34: All monsters: The middle hp: Stunned this turn | C34: 6 | D34: Big Sad
A35: Damaged Monsters | B35: All monsters: 1 of every 4 hp starts empty | C35: 7 | D35: Unpickable
A36: Deep Pockets | B36: All heroes: +1 item slot (max 4) | C36: 2 | D36: Unpickable
A37: Display Case | B37: If there is exactly 1 item in the inventory: All heroes: Copy all unequipped items | C37: 5 | D37: Big Sad
A38: Divine^1 | B38: All heroes: Side pips minimum 1 | C38: 2 | D38: Unpickable | E38: 5%
A39: Divine^2 | B39: All heroes: Side pips minimum 2 | C39: 8 | D39: Big Sad | E39: 5%
A40: Double Loot | B40: Before every 2nd fight: standardloot phase | C40: 8 | D40: Unpickable
A41: Essence Capture^1 | B41: All heroes: Upon death: +1 mana | C41: 3 | D41: Big Sad
A42: Essence Capture^2 | B42: All heroes: Upon death: +2 mana | C42: 7 | D42: Unpickable
A43: Essence Capture^3 | B43: All heroes: Upon death: +3 mana | C43: 10 | D43: Unpickable
A44: Essence Thief | B44: All monsters: Upon death: +1 mana | C44: 3 | D44: Big Sad | F44: Maybe with small adds
A45: Extra reroll | B45: +1 reroll | C45: 3 | D45: Slightly Happy
A46: Fizzing | B46: At the start of the first turn, +2 mana | C46: 3 | D46: Slightly Happy
A47: Free turn | B47: The 1st turn: All monsters: -1 pip to all sides | C47: 7 | D47: Unpickable
A48: Fumes | B48: All most-hp enemies: Start poisoned for 2 | C48: 5 | D48: Unpickable
A49: Greased Dice | B49: The first turn: +1 reroll During boss levels: +1 reroll | C49: 3 | D49: Slightly Sad
A50: Great Start | B50: The 1st turn: All heroes: +1 pip to all sides | C50: 7 | D50: Unpickable
A51: Growth fan | B51: Gain the items 'Seedling' (Replace the left side with '2 damage growth') and 'Glowing Egg' (Add growth to the left side) | C51: 2 | D51: Big Sad
A52: Gym | B52: +1 hp per hero level | C52: 4 | D52: Slightly Happy
A53: h.bot.Level up | B53: Level-up the bottom hero by 1 | C53: 3 | D53: Big Happy
A54: h.bot2.Level up | B54: Level-up the bottom two heroes by 1 | C54: 6 | D54: Big Happy
A55: h.bot3.Level up | B55: Level-up the bottom three heroes by 1 | C55: 9 | D55: Big Happy
A56: h.eo.Level up | B56: Level-up every other hero by 1 | C56: 9 | D56: Big Happy
... A62: Hamstring | B62: All monsters: -1 pip to the two right sides | C62: 6 | D62: Big Sad
A63: Healest | B63: All heroes: +1 pip to all heal/selfheal sides | C63: 3 | D63: Slightly Sad | E63: 10% | F63: Mostly pickable with Mystic
A64: Hero Regen^1 | B64: All heroes: Start with 1 regen | C64: 6 | D64: Big Sad
A65: Hero Regen^2 | B65: All heroes: Start with 2 regen | C65: 10 | D65: Big Sad
A66: hero.critical | B66: All heroes: Add critical to all sides | C66: 8 | D66: Unpickable
A67: hero.cruel | B67: All heroes: Add cruel to all sides | C67: 6 | D67: Big Sad
A68: hero.deathwish | B68: All heroes: Add deathwish to all sides | C68: 10 | D68: Big Sad | F68: Fast curses
A69: hero.dispel | B69: All heroes: Add dispel to all sides | C69: 4 | D69: Unpickable | F69: Actually Impossible to take. It removes your spells when you target heroes among other things
A70: hero.duel | B70: All heroes: Add duel to all sides | C70: 4 | D70: Slightly Happy | F70: Fast Curses
A71: hero.duplicate | B71: All heroes: Add duplicate to all sides | C71: 10 | D71: Unpickable | F71: Lol.
A72: hero.enduring | B72: All heroes: Add enduring to all sides | C72: 4 | D72: Unpickable
A73: hero.engage | B73: All heroes: Add engage to all sides | C73: 11 | D73: Unpickable
A74: hero.fierce | B74: All heroes: Add fierce to all sides | C74: 7 | D74: Big Sad
A75: hero.focus | B75: All heroes: Add focus to all sides | C75: 4 | D75: Slightly Happy
A76: hero.growth | B76: All heroes: Add growth to all sides | C76: 8 | D76: Unpickable
A77: hero.overdog | B77: All heroes: Add overdog to all sides | C77: 9 | D77: Unpickable
A78: hero.pair | B78: All heroes: Add pair to all sides | C78: 7 | D78: Big Happy
A79: hero.ranged | B79: All heroes: Add ranged to all sides | C79: 3 | D79: Unpickable | F79: Spiky ofc
A80: hero.reborn | B80: All heroes: Add reborn to all sides | C80: 1 | D80: Unpickable
A81: hero.rescue | B81: All heroes: Add rescue to all sides | C81: 9 | D81: Big Sad
A82: hero.selfheal | B82: All heroes: Add selfheal to all sides | C82: 7 | D82: Unpickable
A83: hero.selfshield | B83: All heroes: Add selfshield to all sides | C83: 10 | D83: Big Sad | F83: Very defensive curses
A84: hero.sixth | B84: All heroes: Add sixth to all sides | C84: 3 | D84: Big Sad
A85: hero.terminal | B85: All heroes: Add terminal to all sides | C85: 2 | D85: Unpickable
A86: hero.trio | B86: All heroes: Add trio to all sides | C86: 7 | D86: Big Sad
A87: hero.underdog | B87: All heroes: Add underdog to all sides | C87: 9 | D87: Unpickable
A88: hero.undergrowth | B88: All heroes: Add undergrowth to all sides | C88: 5 | D88: Big Sad
A89: hero.vigil | B89: All heroes: Add vigil to all sides | C89: 10 | D89: Unpickable | F89: Can play with die on your turn hero (dead crow, martyr etc)
A90: Hunt^1 | B90: All monsters: Start vulnerable for 1 | C90: 6 | D90: Big Sad
A91: Hunt^2 | B91: All monsters: Start vulnerable for 2 | C91: 11 | D91: Big Sad | F91: Add. Zombie
A92: i.[Tier 10 item] | B92: Gain the [Tier 10 item] | C92: 3 | D92: Depends :)
A93: i.[Tier 11 item] | B93: Gain the [Tier 11 item] | C93: 4 | D93: Depends :)
A94: i.[Tier 12 item] | B94: Gain the [Tier 12 item] | C94: 4 | D94: Depends :)
A95: i.[Tier 13 item] | B95: Gain the [Tier 13 item] | C95: 4 | D95: Depends :)
A96: i.[Tier 14 item] | B96: Gain the [Tier 14 item] | C96: 5 | D96: Depends :)
A97: i.[Tier 15 item] | B97: Gain the [Tier 15 item] | C97: 5 | D97: Depends :)
A98: i.[Tier 16 item] | B98: Gain the [Tier 16 item] | C98: 5 | D98: Depends :)
A99: i.[Tier 17 item] | B99: Gain the [Tier 17 item] | C99: 6 | D99: Depends :)
A100: i.[Tier 2 item] | B100: Gain the [Tier 2 item] | C100: 1 | D100: Depends :)
A101: i.[Tier 3 item] | B101: Gain the [Tier 3 item] | C101: 1 | D101: Depends :)
A102: i.[Tier 4 item] | B102: Gain the [Tier 4 item] | C102: 1 | D102: Depends :)
A103: i.[Tier 5 item] | B103: Gain the [Tier 5 item] | C103: 2 | D103: Depends :)
A104: i.[Tier 6 item] | B104: Gain the [Tier 6 item] | C104: 2 | D104: Depends :) | F104: Tier 6+ are often good depending on the item.
A105: i.[Tier 7 item] | B105: Gain the [Tier 7 item] | C105: 2 | D105: Depends :)
...

Sheet Gen. Heroes
A1: 90 total | B1: T1 Orange | C1: T1 Yellow | D1: T1 Grey | E1: T1 Red | F1: T1 Blue
A2: Basic Spell | F2: 16/30
A3: 1 dmg (1 mana) | F3: 5 | G3: 1 | H3: 1
A4: 1 dmg to all (2 mana) | F4: 1
A5: Heal+Cleanse 1 (1 mana) | F5: 1
A6: Kill an enemy 3 hp or less ranged (2 mana) | F6: 1
A7: Shield cleave 3 (3 mana) | F7: 1
A8: Dmg cleave 3 (5 mana) | F8: 1
A9: 2 dmg Cruel (2 mana) | F9: 1
A10: 2 dmg to all (4 mana) | F10: 1

Sheet 3.1 Sample done. Tierlists!
A1: 3.1: Sample done. Tierlists!
A5: After going 50W-1L in 3.0, Bookclub ended their 50 games in 3.1 with a score of 47W-3L!
A6: Time for fresh tierlists!
A7: The game definitely is harder (more balanced!) as most of the "Big Happy" curses and heroes are nerfed. But you can obviously still win a lot.
A8: We currently hold the WR with a 23 streak and as of 10 March we tied the WR again and are going to try to extend it! Update: Got the WR again with a 27 streak :D
A9: We also scheduled Tierlist streams, we invited #2 Grimmy, #3 HollowDice, #4 Benedict as well as #5 IHateBooks (Xecnar) to join us for more perspectives.
A10: Update: All tierlists done!
A11: Hero tierlist discussion (youtube) by Bookclub+Xecnar+Hollowdice
A12: Item tierlist discussion (twitch) by Bookclub
A15: The tierlists are made assuming:
A16: -Classic Unfair
A17: -Basic Team
... A25: https://docs.google.com/spreadsheets/d/1hAjtpz4afePzlzwhJCXWM629saGS8SZ2PyvNH1PP3eE

Sheet Heroes 3.0
A1: 128 normal heroes (+2 special cases)
A2: Color | B2: Tier | C2: Icon | D2: Hero | E2: HP | F2: Sides | L2: Ability | M2: Passive Ability | N2: Ranking Count | O2: Rank | P2: Note | Q2: Total Counts (excl. Greens)
F3: L | G3: M | H3: T | I3: B | J3: R | K3: RM
A4: Orange | B4: 1 | D4: Lost | E4: 3 | N4: {=INDEX('A-Z Help Sheet'!$B$3:$B$11,MATCH(O4,'A-Z Help Sheet'!$A$3:$A$11,0))} -> 1 | O4: Big Happy | Q4: Big Happy | R4: =countif($N$2:$N$110,1) -> 27
A5: Orange | B5: 1 | D5: Dabble | E5: 6 | N5: {=INDEX('A-Z Help Sheet'!$B$3:$B$11,MATCH(O5,'A-Z Help Sheet'!$A$3:$A$11,0))} -> 1 | O5: Big Happy | Q5: Slightly Happy | R5: =countif($N$2:$N$110,2) -> 25
A6: Orange | B6: 1 | D6: Thief | E6: 4 | N6: {=INDEX('A-Z Help Sheet'!$B$3:$B$11,MATCH(O6,'A-Z Help Sheet'!$A$3:$A$11,0))} -> 2 | O6: Slightly Happy | Q6: Whatever | R6: =countif($N$2:$N$110,3) -> 18
A7: Orange | B7: 1 | D7: Scoundrel | E7: 6 | N7: {=INDEX('A-Z Help Sheet'!$B$3:$B$11,MATCH(O7,'A-Z Help Sheet'!$A$3:$A$11,0))} -> 4 | O7: Slightly Sad | Q7: Slightly Sad | R7: =countif($N$2:$N$110,4) -> 20
A8: Orange | B8: 1 | D8: Clumsy | E8: 5 | N8: {=INDEX('A-Z Help Sheet'!$B$3:$B$11,MATCH(O8,'A-Z Help Sheet'!$A$3:$A$11,0))} -> 5 | O8: Big Sad | Q8: Big sad | R8: =countif($N$2:$N$110,5) -> 17
A9: Orange | B9: 2 | D9: Dabbler | E9: 9 | N9: {=INDEX('A-Z Help Sheet'!$B$3:$B$11,MATCH(O9,'A-Z Help Sheet'!$A$3:$A$11,0))} -> 1 | O9: Big Happy | P9: 9 hp lol
A10: Orange | B10: 2 | D10: Spellblade | E10: 7 | N10: {=INDEX('A-Z Help Sheet'!$B$3:$B$11,MATCH(O10,'A-Z Help Sheet'!$A$3:$A$11,0))} -> 1 | O10: Big Happy
A11: Orange | B11: 2 | D11: Juggler | E11: 7 | N11: {=INDEX('A-Z Help Sheet'!$B$3:$B$11,MATCH(O11,'A-Z Help Sheet'!$A$3:$A$11,0))} -> 2 | O11: Slightly Happy
A12: Orange | B12: 2 | D12: Ranger | E12: 7 | N12: {=INDEX('A-Z Help Sheet'!$B$3:$B$11,MATCH(O12,'A-Z Help Sheet'!$A$3:$A$11,0))} -> 2 | O12: Slightly Happy
A13: Orange | B13: 2 | D13: Rogue | E13: 7 | N13: {=INDEX('A-Z Help Sheet'!$B$3:$B$11,MATCH(O13,'A-Z Help Sheet'!$A$3:$A$11,0))} -> 4 | O13: Slightly Sad
A14: Orange | B14: 2 | D14: Trapper | E14: 8 | N14: {=INDEX('A-Z Help Sheet'!$B$3:$B$11,MATCH(O14,'A-Z Help Sheet'!$A$3:$A$11,0))} -> 4 | O14: Slightly Sad
A15: Orange | B15: 2 | D15: Ninja | E15: 6 | N15: {=INDEX('A-Z Help Sheet'!$B$3:$B$11,MATCH(O15,'A-Z Help Sheet'!$A$3:$A$11,0))} -> 4 | O15: Slightly Sad
A16: Orange | B16: 2 | D16: Gambler | E16: 7 | N16: {=INDEX('A-Z Help Sheet'!$B$3:$B$11,MATCH(O16,'A-Z Help Sheet'!$A$3:$A$11,0))} -> 5 | O16: Big Sad | P16: Need item
A17: Orange | B17: 3 | D17: Agent | E17: 9 | N17: {=INDEX('A-Z Help Sheet'!$B$3:$B$11,MATCH(O17,'A-Z Help Sheet'!$A$3:$A$11,0))} -> 1 | O17: Big Happy
A18: Orange | B18: 3 | D18: Fencer | E18: 9 | N18: {=INDEX('A-Z Help Sheet'!$B$3:$B$11,MATCH(O18,'A-Z Help Sheet'!$A$3:$A$11,0))} -> 1 | O18: Big Happy
A19: Orange | B19: 3 | D19: Assassin | E19: 9 | N19: {=INDEX('A-Z Help Sheet'!$B$3:$B$11,MATCH(O19,'A-Z Help Sheet'!$A$3:$A$11,0))} -> 2 | O19: Slightly Happy
A20: Orange | B20: 3 | D20: Venom | E20: 8 | N20: {=INDEX('A-Z Help Sheet'!$B$3:$B$11,MATCH(O20,'A-Z Help Sheet'!$A$3:$A$11,0))} -> 2 | O20: Slightly Happy
A21: Orange | B21: 3 | D21: Dabblest | E21: 9 | N21: {=INDEX('A-Z Help Sheet'!$B$3:$B$11,MATCH(O21,'A-Z Help Sheet'!$A$3:$A$11,0))} -> 3 | O21: Whatever
A22: Orange | B22: 3 | D22: Roulette | E22: 8 | N22: {=INDEX('A-Z Help Sheet'!$B$3:$B$11,MATCH(O22,'A-Z Help Sheet'!$A$3:$A$11,0))} -> 3 | O22: Whatever | P22: Unpickable without left replacer. Cannot Random at T3 with Roulette in pool
A23: Orange | B23: 3 | D23: Dancer | E23: 8 | N23: {=INDEX('A-Z Help Sheet'!$B$3:$B$11,MATCH(O23,'A-Z Help Sheet'!$A$3:$A$11,0))} -> 4 | O23: Slightly Sad | P23: Has top dodge for the hand
A24: Orange | B24: 3 | D24: Sharpshot | E24: 8 | N24: {=INDEX('A-Z Help Sheet'!$B$3:$B$11,MATCH(O24,'A-Z Help Sheet'!$A$3:$A$11,0))} -> 4 | O24: Slightly Sad
A25: Orange | B25: 3 | D25: Ludus | E25: 6 | N25: {=INDEX('A-Z Help Sheet'!$B$3:$B$11,MATCH(O25,'A-Z Help Sheet'!$A$3:$A$11,0))} -> 5 | O25: Big Sad
A26: Yellow | B26: 1 | D26: Brigand | E26: 5 | N26: {=INDEX('A-Z Help Sheet'!$B$3:$B$11,MATCH(O26,'A-Z Help Sheet'!$A$3:$A$11,0))} -> 1 | O26: Big Happy
A27: Yellow | B27: 1 | D27: Fighter | E27: 5 | N27: {=INDEX('A-Z Help Sheet'!$B$3:$B$11,MATCH(O27,'A-Z Help Sheet'!$A$3:$A$11,0))} -> 2 | O27: Slightly Happy
A28: Yellow | B28: 1 | D28: Hoarder | E28: 6 | N28: {=INDEX('A-Z Help Sheet'!$B$3:$B$11,MATCH(O28,'A-Z Help Sheet'!$A$3:$A$11,0))} -> 2 | O28: Slightly Happy
A29: Yellow | B29: 1 | D29: Ruffian | E29: 4 | N29: {=INDEX('A-Z Help Sheet'!$B$3:$B$11,MATCH(O29,'A-Z Help Sheet'!$A$3:$A$11,0))} -> 4 | O29: Slightly Sad
A30: Yellow | B30: 1 | D30: Lazy | E30: 5 | M30: rolling blanks lol | N30: {=INDEX('A-Z Help Sheet'!$B$3:$B$11,MATCH(O30,'A-Z Help Sheet'!$A$3:$A$11,0))} -> 5 | O30: Big Sad
A31: Yellow | B31: 2 | D31: Scrapper | E31: 8 | N31: {=INDEX('A-Z Help Sheet'!$B$3:$B$11,MATCH(O31,'A-Z Help Sheet'!$A$3:$A$11,0))} -> 1 | O31: Big Happy
A32: Yellow | B32: 2 | D32: Berserker | E32: 8 | N32: {=INDEX('A-Z Help Sheet'!$B$3:$B$11,MATCH(O32,'A-Z Help Sheet'!$A$3:$A$11,0))} -> 2 | O32: Slightly Happy
A33: Yellow | B33: 2 | D33: Gladiator | E33: 7 | N33: {=INDEX('A-Z Help Sheet'!$B$3:$B$11,MATCH(O33,'A-Z Help Sheet'!$A$3:$A$11,0))} -> 2 | O33: Slightly Happy
A34: Yellow | B34: 2 | D34: Soldier | E34: 7 | N34: {=INDEX('A-Z Help Sheet'!$B$3:$B$11,MATCH(O34,'A-Z Help Sheet'!$A$3:$A$11,0))} -> 2 | O34: Slightly Happy
A35: Yellow | B35: 2 | D35: Brute | E35: 8 | N35: {=INDEX('A-Z Help Sheet'!$B$3:$B$11,MATCH(O35,'A-Z Help Sheet'!$A$3:$A$11,0))} -> 3 | O35: Whatever
A36: Yellow | B36: 2 | D36: Sinew | E36: 8 | N36: {=INDEX('A-Z Help Sheet'!$B$3:$B$11,MATCH(O36,'A-Z Help Sheet'!$A$3:$A$11,0))} -> 3 | O36: Whatever
A37: Yellow | B37: 2 | D37: Collector | E37: 8 | N37: {=INDEX('A-Z Help Sheet'!$B$3:$B$11,MATCH(O37,'A-Z Help Sheet'!$A$3:$A$11,0))} -> 5 | O37: Big Sad
A38: Yellow | B38: 2 | D38: Whirl | E38: 7 | N38: {=INDEX('A-Z Help Sheet'!$B$3:$B$11,MATCH(O38,'A-Z Help Sheet'!$A$3:$A$11,0))} -> 5 | O38: Big Sad
